Workbook
Name SlicerCache_Table_1_Col_1: #N/A

Sheet Registros
A1: Fecha | B1: Pedido | C1: Identificacion | D1: PrimerNombre | E1: SegundoNombre | F1: PrimerApellido | G1: SegundoApellido | H1: Telefono | I1: FormaPago | J1: Destinatario | K1: Barrio | L1: Direccion | M1: telefonoDestino | N1: Fecha de Entrega | O1: Hora de Entrega | P1: Cantidad | Q1: Producto | R1: Precio | S1: Iva | T1: Domicilio | U1: Total | V1: Mensaje | W1: Estado | X1: Cuenta | Y1: Firmado | Z1: NombreFirma | AA1: Celular Flora | AB1: Observaciones | AC1: FacturaURL | AD1: LastModified
A2: 46067.326 | B2: 9999 | C2: 1045674390 | D2: Juan B | F2: RAPPI | H2: 572412082838 | J2: Juan B RAPPI | K2: Entrega En Tienda | L2: Entrega En Tienda - Entrega En Tienda | M2: 2412082838 | N2: 46067 | O2: 0.375 | P2: 1 | Q2: 1× Mini Heart Rosas | R2: 130000 | S2: 0 | T2: 0 | U2: 130000 | W2: Aprobado | X2: Rappi | AA2: Rappi | AB2: ID de la orden 2428717905 | AC2: =HYPERLINK("https://drive.google.com/file/d/1qmL0wbaGgLHYPFfVrBd2RR-qXIP2pBVc/view?usp=drivesdk", "Abrir_Factura") -> Abrir_Factura | AD2: 46067.328
A3: 46065.739 | B3: 20000 | C3: 1045745776 | D3: jose | F3: maestre | H3: 57573002603555 | J3: recoge en tienda | K3: Entrega En Tienda | L3: Entrega En Tienda - Entrega En Tienda | N3: 46065 | O3: 0 | P3: 1 | Q3: 1× Arreglo Personalizado | R3: 0 | S3: 0 | T3: 0 | U3: 0 | W3: Aprobado | X3: Cuentas Por Cobrar | AA3: Samsung | AB3: 1 rosa roja arreglada | AC3: =HYPERLINK("", "") | AD3: 46065.74
A4: 45980.425 | B4: 89417 | C4: 1045674063 | D4: Rafael | F4: Campis | H4: 573005140423 | J4: Entrega en tienda | K4: Entrega En Tienda | L4: Entrega en tienda - Entrega en tienda | M4: 3005140423 | N4: 45980 | O4: 0.51041667 | P4: 1 | Q4: 1× Flora Box Mediana 24 Rosas | R4: 200000 | S4: 0 | T4: 0 | U4: 200000 | W4: Aprobado | X4: Tarjeta Debito | Y4: Firmado | Z4: Tu Esposo e Hijos | AA4: Samsung | AC4: =HYPERLINK("https://drive.google.com/file/d/1Q6HcOe5lc0OK6aSMgU05LI07r-6tGCWZ/view?usp=drivesdk","Abrir_Factura") -> Abrir_Factura
A5: 45980.432 | B5: 89420 | C5: 1143144308 | D5: Jhonatan | F5: Montes | H5: 573007775110 | J5: Loraine Cárdenas | L5: Cra 48 # 70- 38 Puerta 10 clinica general del norte - Oficina | M5: 3003790967 | N5: 45980 | O5: 0.50416667 | P5: 1 | Q5: 1× Corazón Mini Surtido | R5: 120000 | S5: 0 | T5: 12000 | U5: 132000 | W5: Aprobado | X5: wompi | Y5: Firmado | Z5: Con cariño, J.M | AA5: Samsung | AC5: =HYPERLINK("https://drive.google.com/file/d/1zN5xtCMPCwxq8fnC_PznxBou3zBerbsX/view?usp=drivesdk","Abrir_Factura") -> Abrir_Factura
A6: 45980.457 | B6: 89421 | C6: 32735597 | D6: Livia | F6: Marino | H6: 573145091990 | J6: María Gabriela Marino | K6: Villa Campestre | L6: Cra 51B #135 -90 edificio villa campestre apartamentos torre 3 apto1401 - Edificio | M6: 3218539173 | N6: 45980 | O6: 0.54166667 | P6: 1 | Q6: 1× Mini Box Surtida | R6: 70000 | S6: 0 | T6: 17000 | U6: 87000 | V6: Felices 15 años Gaby. Te queremos mucho Tía Livi y Caro | W6: Aprobado | X6: Transferencia 4966 | Y6: Firmado | Z6: Felices 15 años Gaby. Te queremos mucho Con cariño Tía Livi y Caro | AA6: Huawei | AC6: =HYPERLINK("https://drive.google.com/file/d/1KU2prUvP8dEaUqtzaTtjwR1yexNQ9IT2/view?usp=drivesdk","Abrir_Factura") -> Abrir_Factura
A7: 45980.346 | B7: 89424 | C7: 1001822182 | D7: Juan | F7: Doncel | H7: 573008608059 | J7: Juan Doncel | K7: Altos de Riomar | L7: Cra 64 #98-90 casa 58 - Conjunto | M7: 3008608059 | N7: 45982 | O7: 0.43125 | P7: 1 | Q7: 1× Bouquet 6 Rosas Rojas | R7: 70000 | S7: 0 | T7: 10000 | U7: 80000 | W7: Aprobado | X7: Transferencia 4966 | Y7: Firmado | Z7: Juan Doncel | AA7: Samsung | AC7: =HYPERLINK("https://drive.google.com/file/d/1imeBapqJ5ny9GZqKzW69TeypXPi6rjI8/view?usp=drivesdk", "Abrir_Factura") -> Abrir_Factura
A8: 45980.593 | B8: 89435 | C8: 60397017 | D8: Paola | F8: Villamizar | H8: 573012340135 | J8: Isabella chaya | K8: Buenavista | L8: Calle 104 No 53 49 apto 902 - Casa | M8: 3012340135 | N8: 45981 | O8: 0.47916667 | P8: 1 | Q8: 1× Flora Box Redonda Lirio | R8: 350000 | S8: 0 | T8: 10000 | U8: 360000 | V8: No importa que tan lejos te lleven tus sueños de regreso siempre te estará esperando con todo el amor tu lugar seguro! | W8: Aprobado | X8: Transferencia 5431 | Y8: Firmado | AA8: Huawei | AC8: =HYPERLINK("https://drive.google.com/file/d/1JOWE6-h1OTfY4o5VSvwcoeevAVbqqzTV/view?usp=drivesdk","Abrir_Factura") -> Abrir_Factura
A9: 45981.549 | B9: 89439 | C9: 72278234 | D9: Juan | F9: Franco | H9: 573004867681 | J9: maria helena cure | K9: Las Delicias | L9: crarrera 44 70 107 - CECAC - Oficina | M9: 3004867681 | N9: 45982 | O9: 0.375 | P9: 1 | Q9: 1× Canasto Mediano Sweet | R9: 150000 | S9: 0 | T9: 13000 | U9: 163000 | V9: Ninguno Solo Firma | W9: Aprobado | X9: Tarjeta Debito | Y9: Firmado | Z9: Juan Franco, German Quiroz y Roberto Arenas | AA9: Huawei | AC9: =HYPERLINK("https://drive.google.com/file/d/1QG_abSdDR9pXi9vpYkZ5C5ymd8hE6ySA/view?usp=drivesdk","Abrir_Factura") -> Abrir_Factura
A10: 45981.543 | B10: 89440 | C10: 1139614281 | D10: Amanda | F10: Gonzalez | H10: 573003582590 | J10: Leonor Molinares | K10: Altos de Riomar | L10: Apto 202 - Edificio | M10: 3157412179 | N10: 45983 | O10: 0.33333333 | P10: 1 | Q10: 1× Canasto Lavanda | R10: 220000 | S10: 0 | T10: 10000 | U10: 230000 | V10: Feliz cumpleaños a la mejor mamá del mundo!! Te amo hoy y siempre. Disfruta tu día | W10: Aprobado | X10: Transferencia Bold | Y10: Firmado | Z10: Amanda | AA10: Samsung | AC10: =HYPERLINK("https://drive.google.com/file/d/1qk0cMmZLcnRbNeTRiCoQo8cqvdR5ODD5/view?usp=drivesdk","Abrir_Factura") -> Abrir_Factura
A11: 45981.638 | B11: 89464 | C11: 1085165600 | D11: Camila | F11: Colina Torres | H11: 573023562503 | J11: Camila Colina Torres | K11: Riomar | L11: Edificio Madrid, apto 6A - Edificio | M11: 3023562503 | N11: 45982 | O11: 0.33333333 | P11: 1 | Q11: 1× Mini Box Surtida | R11: 70000 | S11: 0 | T11: 0 | U11: 70000 | V11: Fabii, estamos muy orgullosas de ti!! Sigue brillando de esa manera tan hermosa, este es el primero de muchos logros para ser una doctora increíble!! Pd: recibe soon tu bono para ir a barre | W11: Aprobado | X11: Transferencia 5431 | Y11: Firmado | Z11: Con amor, Cami, hilla y Vale | AA11: Huawei | AC11: =HYPERLINK("https://drive.google.com/file/d/1xE9QAVo9UPYlWbUz-ZRnrk1l0MIID7xT/view?usp=drivesdk","Abrir_Factura") -> Abrir_Factura
A12: 45982.331 | B12: 89486 | C12: 1140892942 | D12: Fabio | F12: Barrera | H12: 573014656802 | J12: Maria Alejandra Rodriguez | K12: san vicente | L12: cra 55 # 80-285 Castellamare - Edificio | M12: 3014656802 | N12: 45983 | O12: 0.42708333 | P12: 1 | Q12: 1× Flora Box Mediana Aire | R12: 260000 | S12: 0 | T12: 6000 | U12: 266000 | V12: “Feliz navidad y prospero año nuevo. God bless America” | W12: Aprobado | X12: Transferencia Bold | Y12: Firmado | Z12: Fabio y Fendi | AA12: Samsung | AC12: =HYPERLINK("https://drive.google.com/file/d/1zkKAOl95l3oxp3Pm8x46EpnlOftDFTlN/view?usp=drivesdk","Abrir_Factura") -> Abrir_Factura
A13: 45982.331 | B13: 89488 | C13: 7083919972 | D13: Alejandra | F13: Fernandez | H13: 000000 | J13: recoge en tienda | K13: Entrega En Tienda | L13: cra. 52 # 84 - 64 | M13: flora | N13: 45982 | O13: 0.39390046 | P13: 1 | Q13: bouquet surtido | R13: 120000 | T13: 0 | U13: 120000 | W13: Aprobado | X13: Tarjeta Debito | AA13: Samsung | AC13: =HYPERLINK("https://drive.google.com/file/d/1cEUz--eJetbaruc7KpqAaq1TZiyPjLRe/view?usp=drivesdk","Abrir_Factura") -> Abrir_Factura
A14: 45982.425 | B14: 89491 | C14: 1001912485 | D14: Estefani | F14: Acosta | H14: 573045359056 | J14: Cristina duncan | K14: El Prado | L14: Cra58#66-81 apto 202 edificio prado señorial - Edificio | M14: 315 6947216 | N14: 45982 | O14: 0.58333333 | P14: 1 | Q14: 1× Canasto Mediano Sweet | R14: 150000 | S14: 0 | T14: 12000 | U14: 162000 | V14: Feliz día Dra Cristina! Gracias por todo💗 | W14: Aprobado | X14: Transferencia 5431 | Y14: Firmado | Z14: Con cariño, Stefany Acosta. | AA14: Samsung | AC14: =HYPERLINK("https://drive.google.com/file/d/1G3TdmmltYkdcNkWWYssb0Zl7KfTf_PKB/view?usp=drivesdk","Abrir_Factura") -> Abrir_Factura
A15: 45982.442 | B15: 89492 | C15: 1010094699 | D15: Maria Alejandra | F15: Rondon | H15: 573008326249 | J15: Mercedes Uribe | K15: Altos de Riomar | L15: Cra 58#86-85 / Edificio Masseba / apto 203 - Edificio | M15: 3174273757 | N15: 45982 | O15: 0.58333333 | P15: 1 | Q15: 1× Marquito Orquidea | R15: 140000 | S15: 0 | T15: 10000 | U15: 150000 | V15: Merce, te mandamos estas flores con todo nuestro cariño. Eres la más fuerte y nos llena de emocion verte salir adelante después de tantos días en la clínica. Nos alegra un montón saber que ya estás en casa y recuperándote. Ojalá cada día te sientas un poquito mejor y tengas mucha energía. Te queremos muchísimo! | W15: Aprobado | X15: Transferencia 5431 | Y15: Firmado | Z15: Andres y Lale ❤️ | AA15: Samsung | AC15: =HYPERLINK("https://drive.google.com/file/d/1m_-0GFq_FvrrLPsgg2K4_GHu9YAC7tXM/view?usp=drivesdk","Abrir_Factura") -> Abrir_Factura
A16: 45982.451 | B16: 89495 | C16: 72260542 | D16: RONIL | F16: BERDUGO CABRALES | H16: 573165266199 | J16: VALENTINA LOPEZ | K16: Puerto Colombia | L16: Calle 2c # 1 - 21 piso 1 Barrio El Ancla Puerto Colombia - Casa | M16: 3158908107 | N16: 45982 | O16: 0.54166667 | P16: 1 | Q16: 1× Flora Box Mediana Aire | R16: 260000 | S16: 0 | U16: 260000 | V16: Recibe estas flores como un abrazo lleno de orgullo y cariño en este día tan especial. ¡Felicitaciones por tu grado! Este logro es fruto de tu esfuerzo, tu disciplina y tu determinación, te deseamos un camino lleno de nuevas oportunidades, aprendizajes y éxitos. Que este sea solo el comienzo de todo lo grande que estás destinada a lograr. | W16: Aprobado | X16: Transferencia 5431 | Y16: Firmado | Z16: Con cariño, De: Jesús y Ronil | AA16: Huawei | AC16: =HYPERLINK("https://drive.google.com/file/d/1vceMbwsfA7iPkG8BZh6A5JW_EzOEF9vh/view?usp=drivesdk","Abrir_Factura") -> Abrir_Factura
A17: 45982.468 | B17: 89496 | C17: 22587251 | D17: Milena | F17: Escalante De la Cruz | H17: 573026413479 | J17: Vanesa vasco | K17: Miramar | L17: Calle 106 transversal 43-137 edificio Génova marval (Miramar ) al lado del centro comercial Miramar plaza - Edificio | M17: 3207505858 | N17: 45982 | O17: 0.55208333 | P17: 1 | Q17: 1× Corazón Mediano Surtido | R17: 200000 | S17: 0 | T17: 12000 | U17: 212000 | V17: Que bonito es compartir mi vida contigo, qué bonito es compartir risas y coleccionar experiencias a diario, qué bonito es estar con alguien que aunque no te entienda te acepte pero sobre todo te apoye, que bonito es transformar todo lo que nos hace diferente. Que bonito fue el universo al cruzarte en mi camino flaquita🐥❤️✨ I love you | W17: Aprobado | X17: Transferencia 5431 | Y17: Firmado | Z17: Milena Escalante | AA17: Huawei | AC17: =HYPERLINK("https://drive.google.com/file/d/1_Yqu76zdRdRFO82Wex3BeyII0l_UwTbr/view?usp=drivesdk","Abrir_Factura") -> Abrir_Factura
A18: 45982.608 | B18: 89519 | C18: 3232712 | D18: Mariela | F18: Lugo | H18: 573008943808 | J18: Mariela | K18: Villa Country | L18: Cl. 77b # 57 - 103 - Oficina | M18: 3008943808 | N18: 45982 | O18: 0.67916667 | P18: 1 | Q18: 1× Mini Box Claveles | R18: 70000 | S18: 0 | T18: 8000 | U18: 78000 | W18: Aprobado | X18: Transferencia 5431 | Y18: Firmado | Z18: Feliz cumpleaños para mi primera princesa, hoy cumples 12 años es un paso hermoso hacia nuevas aventuras. Que cada día recuerdes lo valiosa, fuerte y especial que eres. Siempre estaré a tu lado para apoyarte y animarte en todo lo que quieras lograr en tu vida . Te amo con todo mi corazón. att: tu Papa | AA18: Samsung | AC18: =HYPERLINK("https://drive.google.com/file/d/1oRFB1tZr_F4EBUKidTRHupRrlbfO0NZy/view?usp=drivesdk","Abrir_Factura") -> Abrir_Factura
A19: 45983.442 | B19: 89520 | C19: 1045730564 | D19: Natalia | F19: Davila | H19: 573145381698 | J19: Sheryn Saab | K19: El Golf | L19: Cra 56 # 79-342 apto 1102 Edificio San Angelo - Edificio | M19: 3135724647 | N19: 45983 | O19: 0.52569444 | P19: 1 | Q19: 1× Marquito Orquidea | R19: 140000 | S19: 0 | T19: 8000 | U19: 148000 | V19: Siempre juntas en todos los momentos importantes de nuestras vidas. Te adoro!! | W19: Aprobado | X19: Transferencia 5431 | Y19: Firmado | Z19: With love, Nat | AA19: Samsung | AC19: =HYPERLINK("https://drive.google.com/file/d/1uolEE4B83xMrWfpQLP7Fponycx3YOhNe/view?usp=drivesdk","Abrir_Factura") -> Abrir_Factura
A20: 45983.451 | B20: 89521 | C20: 1234097133 | D20: Cristhian | F20: De Marchena Rueda | H20: 573209485304 | J20: Cristhian De Marchena Rueda | K20: Santa Ana | L20: Cra 66 #58-69 - Casa | M20: 3103610622 | N20: 45983 | O20: 0.53680556 | P20: 1 | Q20: 1× Flora Box Redonda 24 Rosas de Jardín | R20: 300000 | S20: 0 | T20: 13000 | U20: 313000 | V20: Feliz cumpleaños | W20: Aprobado | X20: Transferencia 5431 | Y20: Firmado | Z20: Con cariño, tu hijo | AA20: Samsung | AC20: =HYPERLINK("https://drive.google.com/file/d/13GCSg1K0PWp5Zn3nfmnoM3eZvYNsVtrh/view?usp=drivesdk","Abrir_Factura") -> Abrir_Factura
A21: 45983.464 | B21: 89524 | C21: 1047435678 | D21: Carlos Javier | F21: Agamez Martínez | H21: 573003794847 | J21: Evelis Carreño | K21: El Parque | L21: Carrera 41 G # 47 - 18 - Casa | M21: 3003927152 | N21: 45984 | O21: 0.4375 | P21: 1 | Q21: 1× Bouquet 12 Rosas Rojas | R21: 100000 | S21: 0 | T21: 30000 | U21: 130000 | V21: Feliz cumpleaños profe, que Dios y la virgen de Fátima te Bendigan, te den muchos años de vida, salud, prosperidad, sabiduría y paciencia, para poder llegar a cada corazón de esos niños que atiendes todos los días y colocar un granito de amor en ellos para que no se sientan solos. Disfruta mucho tú día | W21: Aprobado | X21: Transferencia 4038 | Y21: Firmado | Z21: C.J.A.M | AA21: Huawei | AC21: =HYPERLINK("https://drive.google.com/file/d/1p6eTW6iNvlPr1SXObNYJDYlSZOIP9Lwy/view?usp=drivesdk","Abrir_Factura") -> Abrir_Factura
A22: 45985.453 | B22: 89576 | C22: 1234088982 | D22: Camilo | F22: Echeverri | H22: 573183514405 | J22: Carolina Segebre Abudinen | K22: Altos del Prado | L22: cra 56 Numero 79 - 342 - Edificio | M22: 3183514405 | N22: 45985 | O22: 0.48333333 | P22: 1 | Q22: 1× Flora Box Mediana Topiario | R22: 200000 | S22: 0 | T22: 8000 | U22: 208000 | V22: Muchos éxitos en tu nuevo Proyecto Mi Amor, Atentamente Camilo | W22: Aprobado | X22: Transferencia 5431 | Y22: Firmado | Z22: Camilo Echeverry | AA22: Samsung | AC22: =HYPERLINK("https://drive.google.com/file/d/1dcNInDdlULATd4QMliLUobpA26YHwr_T/view?usp=drivesdk","Abrir_Factura") -> Abrir_Factura
A23: 45985.453 | B23: 89577 | C23: 1129583788 | D23: maría | F23: araque | H23: 5712082705109 | J23: ruth del castillo | K23: El Silencio | L23: clle 71#27-56 - Casa | M23: 3168273246 | N23: 45985 | O23: 0.50972222 | P23: 1 | Q23: 1× Bouquet 6 Rosas Rojas | R23: 70000 | S23: 0 | T23: 15000 | U23: 85000 | V23: Ánimo Mamá ! No estes triste todo va a estar bien, mejórate Pronto. Estamos contigo Te Amamos mucho. De: Jake y Emma Lou | W23: Aprobado | X23: Efectivo | Y23: Firmado | Z23: De: Jake y Emma Lou | AA23: Huawei | AB23: contraentrega-efectivo | AC23: =HYPERLINK("https://drive.google.com/file/d/1rMoXOkBjsn9zyBCqRzNkFis3FMVuhoaO/view?usp=drivesdk","Abrir_Factura") -> Abrir_Factura
A24: 45985.453 | B24: 89578 | C24: 22493961 | D24: Marjorie | F24: Caballero Mendez | H24: 3006517761 | J24: Aida Palmet | K24: Villa Country | L24: Universidad Autónoma del Caribe | M24: 3208485913 | N24: 45985 | O24: 0.43204861 | P24: 1 | Q24: arreglo virgen | R24: 120000 | T24: 8000 | U24: 128000 | W24: Aprobado | X24: Transferencia Jaque | AA24: Samsung | AC24: =HYPERLINK("https://drive.google.com/file/d/11xfeJr3Y9-1YVkjdRifGX7cWsb59kdCn/view?usp=drivesdk","Abrir_Factura") -> Abrir_Factura
A25: 45985.462 | B25: 89581 | C25: 1048933991 | D25: ANDRES | F25: SOLANA | H25: 573006418722 | J25: SOFIA SOLANA | K25: Andalucía | L25: CL 85A 71A 89 - Casa | M25: 3005477557 | N25: 45985 | O25: 0.54513889 | P25: 1 | Q25: 1× Bouquet Gerbera | R25: 150000 | S25: 0 | T25: 10000 | U25: 160000 | V25: Mi amor, Hoy llega una nueva etapa en tu vida, y quiero que sepas que estamos contigo en cada paso. Hoy no solo hay un cambio en tu cuerpo, tambien un crecimiento hermoso, natural y poderoso. Estamos muy orgullosos de ti. Quiero que recuerdes siempre que sigues siendo nuestra niña: dulce, única, fuerte y especial. Nada de esto cambia quién eres; simplemente estás creciendo, floreciendo y descubriendo nuevas partes de ti misma. Y en ese camino, nunca estarás sola. Gracias por confiar en nosotros por permitirme acompañarte y por ser exactamente como eres. Cuando tengas dudas, emociones nuevas o simplemente quieras un abrazo, aquí estaremos para apoyarte, escucharte y cuidarte. Te amamos con todo mi corazón, hoy y siempre. Bienvenida a esta nueva etapa, nuestra niña hermosa. 💗 Con cariño papá y mamá. | W25: Aprobado | X25: Transferencia 4038 | Y25: Firmado | Z25: Papá y Mamá | AA25: Samsung | AB25: caja de ferrero | AC25: =HYPERLINK("https://drive.google.com/file/d/1Wmhkb61QGmThO8RT6-7R71b_6-0wR8_9/view?usp=drivesdk","Abrir_Factura") -> Abrir_Factura
A26: 45985.453 | B26: 89582 | C26: 79105208 | D26: Héctor | F26: Briceño Martínez | H26: 573017262076 | J26: Héctor Briceño Martínez | K26: Entrega En Tienda | L26: Entrega En Tienda - Entrega En Tienda | M26: 3017262076 | N26: 45987 | O26: 0.3125 | P26: 1 | Q26: 1× Flora Box Mediana 24 Rosas | R26: 200000 | S26: 0 | T26: 0 | U26: 200000 | W26: Aprobado | X26: Transferencia 5431 | Y26: Firmado | AA26: Huawei | AC26: =HYPERLINK("https://drive.google.com/file/d/1DJz8Ovx7vJW21P6_j_wHZJVvAbfwdrZc/view?usp=drivesdk","Abrir_Factura") -> Abrir_Factura
A27: 45985.505 | B27: 89583 | C27: 66870320 | D27: alejandra | F27: martinez | H27: 5713475364999 | J27: pedro pallares villarreal | K27: puerto colombia bajo orion | L27: bajo ostion,riviera del mar - Edificio | M27: 3245894951 | N27: 45985 | O27: 0.58888889 | P27: 1 | Q27: 1× Canasto Tierra | R27: 300000 | S27: 0 | T27: 80000 | U27: 380000 | W27: Aprobado | X27: Transferencia 5431 | Y27: Firmado | AA27: Samsung | AC27: =HYPERLINK("https://drive.google.com/file/d/1hHeV0P1MeKc0s6395ixVd76keDgg3xAw/view?usp=drivesdk","Abrir_Factura") -> Abrir_Factura
A28: 45985.54 | B28: 89585 | C28: 0 | D28: RAPPI | F28: Gabriela Galvan | H28: 5730111886453 | J28: gabriela galvan | K28: Entrega En Tienda | L28: Entrega En Tienda - Entrega En Tienda | M28: 30111886453 | N28: 45985 | O28: 0.62361111 | P28: 1 | Q28: 1× Bouquet 6 Rosas Rojas | R28: 70000 | S28: 0 | T28: 0 | U28: 70000 | W28: Aprobado | X28: Efectivo | Y28: Firmado | AA28: Samsung | AB28: rappi | AC28: =HYPERLINK("https://drive.google.com/file/d/1YeuemtjmN3KQZo2BgmVyj7UxFBWU85SR/view?usp=drivesdk","Abrir_Factura") -> Abrir_Factura
A29: 45985.533 | B29: 89586 | C29: 1042849973 | D29: Luis | F29: Consuegra | H29: 573106333999 | J29: Bianca Morales | K29: Ciudad Jardín Modelo | L29: Calle 80#42D1-30 - Casa | M29: 300 8001119 | N29: 45986 | O29: 0.66666667 | P29: 1 | Q29: 1× Bouquet 12 Rosas Rojas | R29: 100000 | S29: 0 | T29: 11000 | U29: 111000 | V29: Gracias por ser la mejor mamá para chiquito, ya quiero volver para que nos reunamos cómo la familia que somos ¡Los amo infinito, princesa! | W29: Aprobado | X29: Transferencia 4966 | Y29: Firmado | Z29: El amor de tu vida | AA29: Huawei | AB29: rosas rosadas | AC29: =HYPERLINK("https://drive.google.com/file/d/13RUZj9I_wS-hPmjdj9xlS4glCK03y9sV/view?usp=drivesdk","Abrir_Factura") -> Abrir_Factura
A30: 45985.598 | B30: 89590 | C30: 0 | D30: didier | F30: rodríguez | H30: 573154015161 | J30: maría nancy | K30: Altos de Riomar | L30: clle 93#42c-123 apto 1202 - Edificio | M30: 3157212330 | N30: 45985 | O30: 0.68263889 | P30: 1 | Q30: 1× Flora Box Surtida Rosas y Orquídeas | R30: 380000 | S30: 0 | T30: 10000 | U30: 390000 | W30: Aprobado | X30: Transferencia 5431 | Y30: Firmado | AA30: Samsung | AC30: =HYPERLINK("https://drive.google.com/file/d/1aPoylWWVWf5qXU1qDFNpy7Tm263YDSoO/view?usp=drivesdk","Abrir_Factura") -> Abrir_Factura
A31: 45985.587 | B31: 89591 | C31: 11240000815 | D31: Matriacanela | F31: Ojeda Villalobos | H31: 573505316838 | J31: María canela | K31: Altos de Riomar | L31: Cl. 98 #65A-54, Riomar, Barranquilla, Atlántico, Colombia - Casa | M31: 3505316838 | N31: 45987 | O31: 0.70833333 | P31: 1 | Q31: 1× Canasto Mediano Sweet | R31: 150000 | S31: 0 | T31: 10000 | U31: 160000 | V31: Hoy celebramos tu vida y lo increíble que eres. Queremos desearte un año lleno de alegría, salud, oportunidades bonitas y mucho amor. Eres una persona especial, con un corazón enorme, y mereces que todo lo bueno llegue a tu vida. Gracias por tu cariño, por tu energía tan linda y por siempre sumar. Aquí estamos para ti, hoy y siempre, con todo el amor y el apoyo del mundo. | W31: Aprobado | X31: Transferencia 5431 | Y31: Firmado | Z31: Emmanuel y canela | AA31: Samsung | AC31: =HYPERLINK("https://drive.google.com/file/d/1CgRZh5d9Cz4PSE2g53g5EbTbIzaJy10c/view?usp=drivesdk","Abrir_Factura") -> Abrir_Factura
A32: 45985.545 | B32: 89592 | C32: 1140888238 | D32: Kevin | F32: Salazar | H32: 573017262076 | J32: Kelly Sierra | K32: Villa Carolina | L32: Cr 74 # 91-120 - casa 37 - Casa | M32: 3008531481 | N32: 45987 | O32: 0.33333333 | P32: 1 | Q32: 1× Flora Box Mediana Sembrado | R32: 170000 | S32: 0 | T32: 10000 | U32: 180000 | V32: Por amarte y cuidarte Dios me quiere más. Feliz cumpleaños madre, Te amo | W32: Aprobado | X32: Transferencia 5431 | Y32: Firmado | Z32: Tu hijo | AA32: Huawei | AC32: =HYPERLINK("https://drive.google.com/file/d/1qjOjeMEq-dcRKZs1i7ayVHmG1i1qS0gv/view?usp=drivesdk","Abrir_Factura") -> Abrir_Factura
A33: 45985.603 | B33: 89593 | C33: 72357914 | D33: German | F33: Blanco | H33: 573017366162 | J33: Rochy Poveda | K33: Altos del Prado | L33: Carrera 52 # 82 -253 riu52 apt 1601 - Edificio | M33: 304 3045673 | N33: 45986 | O33: 0.45833333 | P33: 1 | Q33: 1× Flora Box Romantic Flores | R33: 190000 | S33: 0 | T33: 8000 | U33: 198000 | V33: Por muchos años de vida juntos. | W33: Aprobado | X33: Transferencia 4038 | Y33: Firmado | Z33: G.B | AA33: Samsung | AC33: =HYPERLINK("https://drive.google.com/file/d/1_gvJfscim8jqdwa1JBpi45Xlp1hCIMJ-/view?usp=drivesdk","Abrir_Factura") -> Abrir_Factura
A34: 45985.61 | B34: 89595 | C34: 1000596064 | D34: Ana Maria | F34: Cantor Daza | H34: 33666513994 | J34: Mary Luz Daza Bedoya | K34: Alameda del Río | L34: Calle 112 #43-185 apt 701 torre 4 - Edificio | M34: 33666513994 | N34: 45986 | O34: 0.3125 | P34: 1 | Q34: 1× Flora Box Mediana Tulipanes | 1× Canasto Mediano Sweet | R34: 500000 | S34: 0 | T34: 17000 | U34: 517000 | V34: Mamá, Felices 50 primaveras, me encantaría estar ahí contigo, pero aun en la distancia nuestro amor siempre será más grande. Estoy orgullosa de la mujer que eres, y solo puedo desearte que toda la luz que das siempre vuelva a tu camino. Te amo. | W34: Aprobado | X34: Transferencia 5431 | Y34: Firmado | Z34: Tu Hijita | AA34: Huawei | AC34: =HYPERLINK("https://drive.google.com/file/d/1LKP3EIegU1W4rql_LdIuDrgySi8abKqL/view?usp=drivesdk","Abrir_Factura") -> Abrir_Factura
A35: 45985.629 | B35: 89596 | C35: 1140902669 | D35: Mateo | F35: Tamara Diago | H35: 573163111155 | J35: Sophia Gomez Melo | K35: Villa Country | L35: Cra 57#78-67 Apto 102 - Edificio | M35: 3145737004 | N35: 45985 | O35: 0.7125 | P35: 1 | Q35: 1× Flora Box Mediana 24 Rosas | R35: 200000 | S35: 0 | T35: 8000 | U35: 208000 | V35: Mi amor, feliz cumpleaños, por miles de años más a tu lado, gracias por ser tan cariñosa, especial y tan incondicional. Siempre te mereces lo mejor, le doy gracias a Dios por ponerte en mi vida, te amo. | W35: Aprobado | X35: Transferencia Bold | Y35: Firmado | Z35: Mateo Támara Diago | AA35: Samsung | AC35: =HYPERLINK("https://drive.google.com/file/d/1uo1OaQOagqzpenPGAQpunkr43JRC7_I4/view?usp=drivesdk","Abrir_Factura") -> Abrir_Factura
A36: 45985.607 | B36: 89599 | C36: 1140820157 | D36: juan manuel | F36: serna | H36: 16469443749 | J36: Juan Manuel Serna | K36: El Golf | L36: Carrera 59 81 149 apto 302 - Casa | M36: 16469443749 | N36: 45985 | O36: 0.69236111 | P36: 1 | Q36: 1× Flora Box Romantic Flores | R36: 190000 | S36: 0 | T36: 8000 | U36: 198000 | V36: Hermosa, feliz 8 años de amor, de trabajar juntos nuestro camino al cielo. Te amo y por muchos años mas juntos | W36: Aprobado | X36: Transferencia Bold | Y36: Firmado | Z36: Chicho | AA36: Samsung | AC36: =HYPERLINK("https://drive.google.com/file/d/1qXmNrRtHaSf4YvNHA76W6ZrYoZI7gWmJ/view?usp=drivesdk","Abrir_Factura") -> Abrir_Factura
A37: 45985.534 | B37: 89600 | C37: 1042849973 | D37: Luis | F37: Consuegra | H37: 573106333999 | J37: Bianca Morales | K37: Ciudad Jardín Modelo | L37: Calle 80#42D1-30 - Casa | M37: 300 8001119 | N37: 45986 | O37: 0.66666667 | P37: 1 | Q37: 1× Bouquet 12 Rosas Rojas | R37: 100000 | S37: 0 | T37: 11000 | U37: 111000 | V37: Gracias por ser la mejor mamá para chiquito, ya quiero volver para que nos reunamos cómo la familia que somos ¡Los amo infinito, princesa! | W37: Aprobado | X37: Transferencia 5431 | Y37: Firmado | Z37: El amor de tu vida | AA37: Huawei | AB37: rosas rosadas | AC37: =HYPERLINK("https://drive.google.com/file/d/1dTdiX9JRBtYjep8XpSZvXwS6oxHDU9Aw/view?usp=drivesdk","Abrir_Factura") -> Abrir_Factura
A38: 45985.891 | B38: 89601 | C38: 1140838766 | D38: Carolina | F38: Zuluaga Gomez | H38: 573007895738 | J38: Nubia Gómez | K38: Altos del Prado | L38: Cra 52 # 82 - 161 Apto 4B - Ed. Asturias - Edificio | M38: 300 8509958 | N38: 45986 | O38: 0.375 | P38: 1 | Q38: 1× Flora Box Mediana Aire | R38: 260000 | S38: 0 | T38: 8000 | U38: 268000 | V38: ¡Feliz Aniversario mi amor! Son 36 años juntos, gracias por tu amor incondicional. Tu amor por siempre. | W38: Aprobado | X38: Cuentas Por Cobrar | Y38: Firmado | Z38: Rodrigo. | AA38: Samsung | AC38: =HYPERLINK("https://drive.google.com/file/d/1jS7ICHjK3Ja9Sni_4aId8l_gmK3m0wxR/view?usp=drivesdk","Abrir_Factura") -> Abrir_Factura
A39: 45985.732 | B39: 89602 | C39: 1002211373 | D39: Daniel | F39: Alvarado | H39: 16562620163 | J39: Kattia Amashta | K39: Altos del Prado | L39: Cra 52 #82-162 apto 7B - Edificio | M39: 3188833856 | N39: 45986 | O39: 0.375 | P39: 1 | Q39: 1× Guacal Surtido Lirio | R39: 160000 | S39: 0 | T39: 8000 | U39: 168000 | V39: Feliz cumpleaños a la Wonderwoman de mi vida, te amo mami! ❤️ | W39: Aprobado | X39: Transferencia 4966 | Y39: Firmado | Z39: Danny | AA39: Huawei | AC39: =HYPERLINK("https://drive.google.com/file/d/1d_GwwPImE8x23RYE5um8UpZHt6z0QyAU/view?usp=drivesdk","Abrir_Factura") -> Abrir_Factura
A40: 45985.637 | B40: 89603 | C40: 1140841620 | D40: Daniela | F40: Osorio | H40: 573188062999 | J40: Mabel Salebe | K40: Altos del Prado | L40: Carrera 49C # 80 - 255. Edificio Las Vistas. Apartamento 1B - Edificio | M40: 3168303473 | N40: 45986 | O40: 0.41666667 | P40: 1 | Q40: flora box 50 rosas rojas | R40: 400000 | S40: 0 | T40: 8000 | U40: 408000 | V40: Feliz cumpleaños mamita. Te amamos con todo nuestro 🩷 Pronto nos vemos | W40: Aprobado | X40: Transferencia 5431 | Y40: Firmado | Z40: Dani y Juli | AA40: Samsung | AC40: =HYPERLINK("https://drive.google.com/file/d/1tMa5dPjluk8kZrE1XyAxIt43SJ-nlO03/view?usp=drivesdk","Abrir_Factura") -> Abrir_Factura
A41: 45986.393 | B41: 89612 | C41: 1140899289 | D41: Bryan | F41: Contreras | H41: 573017188503 | J41: Viviana Rebolledo | K41: Villa Santos | L41: Cl 96a 42 52 - parque 96 casa 2 - Casa | M41: 3017188503 | N41: 45986 | O41: 0.66666667 | P41: 1 | Q41: 1× Mini Box Orquidea | R41: 80000 | S41: 0 | T41: 10000 | U41: 90000 | W41: Aprobado | X41: Transferencia 5431 | Y41: Anónimo | AA41: Samsung | AC41: =HYPERLINK("https://drive.google.com/file/d/1qayxzrV_sfkPDjBx7vFePqkP6UqTQguF/view?usp=drivesdk","Abrir_Factura") -> Abrir_Factura
A42: 45986.41 | B42: 89613 | C42: 1010150521 | D42: Nicolle | F42: Morales | H42: 573013625860 | J42: Karoll Mantilla | K42: San Isidro | L42: Cra 30 #58-83 Timbre 2 Santo Domingo Sabio - Edificio | M42: 3115353719 | N42: 45986 | O42: 0.52083333 | P42: 1 | Q42: 1× Mini Box Surtida | R42: 70000 | S42: 0 | T42: 15000 | U42: 85000 | V42: Karoll linda, Gracias por ser esa luz tan bonita en nuestras vidas. Te celebramos, te queremos y estamos felices de tenerte siempre. Con amor, Nicolle, David y Alejandra 💐❤️ | W42: Aprobado | X42: Transferencia 5431 | Y42: Firmado | Z42: Tus mejores amigos | AA42: Huawei | AC42: =HYPERLINK("https://drive.google.com/file/d/1og5udDEBHgP7cbWiPagTWH54C8YAzQUf/view?usp=drivesdk","Abrir_Factura") -> Abrir_Factura
A43: 45985.818 | B43: 89614 | C43: 1129565524 | D43: Juliana | F43: Villegas | H43: 573207092819 | J43: Maria del Socorro Bermeo Navia | K43: El Prado | L43: Calle 76 No 54 -231 - Oficina | M43: 3207092819 | N43: 45986 | O43: 0.4375 | P43: 1 | Q43: 1× Marquito Surtido Pastel | R43: 120000 | S43: 0 | T43: 12000 | U43: 132000 | V43: Mary, En este día tan especial, quiero desearte un cumpleaños lleno de luz, alegría y que todo lo bonito que tú le regalas al mundo regrese a ti en bendición y mucho amor. Que venga un año lleno de felicidad, | W43: Aprobado | X43: Transferencia Bold | Y43: Firmado | Z43: Con Cariño, July Villegas & Familia. | AA43: Samsung | AC43: =HYPERLINK("https://drive.google.com/file/d/1Erq1WiveqCI3PaiUFc5l_lRZjJ2nz4VJ/view?usp=drivesdk","Abrir_Factura") -> Abrir_Factura
A44: 45986.389 | B44: 89615 | C44: 1043669351 | D44: Juan Esteban | F44: Adarraga Fontalvo | H44: 573167502204 | J44: Daniela Lanao | K44: miramar | L44: Calle 97 # 42F - 43, Conjunto residencial mirador del mar 2, apartamento 1008, torre 2 - Edificio | M44: 3004449637 | N44: 45993 | O44: 0.41666667 | P44: 1 | Q44: 1× Flora Box Mediana Pastel | R44: 180000 | S44: 0 | T44: 12000 | U44: 192000 | W44: Aprobado | X44: Transferencia 5431 | Y44: Firmado | Z44: Con amor, Juan | AA44: Samsung | AC44: =HYPERLINK("https://drive.google.com/file/d/1bDmatbBVKSZyD0pTUF4qjBvThDW_0Zq7/view?usp=drivesdk","Abrir_Factura") -> Abrir_Factura
A45: 45986.525 | B45: 89628 | C45: 1140847215 | D45: Andrea | F45: Consuegra | H45: 3008374077 | J45: andrea consuegra | K45: Entrega En Tienda | L45: cra 52#82-253 apto 904 - Casa | M45: 3008374077 | N45: 45986 | O45: 0.60972222 | P45: 1 | Q45: 1× Virgen Guadalupe o Milagrosa Pequeña | R45: 120000 | S45: 0 | U45: 120000 | W45: Aprobado | X45: Transferencia Jaque | Y45: Firmado | AA45: Samsung | AC45: =HYPERLINK("https://drive.google.com/file/d/1r2A9_lpsdHUWEmXEuyRavsvuplwg7wo9/view?usp=drivesdk","Abrir_Factura") -> Abrir_Factura
A46: 45986.535 | B46: 89629 | C46: 580881 | D46: Nicholas | F46: Oganesoff | H46: 13016610096 | J46: Nicolas | K46: Riomar | L46: Edificio Epic 91 Cra. 64c ##86171 Riomar - Edificio | M46: 13016610096 | N46: 45988 | O46: 0.35416667 | P46: 1 | Q46: 1× Flora Box Grande Topiario Rosas | 1× Topper Happy Birthday | R46: 570000 | S46: 0 | T46: 10000 | U46: 580000 | V46: Happy Birthday Princess!!!! | W46: Aprobado | X46: Transferencia Bold | Y46: Firmado | Z46: Your Husband | AA46: Samsung | AC46: =HYPERLINK("https://drive.google.com/file/d/1MSfmft_RTKxj_aR41j3C9WJAXqCe2PWd/view?usp=drivesdk","Abrir_Factura") -> Abrir_Factura
A47: 45986.411 | B47: 89630 | C47: 80420054 | D47: Fabio | F47: Mendez | H47: 573112029123 | J47: Ana Milena Aponte | K47: san vicente | L47: Cra 53 N 82-242 Apto 801 Edificio San Marino - Edificio | M47: 3216433061 | N47: 45986 | O47: 0.75 | P47: 1 | Q47: 1× Bouquet 36 Rosas Rojas | R47: 294000 | S47: 0 | T47: 6000 | U47: 300000 | V47: Solo espero q poder alegrar tu vida y tus días!!!! Ánimo! | W47: Aprobado | X47: Transferencia 5431 | Y47: Firmado | Z47: Fabio | AA47: Samsung | AC47: =HYPERLINK("https://drive.google.com/file/d/12vTXMYKWPyYlvgDgk0cTM4eJqlGp50pB/view?usp=drivesdk","Abrir_Factura") -> Abrir_Factura
A48: 45986.624 | B48: 89631 | C48: 1010077411 | D48: Rafael | F48: Socarrasa | H48: #ERROR! | J48: Rafael | K48: Bethania | L48: Carrera 39#75b-38 edificio Lisboa, apto 605 - Edificio | M48: ‪+57 323 4095885‬ | N48: 45986 | O48: 0.70694444 | P48: 1 | Q48: 1× Bouquet 6 Rosas Rojas | R48: 70000 | S48: 0 | T48: 11000 | U48: 81000 | V48: Eres una persona maravillosa, me haces muy feliz amor de mi vida! TE amo ❤️ | W48: Aprobado | X48: Transferencia 4966 | Y48: Firmado | Z48: De: Gus Gus para : Mi Puchi Puchi | AA48: Huawei | AC48: =HYPERLINK("https://drive.google.com/file/d/1a0L_K-jmT_50wk2Xe5bRvUINZ2Erjzuz/view?usp=drivesdk","Abrir_Factura") -> Abrir_Factura
A49: 45986.663 | B49: 89632 | C49: 32723192 | D49: flor | F49: carreño | H49: 573176609335 | J49: milena | K49: El Golf | L49: cra 58#81-110 apto 14 - Edificio | M49: 317 6609335 | N49: 45986 | O49: 0.74791667 | P49: 1 | Q49: 1× Virgen Guadalupe o Milagrosa Grande | R49: 200000 | S49: 0 | T49: 8000 | U49: 208000 | W49: Aprobado | X49: Transferencia Jaque | Y49: Firmado | AA49: Samsung | AC49: =HYPERLINK("https://drive.google.com/file/d/1Q_f4iOQAy1iJ3M8xS47vhaHyNgE1HQvX/view?usp=drivesdk","Abrir_Factura") -> Abrir_Factura
A50: 45986.703 | B50: 89633 | C50: 1045752007 | D50: fabian | F50: padilla | H50: 573022812819 | J50: isabella huertas | K50: Villa Carolina | L50: clle 91#70-64 - Casa | M50: 3113106759 | N50: 45986 | O50: 0.78819444 | P50: 1 | Q50: 1× Bouquet 6 Rosas Rojas | R50: 70000 | S50: 0 | T50: 10000 | U50: 80000 | W50: Aprobado | X50: Transferencia 5431 | Y50: Firmado | AA50: Huawei | AC50: =HYPERLINK("https://drive.google.com/file/d/1uuRLheIsPhD7sPgI0j-95rSNlXNgE6_o/view?usp=drivesdk","Abrir_Factura") -> Abrir_Factura
A51: 45986.705 | B51: 89634 | C51: 1140856569 | D51: daniela | F51: acosta | H51: 57226133817 | J51: kelly sierra | K51: Altos de Riomar | L51: cra 74#91-120 casa 37 - Casa | M51: 3008531481 | N51: 45986 | O51: 0.79097222 | P51: 1 | Q51: 1× Flora Gift Box JP | R51: 260000 | S51: 0 | T51: 10000 | U51: 270000 | W51: Aprobado | X51: Transferencia 4966 | Y51: Firmado | AA51: Samsung | AC51: =HYPERLINK("https://drive.google.com/file/d/1UaIu7t43uf5-WlUu7MsY0QUMBxkfJxkn/view?usp=drivesdk","Abrir_Factura") -> Abrir_Factura
A52: 45987.315 | B52: 89638 | C52: 22736562 | D52: Lina | F52: castro | H52: 573017156935 | J52: Antonela Rodriguez | K52: san vicente | L52: Cra. 64 #84-174, pizzeria L'America - Edificio | M52: 3138692496 | N52: 45987 | O52: 0.4 | P52: 1 | Q52: 1× Mini Box Hortensias y Mini Rosa | R52: 70000 | S52: 0 | T52: 6000 | U52: 76000 | W52: Aprobado | X52: Transferencia 4966 | Y52: Firmado | AA52: Huawei | AC52: =HYPERLINK("https://drive.google.com/file/d/1t--nKRW2oaUJ7i78I1WFvuYdfXigzloV/view?usp=drivesdk","Abrir_Factura") -> Abrir_Factura
A53: 45987.362 | B53: 89639 | C53: 1079914726 | D53: Jaider | F53: Suárez polo | H53: 573104214627 | J53: alejandra julio | K53: Alameda del Río | L53: Calle 117 42b 74 t3 apto 704 Conjunto Paloma Alameda del Rio - Casa | M53: 3104214627 | N53: 45987 | O53: 0.44513889 | P53: 1 | Q53: 1× Bouquet 50 Rosas Rojas | R53: 300000 | S53: 0 | T53: 17000 | U53: 317000 | W53: Aprobado | X53: Transferencia 4966 | Y53: Firmado | AA53: Huawei | AC53: =HYPERLINK("https://drive.google.com/file/d/1r80m_yN2D6Mre1POsmrXGp7Gf1yeNBEV/view?usp=drivesdk","Abrir_Factura") -> Abrir_Factura
A54: 45987.389 | B54: 89640 | C54: 1102882652 | D54: Elmer | F54: Cure | H54: 573008593756 | J54: En tienda | K54: Entrega En Tienda | L54: Entrega En Tienda - Entrega En Tienda | M54: 3008593756 | N54: 45988 | O54: 0.47916667 | P54: 1 | Q54: 1× Bouquet 24 Rosas Rojas | R54: 153000 | S54: 0 | T54: 0 | U54: 153000 | V54: Feliz cumpleaños amor de mi vida entera, te amo con todo mi corazón ❤️ | W54: Aprobado | X54: Cuentas Por Cobrar | Y54: Firmado | Z54: Feliz cumpleaños amor de mi vida entera, te amo con todo mi corazón ❤️ | AA54: Samsung | AC54: =HYPERLINK("https://drive.google.com/file/d/15sjSTbP7SepLak-mcCaFtc6n-VT1-t9L/view?usp=drivesdk","Abrir_Factura") -> Abrir_Factura
A55: 45987.391 | B55: 89641 | C55: 1042351150 | D55: Evelyng | F55: Torres | H55: 573159282463 | J55: Claudia Díaz | K55: Villa Country | L55: Carrera 55 72 109 centro ejecutivo 2 piso 7 - Edificio | M55: 3113547794 | N55: 45987 | O55: 0.47430556 | P55: 1 | Q55: 1× Mini Box Orquidea | R55: 80000 | S55: 0 | T55: 8000 | U55: 88000 | V55: Clau, quiero recordarte lo mucho que significas para mí. Que estas flores simbolicen el amor y la fuerza que llevas dentro. Como ellas, que siempre florezcas incluso en tiempos difíciles, encontrando en cada reto una oportunidad para brillar. Que la luz y la paz te acompañen siempre, llenando tus días de alegría. Gracias por ser una amiga tan única. Te deseo un año lleno de bendiciones y milagros para tu corazón. ¡Feliz cumpleaños! Te quiero. | W55: Aprobado | X55: Transferencia 4966 | Y55: Firmado | Z55: Eve T. | AA55: Samsung | AC55: =HYPERLINK("https://drive.google.com/file/d/1MvucbSSYL0h_nCmQbzlgMWNdqdCgtJPz/view?usp=drivesdk","Abrir_Factura") -> Abrir_Factura
A56: 45987.388 | B56: 89643 | C56: 1140848061 | D56: Dayana | F56: Rios | H56: 573147754370 | J56: Jenny Manrique | K56: Riomar | L56: Carrera 65 # 85-135 casa 3 - Conjunto | M56: 3157076259 | N56: 45987 | O56: 0.46666667 | P56: 1 | Q56: 1× Mini Box Hortensias y Mini Rosa | R56: 70000 | S56: 0 | T56: 10000 | U56: 80000 | V56: Hola Jenny! Te deseo pronta recuperación. Te envío un abrazo y mucha energia positiva, aquí estoy para lo que necesites… Espero verte de vuelta pronto! | W56: Aprobado | X56: Transferencia 4966 | Y56: Firmado | Z56: Con cariño, Sandra Arango | AA56: Samsung | AC56: =HYPERLINK("https://drive.google.com/file/d/1PeRc7q0-wKflEmdQFokIAqpGQctpR2Kl/view?usp=drivesdk","Abrir_Factura") -> Abrir_Factura
A57: 45987.451 | B57: 89645 | C57: 72297514 | D57: Angela | F57: Acosta | H57: 573017486941 | J57: Carrera 38 calle 74 edificio Sies 123 CAD | K57: Las Mercedes | L57: Oficina del modelo - Edificio | M57: 3005936006 | N57: 45987 | O57: 0.625 | P57: 1 | Q57: 1× Bouquet 12 Rosas Rojas | R57: 100000 | S57: 0 | T57: 12000 | U57: 112000 | V57: Recuerda que son etapas ! | W57: Aprobado | X57: Transferencia 4966 | Y57: Anónimo | AA57: Huawei | AC57: =HYPERLINK("https://drive.google.com/file/d/1R9l3APmZRHP4ncpmkR0sdus0f0bzTLdf/view?usp=drivesdk","Abrir_Factura") -> Abrir_Factura
A58: 45987.466 | B58: 89647 | C58: 1140885990 | D58: Ricardo | F58: Torres | H58: 573015853230 | J58: Ricardo | K58: soledad | L58: Calle 30 #39-6 - Casa | M58: 3015853230 | N58: 45987 | O58: 0.625 | P58: 1 | Q58: 1× Bouquet 12 Rosas Rojas | R58: 100000 | S58: 0 | T58: 30000 | U58: 130000 | V58: ¡Feliz Cumpleaños! | W58: Aprobado | X58: Transferencia 4966 | Y58: Anónimo | AA58: Samsung | AC58: =HYPERLINK("https://drive.google.com/file/d/1yITNndTl7ljW1u3FKI9s1_p2m0t-mnML/view?usp=drivesdk","Abrir_Factura") -> Abrir_Factura
A59: 45987.478 | B59: 89648 | C59: 1020740415 | D59: James | F59: Bello Castillo | H59: 573008439408 | J59: Melody Torres | K59: Villa Country | L59: Cra 57 # 77 - 53 - Edificio | M59: 3008439408 | N59: 45989 | O59: 0.33333333 | P59: 1 | Q59: 1× Flora Box Surtida Rosas y Orquídeas | R59: 380000 | S59: 0 | T59: 8000 | U59: 388000 | V59: Gracias por existir, mi amor. Eres la mejor parte de mis días. | W59: Aprobado | X59: Transferencia 4966 | Y59: Firmado | Z59: Con amor, James | AA59: Huawei | AC59: =HYPERLINK("https://drive.google.com/file/d/1g8pjexJg6gW2eriNoy9KtNlN_y-WDlEQ/view?usp=drivesdk","Abrir_Factura") -> Abrir_Factura
A60: 45987.525 | B60: 89649 | C60: 12221969151 | D60: elisa | F60: lópez | H60: 572402646180 | J60: elisa lópez | K60: Entrega En Tienda | L60: Entrega En Tienda - Entrega En Tienda | M60: 2402646180 | N60: 45987 | O60: 0.61041667 | P60: 1 | Q60: 1× Mini Box Orquidea | R60: 80000 | S60: 0 | T60: 0 | U60: 80000 | W60: Aprobado | X60: Cuentas Por Cobrar | Y60: Firmado | AA60: Samsung | AB60: rappi | AC60: =HYPERLINK("https://drive.google.com/file/d/1OMkdGrSpZEQbZiu42BWVQhttX6_2Zdjm/view?usp=drivesdk","Abrir_Factura") -> Abrir_Factura
A61: 45987.57 | B61: 89650 | C61: 1120750688 | D61: Maria Jose | F61: Lopez | H61: 573012153820 | J61: María montes | K61: El Carmén | L61: Cra 20A #60 - 52 - Casa | M61: 3135944149 | N61: 45987 | O61: 0.65486111 | P61: 1 | Q61: 1× Flora Mini Plus Box Redonda | R61: 130000 | S61: 0 | T61: 16000 | U61: 146000 | V61: Mami Yo estoy muy orgulloso de ti | W61: Aprobado | X61: Transferencia 4966 | Y61: Firmado | Z61: GEEM | AA61: Samsung | AC61: =HYPERLINK("https://drive.google.com/file/d/1QtZ0XByhyUlEKYuDEWnR-8VW4RHriN9t/view?usp=drivesdk","Abrir_Factura") -> Abrir_Factura
A62: 45987.545 | B62: 89651 | C62: 1123732178 | D62: ALEJANDRA | F62: DUARTE | H62: 5731269606612 | J62: Valentina Ramirez | K62: Riomar | L62: calle 90 # 58-51 apto 1202 - Edificio | M62: 3003053176 | N62: 45987 | O62: 0.62569444 | P62: 1 | Q62: 1xCanasto Lavanda | R62: 238000 | S62: 0 | T62: 10000 | U62: 248000 | V62: Bienvenida, Amelia. Qué emoción tan grande tenerte por fin con nosotros. Tu llegada es una bendición que llena de luz y alegría a toda la familia, y nuestros corazones no pueden estar más felices. Ricardo y Valentina, muchísimas felicitaciones. Verlos recibir a Amelia y comenzar esta nueva etapa me conmueve profundamente. Ricardo, verte convertirme en papá me llena de orgullo, y Valentina, gracias por traer a esta pequeña tan especial a nuestras vidas. Amelia, preciosa, deseo que tu vida esté siempre rodeada de amor, ternura y bienestar. Que crezcas sanita, feliz y acompañada de muchas risas, abrazos y momentos inolvidables. Ojalá podamos estar cerquita para acompañarte en cada descubrimiento, y que junto a Alejandro puedan compartir juegos, travesuras y esa complicidad tan bonita que solo los primos saben construir. Que Dios y la Virgen te cuiden y te acompañen siempre ✨ Y quiero que sepan que su tía Ale está llena de ilusión, con el corazón desbordado de amor por ti, Amelia. Tu llegada nos ha hecho la vida aún más bonita. Con todo nuestro cariño, Alejandro, Alejandra y Jaime | W62: Aprobado | X62: Transferencia 4966 | Y62: Firmado | Z62: Familia Baute Duarte | AA62: Huawei | AC62: =HYPERLINK("https://drive.google.com/file/d/1Fd4g8MUSBezfB7TqpSd_9Ez7wIEPgyYM/view?usp=drivesdk","Abrir_Factura") -> Abrir_Factura
A63: 45987.631 | B63: 89652 | C63: 1001997753 | D63: valentino | F63: goméz | H63: 573128996844 | J63: valentino goméz | K63: Entrega En Tienda | L63: Entrega En Tienda - Entrega En Tienda | M63: 3128996844 | N63: 45987 | O63: 0.71666667 | P63: 1 | Q63: 1× Flora Box Solitario Rosa | R63: 60000 | S63: 0 | T63: 0 | U63: 60000 | W63: Aprobado | X63: Tarjeta Debito | Y63: Firmado | AA63: Samsung | AC63: =HYPERLINK("https://drive.google.com/file/d/1vBgZ10_50crl_h_IIOnugVFhqoSAXhpN/view?usp=drivesdk","Abrir_Factura") -> Abrir_Factura
A64: 45987.635 | B64: 89653 | C64: 0 | D64: vanina | F64: zambrano | H64: 573226450395 | J64: vanina zambrano | K64: Bethania | L64: cra 42a2#87b-08 - Casa | M64: 3226450395 | N64: 45987 | O64: 0.72013889 | P64: 1 | Q64: 1× Bouquet 12 Rosas Rojas | R64: 100000 | S64: 0 | T64: 11000 | U64: 111000 | W64: Aprobado | X64: Transferencia 4966 | Y64: Firmado | AA64: Huawei | AC64: =HYPERLINK("https://drive.google.com/file/d/1niJ_fMVvxJNceZp22swFZeAUZcY_1KaX/view?usp=drivesdk","Abrir_Factura") -> Abrir_Factura
A65: 45987.51 | B65: 89654 | C65: 1002439554 | D65: Douglas | F65: Camargo | H65: 573147511194 | J65: Douglas Camargo | K65: Entrega En Tienda | L65: Entrega En Tienda - Entrega En Tienda | M65: 3147511194 | N65: 45987 | O65: 0.625 | P65: 1 | Q65: 1× Flora Box Romantic Flores | R65: 190000 | S65: 0 | T65: 0 | U65: 190000 | V65: Feliz cumpleaños mi amor, gracias por siempre estar, TE AMO💕 | W65: Aprobado | X65: Transferencia Bold | Y65: Firmado | Z65: De: Douglas Camargo | AA65: Huawei | AC65: =HYPERLINK("https://drive.google.com/file/d/1kfc_sh6rFThB_5o4kIBh4DFzW6YcSBpR/view?usp=drivesdk","Abrir_Factura") -> Abrir_Factura
A66: 45987.657 | B66: 89655 | C66: 1234094577 | D66: andrea | F66: lopez | H66: 5734624368707 | J66: maria camila chavez | K66: Olaya | L66: cra 27b#68b-61 - Casa | M66: 3186013144 | N66: 45987 | O66: 0.74097222 | P66: 1 | Q66: 1× Marquito Surtido Pastel | R66: 120000 | S66: 0 | T66: 15000 | U66: 135000 | W66: Aprobado | X66: Transferencia 4038 | Y66: Firmado | AA66: Huawei | AC66: =HYPERLINK("https://drive.google.com/file/d/17TekeX_8slCu2msFrErTkaxBkinglIJz/view?usp=drivesdk","Abrir_Factura") -> Abrir_Factura
A67: 45987.668 | B67: 89656 | C67: 1065617402 | D67: deckson | F67: romero | H67: 573233030894 | J67: deckson romero | K67: El Prado | L67: cra 54#70-115 - Casa | M67: 3233030894 | N67: 45987 | O67: 0.75347222 | P67: 1 | Q67: 1× Bouquet 6 Rosas Rojas | R67: 70000 | S67: 0 | T67: 12000 | U67: 82000 | W67: Aprobado | X67: Efectivo | Y67: Firmado | AA67: Samsung | AC67: =HYPERLINK("https://drive.google.com/file/d/1dcOGe6DyM-LosU_4u7brTyCeG5ggdp0z/view?usp=drivesdk","Abrir_Factura") -> Abrir_Factura
A68: 45987.712 | B68: 89657 | C68: 80240210 | D68: Joel | F68: Rodriguez | H68: 573165292287 | J68: Joel Rodriguez | K68: Buenavista | L68: Calle 99 #58-99 torre 1 apto 1204 - Casa | M68: 3165292287 | N68: 45987 | O68: 0.79861111 | P68: 1 | Q68: 1× Canasto 24 Rosas + Orquideas | R68: 320000 | S68: 0 | T68: 10000 | U68: 330000 | V68: Te amamos | W68: Aprobado | X68: Transferencia Bold | Y68: Firmado | Z68: Isco y Joel | AA68: Samsung | AC68: =HYPERLINK("https://drive.google.com/file/d/1-PaH4bwvumALI8dcTYFoRr8r0TdXi67k/view?usp=drivesdk","Abrir_Factura") -> Abrir_Factura
A69: 45988.319 | B69: 89658 | C69: 1143142098 | D69: Loraine | F69: Julio Solano | H69: 573013535388 | J69: Ana Solano Escorcia | K69: Las Nieves | L69: Calle 17 # 17b -25 - Casa | M69: #ERROR! | N69: 45992 | O69: 0.93888889 | P69: 1 | Q69: 1× Flora Mini Plus Box Redonda | R69: 130000 | S69: 0 | T69: 20000 | U69: 150000 | V69: En este dia tan especial, queremos desearte un feliz cumpleaños! Que Dios siga llenando tu vida de momentos felices... | W69: Aprobado | X69: Transferencia 5431 | Y69: Firmado | Z69: Harold, Marjorie, Timothy y Kathrina | AA69: Huawei | AC69: =HYPERLINK("https://drive.google.com/file/d/11V8DLMy10_NVUGwJwfsNemZTO_WepDEo/view?usp=drivesdk","Abrir_Factura") -> Abrir_Factura
A70: 45988.353 | B70: 89659 | C70: 1192767057 | D70: Juan Pablo | F70: Gómez Moros | H70: 573104363236 | J70: Juan Pablo Gomez | K70: Villa Santos | L70: calle 104#51B-154 - Casa | M70: 3104363236 | N70: 45988 | O70: 0.43611111 | P70: 1 | Q70: 1× Mini Box Orquidea | R70: 80000 | S70: 0 | T70: 10000 | U70: 90000 | V70: Bienvenida pook | W70: Aprobado | X70: Transferencia 5431 | Y70: Firmado | Z70: Con cariño, pook | AA70: Huawei | AC70: =HYPERLINK("https://drive.google.com/file/d/1Hf3AnJtl8ETq6gVRHQxh-wAzTU6oJy1U/view?usp=drivesdk","Abrir_Factura") -> Abrir_Factura
A71: 45988.393 | B71: 89681 | C71: 1234092314 | D71: Steven Javier | F71: Duran Sandoval | H71: 573117074781 | J71: Andrea González | K71: El Prado | L71: Cra 52 #70-155 - Oficina | M71: 3007010583 | N71: 45988 | O71: 0.47222222 | P71: 1 | Q71: 1× Bouquet 6 Rosas Rojas | R71: 70000 | S71: 0 | T71: 12000 | U71: 82000 | V71: En la vida hay errores que se pueden pagar caros, pero aún así más caro sería no intentar arreglarlos. Estás flores son un diminutivo para lo hermosa mujer que eres tú, ni querida niña. | W71: Aprobado | X71: Transferencia 4038 | Y71: Firmado | Z71: Ste. | AA71: Samsung | AC71: =HYPERLINK("https://drive.google.com/file/d/16CKavTy2D6vaE6xSZCxR9jXHZsQriGSs/view?usp=drivesdk","Abrir_Factura") -> Abrir_Factura
A72: 45988.383 | B72: 89682 | C72: 1121555531 | D72: Valeria | F72: Amaya Montero | H72: 573164502773 | J72: Margarita de Montero | K72: Villa Campestre | L72: Calle 2A #20-61 - Conjunto | M72: 3164502773 | N72: 45988 | O72: 0.47916667 | P72: 1 | Q72: 1× Mini Box Surtida | R72: 70000 | S72: 0 | T72: 17000 | U72: 87000 | V72: Feliz cumpleaños, abuelita🩷🌸 Hoy quiero agradecerte por todo el amor que me has dado desde que soy una niña. Tú, que siempre sabías cómo hacerme reír, cómo tranquilizarme con solo una mirada y cómo convertir cualquier tarde en un recuerdo bonito. Gracias por las veces que te sentaste conmigo a hacer tareas, por tu paciencia infinita y por esa ternura que solo tú sabes dar. Sé que los años han traído cambios, pero mi amor por ti sigue intacto, firme, igual que tu fuerza. A veces siento que ahora es mi turno de cuidarte como tú me cuidaste siempre, y lo hago con todo el corazón porque eres una de las personas más importantes de mi vida. Te deseo un cumpleaños lleno de paz, de momentos suaves, y de todo el cariño que mereces. Gracias por existir, abuelita. Te amo más de lo que mis palabras pueden explicar. | W72: Aprobado | X72: Transferencia 4966 | Y72: Firmado | Z72: Con mucho cariño, tu nieta favorita Valeria | AA72: Samsung | AC72: =HYPERLINK("https://drive.google.com/file/d/1mwjbQkhQmDg1arMNyvpD38SfnIoLxhGr/view?usp=drivesdk","Abrir_Factura") -> Abrir_Factura
A73: 45988.401 | B73: 89684 | C73: 44154964 | D73: Karla | F73: Castillo | H73: =17728993732 -> 17728993732 | J73: Karla castilo | K73: soledad | L73: Calle 42 #2604 arboleda , soledad - Casa | M73: 573046525981 | N73: 45989 | O73: 0.45833333 | P73: 1 | Q73: 1× Bouquet 6 Rosas Rojas | R73: 70000 | S73: 0 | T73: 30000 | U73: 100000 | V73: Felicitaciones por tu grado ( congratulations) we love you sweetheart. MAMA Y RAFI | W73: Aprobado | X73: Transferencia Bold | Y73: Firmado | Z73: RAFI | AA73: Samsung | AC73: =HYPERLINK("https://drive.google.com/file/d/12uH0D1U4bggh5_2v_EUOFK5Lon3HQKT-/view?usp=drivesdk","Abrir_Factura") -> Abrir_Factura
A74: 45988.402 | B74: 89685 | C74: 1007016681 | D74: Paulina | F74: Dangond | H74: 573105204973 | J74: Marianella Maal | K74: Altos del Prado | L74: Cra 55#79-64 - Casa | M74: 3103608136 | N74: 45988 | O74: 0.4875 | P74: 1 | Q74: 1× Mini Box Hortensias y Mini Rosa | R74: 70000 | S74: 0 | T74: 8000 | U74: 78000 | V74: Feliz Cumpleaños Mami! Que cumplas mil más, te quiero infinito. - Pau | W74: Aprobado | X74: Transferencia 5431 | Y74: Firmado | Z74: Pau | AA74: Huawei | AB74: 17862477283 | AC74: =HYPERLINK("https://drive.google.com/file/d/18TN7qrRm8ZzXNrxblPjg79buvB5gMiHS/view?usp=drivesdk", "Abrir_Factura") -> Abrir_Factura
A75: 45988.422 | B75: 89686 | C75: 1003000035 | D75: Maria Jose | F75: Romero | H75: 573054888516 | J75: Yulimar Coronell | K75: Alameda del Río | L75: Ruiseñor 1 - Conjunto | M75: 305 2134848 | N75: 45988 | O75: 0.49652778 | P75: 1 | Q75: 1× Mini Box Hortensias y Mini Rosa | R75: 70000 | S75: 0 | T75: 17000 | U75: 87000 | W75: Aprobado | X75: Transferencia 5431 | Y75: Firmado | Z75: Eres una persona maravillosa: auténtica, leal y de corazón lindo. Gracias por ser una amiga que suma y que hace todo más fácil. Que este año te pasen cosas muy bonitas y que Dios te bendiga muchísimo. Feliz cumpleaños. | AA75: Samsung | AC75: =HYPERLINK("https://drive.google.com/file/d/19kkw9nKdK_AKjIRrNi2tuGuQWyt5sfP3/view?usp=drivesdk","Abrir_Factura") -> Abrir_Factura
A76: 45988.448 | B76: 89687 | C76: 1192816447 | D76: Keily Johanna | F76: Carpintero Puello | H76: 573172391248 | J76: Valery Carpintero | K76: soledad | L76: Cra 10c No. 61b-12 - Casa | M76: 3172391248 | N76: 45988 | O76: 0.52361111 | P76: 1 | Q76: 1× Mini Box Surtida | R76: 70000 | S76: 0 | T76: 30000 | U76: 100000 | V76: Mi hermana querida, verte graduarte es uno de los momentos más especiales. Has demostrado que cuando sueñas en grande y trabajas duro, todo es posible. ¡Felicidades por este logro tan merecido! | W76: Aprobado | X76: Transferencia 5431 | Y76: Firmado | Z76: De tus hermanas❤️ | AA76: Huawei | AC76: =HYPERLINK("https://drive.google.com/file/d/1j3ASJabP19sEJ-WKWHqmQjByfzZb1ykT/view?usp=drivesdk","Abrir_Factura") -> Abrir_Factura
A77: 45988.485 | B77: 89688 | C77: 85467695 | D77: Alexander | F77: Ospina | H77: 573166907488 | J77: Alexander Ospina | K77: Entrega En Tienda | L77: Entrega En Tienda - Entrega En Tienda | M77: 3166907488 | N77: 45988 | O77: 0.61180556 | P77: 1 | Q77: 1× Flora Box Redonda 24 Rosas de Jardín | R77: 300000 | S77: 0 | T77: 0 | U77: 300000 | V77: Para mi cosita linda No hay excusa valida, estas flores llevan mis mas sincera disculpa y mi deseo de volver a verte sonreir. Lamento lo sucedido. Te amo demasiado | W77: Aprobado | X77: Tarjeta Debito | Y77: Anónimo | AA77: Samsung | AC77: =HYPERLINK("https://drive.google.com/file/d/1Bckccwek0H_JgcUa6Yhy4-ob0Gf5NHb_/view?usp=drivesdk","Abrir_Factura") -> Abrir_Factura
A78: 45987.952 | B78: 89689 | C78: 1043841188 | D78: Fray David | F78: Marriaga | H78: 573205928079 | J78: Mary Carmen | K78: El Porvenir | L78: CRA 45 74-91 - Casa | M78: 320 5928079 | N78: 45988 | O78: 0.54166667 | P78: 1 | Q78: 1× Mini Box Hortensias y Mini Rosa | R78: 70000 | S78: 0 | T78: 10000 | U78: 80000 | V78: Hoy descubrí el amor al final de tus besos y encontré la canción que Dios me prometió y descubrí que tú y descubrí que yo sembramos el amor y el amor floreció | W78: Aprobado | X78: Transferencia 5431 | Y78: Firmado | Z78: Fray David Marriaga | AA78: Samsung | AC78: =HYPERLINK("https://drive.google.com/file/d/1h7waYFPF6Mnz1nOyxU4sjyD-OZsWrZZJ/view?usp=drivesdk","Abrir_Factura") -> Abrir_Factura
A79: 45988 | B79: 89690 | C79: 32748863 | D79: adriana | F79: Vazques | H79: 317 4289182 | J79: adriana | K79: Entrega En Tienda | L79: tienda | M79: 317 4289182 | N79: 45988 | O79: 0.52002315 | P79: 1 | Q79: flores surtidas | R79: 28000 | T79: 0 | U79: 28000 | W79: Aprobado | X79: Tarjeta Debito | AA79: Huawei | AC79: =HYPERLINK("https://drive.google.com/file/d/1W_KXMt8uzlwMKnTIQpNNFtlz-uxPqTzJ/view?usp=drivesdk", "Abrir_Factura") -> Abrir_Factura
A80: 45988.409 | B80: 89691 | C80: 0 | D80: Aldo | F80: Bará Cousin | H80: 50379100639 | J80: Esmeralda Lemus / Carolina Leon | K80: san vicente | L80: Edificio Áncora, Cr 50 #90-61 Apto 801 - Casa | M80: #ERROR! | N80: 45988 | O80: 0.66666667 | P80: 1 | Q80: 1× Flora Box Mediana 24 Rosas | R80: 200000 | S80: 0 | T80: 6000 | U80: 206000 | V80: Que tu voz siempre sea la razón de mi sonrisa | W80: Aprobado | X80: Transferencia Bold | Y80: Firmado | Z80: ABC | AA80: Huawei | AC80: =HYPERLINK("https://drive.google.com/file/d/11XSY7Yl5YbGymBLmwFQU8UITp2Aqit66/view?usp=drivesdk","Abrir_Factura") -> Abrir_Factura
A81: 45988.395 | B81: 89692 | C81: 1042240891 | D81: Daniella | F81: Char | H81: 573205337978 | J81: Mirza Del Valle | K81: san vicente | L81: Calle 87 #47-40 edf verdi apto 2B - Edificio | M81: #ERROR! | N81: 45989 | O81: 0.45833333 | P81: 1 | Q81: 1× Flora Gift Box JP | R81: 260000 | S81: 0 | T81: 6000 | U81: 266000 | V81: Felicitaciones Michu! Porque este logro no solo es un testimonio del esfuerzo de tu hijo, sino también de tu increíble fortaleza, amor y dedicación. | W81: Aprobado | X81: Transferencia 5431 | Y81: Firmado | Z81: Con cariño: Liliana Rozo y Daniella Char | AA81: Huawei | AC81: =HYPERLINK("https://drive.google.com/file/d/1RPf6r2u2G_LfkWlC81jE4Ob7pX7b8qk7/view?usp=drivesdk","Abrir_Factura") -> Abrir_Factura
A82: 45988.541 | B82: 89693 | C82: 1044217285 | D82: Luciana | F82: Ripoll | H82: 573117393493 | J82: Luciana Ripoll | K82: Altos de Riomar | L82: Apto 303 - Edificio | M82: 3117393493 | N82: 45988 | O82: 0.6875 | P82: 1 | Q82: 1× Marquito 12 Rosas | R82: 140000 | S82: 0 | T82: 10000 | U82: 150000 | V82: Feliz cumpleaños, eres la mejor mamá y esposa del mundo. Te amamos | W82: Aprobado | X82: Transferencia 5431 | Y82: Firmado | Z82: Con cariño, Iván y Luciana | AA82: Huawei | AC82: =HYPERLINK("https://drive.google.com/file/d/1Jydzs20SX6p_ate9ADvvxv7YSB-ggDI5/view?usp=drivesdk","Abrir_Factura") -> Abrir_Factura
A83: 45988.584 | B83: 89701 | C83: 1010163840 | D83: Daniel | F83: Vásquez | H83: 573022653371 | J83: Mayo | K83: Riomar | L83: Cra 58#84-214 - Casa | M83: 3107343510 | N83: 45989 | O83: 0.33333333 | P83: 1 | Q83: 1× Flora Box Mediana Pastel | R83: 180000 | S83: 0 | T83: 10000 | U83: 190000 | V83: Para mi suegra favorita. La mejor de las mejores. Feliz cumpleaños. Te quiero mucho Mayo. Mil bendiciones este nuevo año. | W83: Aprobado | X83: Transferencia 5431 | Y83: Firmado | Z83: Cuñis | AA83: Samsung | AC83: =HYPERLINK("https://drive.google.com/file/d/1nEwCaoWkL1QqayegI9U_oEwq7GpFG7xz/view?usp=drivesdk","Abrir_Factura") -> Abrir_Factura
A84: 45988.621 | B84: 89702 | C84: 1003123104 | D84: Anggel | F84: Rangel | H84: 573114081183 | J84: Roxy Vanessa Ortiz Quintero | K84: Riomar | L84: Cra 52 #82-253 Edificio RIU 52 - Edificio | M84: 3114081183 | N84: 45988 | O84: 0.70416667 | P84: 1 | Q84: 1× Marquito Surtido Pastel | R84: 120000 | S84: 0 | T84: 10000 | U84: 130000 | V84: Querida Roxy Vanessa, ¡Felicidades de todo corazón! Verte alcanzar tu grado de especialización nos llena de orgullo y alegría inmensa. Sabemos cuánto luchaste, cuánto soñaste y cuánta fuerza pusiste para lograrlo. Este triunfo es solo el inicio de todo lo grande que te espera. Te admiramos y te amamos muchísimo. | W84: Aprobado | X84: Transferencia 5431 | Y84: Firmado | Z84: Con todo el cariño, Tus mejores amigas Luisa y Anggel | AA84: Huawei | AC84: =HYPERLINK("https://drive.google.com/file/d/1z4ZuzoEsYqLAvhDy2T_rFMd2CFw7LS27/view?usp=drivesdk","Abrir_Factura") -> Abrir_Factura
A85: 45989.352 | B85: 89703 | C85: 232511 | D85: aracelis | F85: martinez | H85: 573106150116 | J85: josefina henao | K85: Altos de Riomar | L85: clle 93#49c-186 casa - Casa | M85: 573106150116 | N85: 45989 | O85: 0.43611111 | P85: 1 | Q85: 1× Cerámica Sweet Pea | R85: 90000 | S85: 0 | T85: 10000 | U85: 100000 | W85: Aprobado | X85: Efectivo | Y85: Firmado | AA85: Samsung | AC85: =HYPERLINK("https://drive.google.com/file/d/1as-aIeXrvbgNCqDyP7H6AW7E9FHQwnuy/view?usp=drivesdk","Abrir_Factura") -> Abrir_Factura
A86: 45989.364 | B86: 89706 | C86: 1143469686 | D86: elizabeht | F86: suarez | H86: 573013127318 | J86: Katia Benítez | K86: La Concepción | L86: clle 70b#41-94 clínica la asuncion maternidad hab 11 | M86: 3244510698 | N86: 45989 | O86: 0.44722222 | P86: 1 | Q86: 1× Mini Box Hortensias y Mini Rosa | R86: 70000 | S86: 0 | T86: 12000 | U86: 82000 | W86: Aprobado | X86: Transferencia 5431 | Y86: Firmado | AA86: Huawei | AC86: =HYPERLINK("https://drive.google.com/file/d/1MADP7OwKgXJBV5Io3K6guMexAdcTUDLb/view?usp=drivesdk","Abrir_Factura") -> Abrir_Factura
A87: 45989.36 | B87: 89721 | C87: 22467011 | D87: Giselle | F87: Cure | H87: 34697749517 | J87: María Camila Borrero | K87: Las Mercedes | L87: Cra 38b #77-69 - Casa | M87: 304 2921022 | N87: 45990 | O87: 0.375 | P87: 1 | Q87: 1× Bouquet 6 Rosas Rojas | R87: 70000 | S87: 0 | T87: 12000 | U87: 82000 | V87: te extraño mucho, celebro este logro como si estuviera a tu lado. Este solo es el principio de todo lo bonito que te espera. Te amo! Estoy feliz por ti, aunque no pueda darte el abrazo que quisiera. | W87: Aprobado | X87: Transferencia 5431 | Y87: Firmado | Z87: Emege | AA87: Huawei | AC87: =HYPERLINK("https://drive.google.com/file/d/1ORuReyFpMp6sRB7CdsUXUhCa3o6VU-ex/view?usp=drivesdk","Abrir_Factura") -> Abrir_Factura
A88: 45989.394 | B88: 89722 | C88: 72023311 | D88: Álvaro | F88: Elles | H88: 573017688486 | J88: Marly Angulo | K88: adela de char | L88: Calle 21c #10-27 2 etapa - Casa | M88: 3171538860 | N88: 45989 | O88: 0.47430556 | P88: 1 | Q88: 1× Marquito Girasol | R88: 120000 | S88: 0 | T88: 17000 | U88: 137000 | V88: Honestamente, que te hayas recuperado me sabe a… Gloria. Te quiero mucho. | W88: Aprobado | X88: Transferencia 5431 | Y88: Anónimo | AA88: Huawei | AC88: =HYPERLINK("https://drive.google.com/file/d/1fC1TiI5v8VcYFqzS_pLwZRCaBIFatwZ1/view?usp=drivesdk","Abrir_Factura") -> Abrir_Factura
A89: 45989 | B89: 89723 | C89: 63543839 | D89: Ana Lucia | F89: Villamizar | H89: 3156234881 | J89: entrega en tienda | K89: Entrega En Tienda | L89: entrega en tienda | M89: 3156234881 | N89: 45989 | O89: 0.4262037 | P89: 1 | Q89: bouquet surtido pastel | R89: 40000 | T89: 0 | U89: 40000 | W89: Aprobado | X89: Tarjeta Credito | AA89: Samsung | AC89: =HYPERLINK("https://drive.google.com/file/d/1rQS9Ny8Q1r_JEvhca05KtdVRLX96TNJS/view?usp=drivesdk", "Abrir_Factura") -> Abrir_Factura
A90: 45989 | B90: 89724 | C90: 19352359 | D90: Alberto | F90: Rojas | H90: 3157241281 | J90: Entrega en tienda | K90: Entrega En Tienda | L90: flora | M90: 3157241281 | N90: 45989 | O90: 0.44429398 | P90: 1 | Q90: flores surtidas | R90: 164000 | T90: 0 | U90: 164000 | W90: Aprobado | X90: Efectivo | AA90: Samsung | AC90: =HYPERLINK("https://drive.google.com/file/d/1fxIgPVRoa33di3ub-NUqC-aM7E6uCfY2/view?usp=drivesdk", "Abrir_Factura") -> Abrir_Factura
A91: 45989.419 | B91: 89726 | C91: 1140765390 | D91: Sergio | F91: Mantilla | H91: 573147065545 | J91: Katia De Aguas | K91: Alameda del Río | L91: Apto 504 T2 Conjunto Tucán calle 114 #42-300 - Conjunto | M91: 3175463514 | N91: 45989 | O91: 0.50486111 | P91: 1 | Q91: 1× Mini Box Hortensias y Mini Rosa | R91: 70000 | S91: 0 | T91: 17000 | U91: 87000 | V91: Cada 28 de Noviembre pienso en ti, Hoy quise regalarte algo que siempre te ha hecho feliz. Ojalá estas flores te abracen un poquito por mí. Feliz cumpleaños. | W91: Aprobado | X91: Transferencia 4038 | Y91: Firmado | Z91: Sergio M | AA91: Samsung | AC91: =HYPERLINK("https://drive.google.com/file/d/1CruZAQgW1jbfy8erqhksI2MftFfXBw-j/view?usp=drivesdk","Abrir_Factura") -> Abrir_Factura
A92: 45989 | B92: 89727 | C92: 1044214453 | D92: Valery | F92: Mendoza | H92: 3013772533 | J92: Salemh Coronado | K92: Alfonso López | L92: Calle 47C #21c-12 | M92: 3013772533 | N92: 45989 | O92: 0.51012731 | P92: 1 | Q92: bouquet surtido | R92: 40000 | T92: 15000 | U92: 55000 | W92: Aprobado | X92: Transferencia 5431 | AA92: Huawei | AC92: =HYPERLINK("https://drive.google.com/file/d/1iJJTLXdbfChG-numVGxtaeAuTV-Z2m_O/view?usp=drivesdk", "Abrir_Factura") -> Abrir_Factura
A93: 45989.412 | B93: 89728 | C93: 1010065981 | D93: Santiago | F93: Florez | H93: 13059032689 | J93: Libia Payan | K93: El Limoncito | L93: Calle 85a#73-44 - Casa | M93: 3017489693 | N93: 45989 | O93: 0.49791667 | P93: 1 | Q93: 1× Bouquet Gerbera | R93: 150000 | S93: 0 | T93: 10000 | U93: 160000 | W93: Aprobado | X93: Transferencia 5431 | Y93: Anónimo | AA93: Huawei | AC93: =HYPERLINK("https://drive.google.com/file/d/1vIAX37zAkrfSCVnE5onCd4aTGx_YIy39/view?usp=drivesdk","Abrir_Factura") -> Abrir_Factura
A94: 45989.485 | B94: 89729 | C94: 72328745 | D94: Ronald | F94: Barrios | H94: 573147126101 | J94: ronald | K94: Entrega En Tienda | L94: flora - Entrega en tienda | M94: barrios | N94: 45989 | O94: 0.57083333 | P94: 1 | Q94: 1× Flora Box Solitario Rosa | R94: 60000 | S94: 0 | T94: 0 | U94: 60000 | W94: Aprobado | X94: Tarjeta Debito | Y94: Firmado | AA94: Samsung | AC94: =HYPERLINK("https://drive.google.com/file/d/1nQF_exO2AjH8iyvO3i4sXD1W4QjVdKoV/view?usp=drivesdk","Abrir_Factura") -> Abrir_Factura
A95: 45989.472 | B95: 89730 | C95: 45764004 | D95: Andrea | F95: Torres | H95: 573052300848 | J95: Natalia Torres | K95: Altos de Riomar | L95: torre 5 apto 104 - Conjunto | M95: 3052300848 | N95: 45989 | O95: 0.59513889 | P95: 1 | Q95: 1× Bouquet 12 Rosas Rojas | R95: 100000 | S95: 0 | T95: 10000 | U95: 110000 | V95: Querida Naty, culminas tu internado y nuestro corazón no puede sentirse más orgulloso. Tu esfuerzo y entrega te han llevado a ello. Gracias por demostrarnos que los sueños se alcanzan con disciplina y valentía. Te celebramos, te admiramos y te acompañamos siempre. ¡Felicidades por este gran logro, te amamos doctora! | W95: Aprobado | X95: Transferencia 5431 | Y95: Firmado | Z95: Con amor, Andre sofy Elkin y Ely | AA95: Samsung | AC95: =HYPERLINK("https://drive.google.com/file/d/1jJGX6zwKVZ4vnO-89TnhJ9BQJYYAyYbi/view?usp=drivesdk","Abrir_Factura") -> Abrir_Factura
A96: 45989.505 | B96: 89731 | C96: 1041693775 | D96: Adrián | F96: tovar | H96: 573028296647 | J96: Maria Victoria villalobos | K96: Villa Santos | L96: Cra. 47 #100 - 144 apto 1002 A - Edificio | M96: 3028296647 | N96: 45992 | O96: 0.33819444 | P96: 1 | Q96: 1× Bouquet 100 Rosas Rojas | R96: 580000 | S96: 0 | T96: 10000 | U96: 590000 | V96: feliz cumpleaños que dios te bendiga, espero que todos tus sueños se estén cumpliendo. Quise darte este detalle, pequeño comparado con todo lo que algún día quise hacer por ti. | W96: Aprobado | X96: Transferencia 5431 | Y96: Firmado | Z96: Adrian Tovar | AA96: Huawei | AB96: ver whatsapp rosas rosadas, adicion cinta | AC96: =HYPERLINK("https://drive.google.com/file/d/1r8WdezvDiyGsAR_fEBWmHrbvxyjIyyKg/view?usp=drivesdk","Abrir_Factura") -> Abrir_Factura
A97: 45989 | B97: 89732 | C97: 1047214424 | D97: Eliana | F97: Valdeblanquez | H97: 3012527025 | J97: Dra Sara Solano | K97: miramar | L97: CRA 45 #99c- 94 torre 4 piso 5 apto 513 conjunto residencial portal de miramar | M97: 301 5304081 | N97: 45989 | O97: 0.5249537 | P97: 1 | Q97: bouquet surtido | R97: 130000 | T97: 12000 | U97: 142000 | W97: Aprobado | X97: Transferencia 5431 | AA97: Samsung | AC97: =HYPERLINK("https://drive.google.com/file/d/1mX44ErcLMa-u4onBVNEBKi-fha2riKXs/view?usp=drivesdk", "Abrir_Factura") -> Abrir_Factura
A98: 45989.54 | B98: 89734 | C98: 22517899 | D98: Johana | F98: toscano | H98: 573005363005 | J98: johana toscano | K98: El Limoncito | L98: Carrera 49c # 74-144 Restoration Church - Casa | M98: 3005363005 | N98: 45990 | O98: 0.56944444 | P98: 1 | Q98: 1× Canasto Lavanda | R98: 220000 | S98: 0 | T98: 10000 | U98: 230000 | V98: Sully : le voy gracias a Dios por ser tan incondicional para mi vida y ministerio Le pido al Señor que cada día sea añadiendo más de se amor, favor y gracias Que siempre guarde ese hermoso corazón que tienes Y nunca olvides que te amo mucho 🌷 | W98: Aprobado | X98: Transferencia Bold | Y98: Firmado | AA98: Samsung | AC98: =HYPERLINK("https://drive.google.com/file/d/1RcqxmvCdq089UyNT3LnL2MxrJvN-5EKG/view?usp=drivesdk","Abrir_Factura") -> Abrir_Factura
A99: 45989.597 | B99: 89735 | C99: 32710299 | D99: liliana | F99: logreira | H99: 573164426240 | J99: ingrid logreira | K99: José Antonio Galán | L99: cra 2#35-35 casa 104 villa linda /galán - Conjunto | M99: 3164426240 | N99: 45967 | O99: 0.97152778 | P99: 1 | Q99: 1× Arreglo Personalizado | R99: 140000 | S99: 0 | T99: 20000 | U99: 160000 | V99: BOUQUET DE MINI CALAS BLANCAS ,NOVIA | W99: Aprobado | X99: Transferencia 5431 | Y99: Firmado | AA99: Samsung | AC99: =HYPERLINK("https://drive.google.com/file/d/1mHPVLO5eVBFo2DUY-BvwS34I6xywa_-l/view?usp=drivesdk","Abrir_Factura") -> Abrir_Factura
A100: 45989.585 | B100: 89736 | C100: 22737126 | D100: Darly | F100: Altamar | H100: 573106709048 | J100: Mia | K100: Altos de Riomar | L100: Cra 59b no 94-180 Casa esquina - Casa | M100: 3106709048 | N100: 45989 | O100: 0.66875 | P100: 1 | Q100: 1× Marquito 12 Rosas | R100: 140000 | S100: 0 | T100: 10000 | U100: 150000 | V100: Feliz Cumpleaños Mia! Que hoy sea un día maravilloso. Gracias por ser tan especial. Te quiero mucho. | W100: Aprobado | X100: Transferencia 5431 | Y100: Firmado | Z100: Samuel | AA100: Samsung | AC100: =HYPERLINK("https://drive.google.com/file/d/1cyb7xtNWugPgy5GYdn7ZKfhFpoisafc4/view?usp=drivesdk","Abrir_Factura") -> Abrir_Factura
...

Sheet Produccion
A1: N°Pedido | B1: Cliente | C1: Telefono | D1: Codigo | E1: Nombre_Producto | F1: Barrio | G1: Destinatario | H1: Dirección | I1: Teléfono destino | J1: Fecha de Entrega | K1: Hora de Entrega | L1: Forma de Pago | M1: Valor Cobrado | N1: Fecha | O1: Hora de Registro | P1: Estado del Pedido | Q1: Asignado | R1: Notificado | S1: Procesado | T1: Entrega En Tienda | U1: Zona | V1: Cuenta | W1: Observaciones
A2: 90797 | B2: samir vence | C2: 573204580008 | D2: 56 | E2: 1× Corazón Mediano Rosas | F2: Entrega En Tienda | G2: samir vence | H2: Entrega En Tienda - Entrega En Tienda | I2: 3204580008 | J2: 46027 | K2: 0.41666667 | M2: 220000 | N2: 46027.342 | O2: 08:14 | P2: TERMINADO | Q2: Elibeth Salgado | R2: Enviado 5/1/2026, 8:14:21 a. m. | T2: Sí | U2: Entrega En Tienda | V2: Transferencia 5431
A3: 90796 | B3: Laura Botero | C3: 573017850753 | D3: 63 | E3: 1× Guacal Surtido Lirio | F3: Altos del Prado | G3: Saida Sojo | H3: Calle 82 #59-59, Apto 303 - Edificio | I3: 3106306140 | J3: 46039 | K3: 0.66666667 | M3: 168000 | N3: 46025.823 | O3: 08:06 | P3: TERMINADO | Q3: Cristina Arrieta | R3: Enviado 5/1/2026, 8:06:56 a. m. | T3: No | U3: Zona 2 | V3: Transferencia 5431
A4: 90795 | B4: william Eichler | C4: 5.70049e+16 | D4: 21 | E4: 1× Flora Box Mediana Pastel | F4: Bethania | G4: Isabella Clavijo | H4: Calle 76 #39-39 - Casa | I4: 3011656550 | J4: 46030 | K4: 0.375 | M4: 192000 | N4: 46027.335 | O4: 08:03 | P4: TERMINADO | Q4: Elibeth Salgado | R4: Enviado 5/1/2026, 8:04:06 a. m. | T4: No | U4: Zona 2 | V4: Paypal
A5: 90794 | B5: Tatiana Guerrero Londoño | C5: 573187955699 | D5: 29 | E5: 1× Mini Box Orquidea | F5: Entrega En Tienda | G5: Tatiana Guerrero Londoño | H5: Entrega En Tienda - Entrega En Tienda | I5: 3187955699 | J5: 46027 | K5: 0 | M5: 80000 | N5: 46027.323 | O5: 07:49 | P5: TERMINADO | Q5: Elibeth Salgado | R5: Enviado 5/1/2026, 7:49:49 a. m. | T5: Sí | U5: Entrega En Tienda | V5: Efectivo | W5: Para: Juany Álvarez De: Luz Del Carmen, Margarita, Tatiana, Lorena, Balbina, Angie, Javier, Liceth, Dawi, Claudia, Adriana S., Karen, Fernando y Luz Marina.
A6: 90793 | B6: DANIEL CHAZAROWATTY | C6: 577748258571 | D6: ? | E6: 1× Bouquet 12 Rosas Rosadas | F6: Nuevo Horizonte | G6: VALENTINA LOPEZ | H6: CRA 42 # 82A-96 - Casa | I6: 3171346718 | J6: 46027 | K6: 0.375 | M6: 112000 | N6: 46027.307 | O6: 07:23 | P6: TERMINADO | Q6: Elibeth Salgado | R6: Enviado 5/1/2026, 7:23:20 a. m. | T6: No | U6: Zona 3 | V6: Transferencia 5431
A7: 90792 | B7: jorge visbal | C7: 573015013641 | D7: 29 | E7: 1× Mini Box Orquidea | F7: Villa Campestre | G7: ELEANA LOPEZ | H7: CRA 20#2A-10 CONJ, TERRA CASA 271 - Casa | I7: 3164703494 | J7: 46027 | K7: 0.375 | M7: 95000 | N7: 46027.3 | O7: 07:12 | P7: TERMINADO | Q7: Elibeth Salgado | R7: Enviado 5/1/2026, 7:13:02 a. m. | T7: No | U7: Zona 5 | V7: Transferencia 4966
A8: 90791 | B8: Julieth Martinez | C8: 573008060384 | D8: 64 | E8: 1× Marquito Orquidea | F8: Entrega En Tienda | G8: Julieth Martinez | H8: Entrega En Tienda - Entrega En Tienda | I8: 3008060384 | J8: 46027 | K8: 0.375 | M8: 140000 | N8: 46027.293 | O8: 07:02 | P8: TERMINADO | Q8: Elibeth Salgado | R8: Enviado 5/1/2026, 7:02:37 a. m. | T8: Sí | U8: Entrega En Tienda | V8: Cuentas Por Cobrar | W8: rappi
A9: 90790 | B9: vivian feris | C9: 573157264794 | D9: 95 | E9: 1× Arreglo Personalizado | F9: Entrega En Tienda | G9: vivian feris | H9: Entrega En Tienda - Entrega En Tienda | J9: 46022 | K9: 0 | M9: 182000 | N9: 46022.609 | O9: 14:37 | P9: TERMINADO | Q9: Cristina Arrieta | R9: Enviado 31/12/2025, 2:37:57 p. m. | T9: Sí | U9: Entrega En Tienda | V9: Transferencia 4966
A10: 90789 | B10: MARIA HELENA CHARRIS PEÑA | C10: 5731664237392 | D10: ? | E10: 5 canastos surtidos en amarillo | F10: caujaral | G10: maria elena | H10: caujaral - Casa | J10: 46022 | K10: 0 | M10: 1275000 | N10: 46022 | O10: 14:34 | P10: TERMINADO | Q10: Elibeth Salgado | R10: Enviado 31/12/2025, 2:34:45 p. m. | T10: No | V10: Transferencia 5431 | W10: 5 canastos surtidos
A11: 90788 | B11: Zora Virginia | C11: 13312434171 | D11: 95 | E11: 1× Arreglo Personalizado | F11: El Recreo | G11: Maria Kamila | H11: Recreo kra 34 #58-46 - Casa | J11: 46022 | K11: 0 | M11: 14000 | N11: 46022.592 | O11: 14:20 | P11: TERMINADO | Q11: James de la Cruz | R11: Enviado 31/12/2025, 2:21:08 p. m. | T11: No | U11: Zona 2 | V11: Transferencia 5431 | W11: sembrado sin orquidas y rosas rosadas
A12: 90787 | B12: Jose Castillo palacio | C12: 573004340336 | D12: 59 | E12: 1× Corazón Mediano Surtido | F12: La Cumbre | G12: VICTORIA ROMERO CASTILLO | H12: Calle 90#42e-11 casa 1 Barranquilla - Casa | J12: 46022 | K12: 0.58333333 | M12: 212000 | N12: 46022.58 | O12: 14:00 | P12: TERMINADO | Q12: Cristina Arrieta | R12: Enviado 31/12/2025, 2:00:33 p. m. | T12: No | U12: Zona 4 | V12: Transferencia 4038
A13: 90786 | B13: karen Quintero | C13: 573229447327 | D13: 95 | E13: 1× Arreglo Personalizado | F13: Entrega En Tienda | G13: karen Quintero | H13: Entrega En Tienda - Entrega En Tienda | I13: 3229447327 | J13: 46022 | K13: 0 | M13: 40000 | N13: 46022.573 | O13: 13:46 | P13: TERMINADO | Q13: Elibeth Salgado | R13: Enviado 31/12/2025, 1:46:32 p. m. | T13: Sí | U13: Entrega En Tienda | V13: Transferencia 6913 | W13: 12 rosas rojas
A14: 90785 | B14: B&A INGENIERIA Y CONSTRUCCIONES SAS empresa | C14: 573015669546 | D14: 95 | E14: 1× Arreglo Personalizado | G14: jorge agudelo | H14: ZIOON TOWERS - Casa | J14: 46022 | K14: 0 | M14: 189690 | N14: 46022.457 | O14: 13:05 | P14: TERMINADO | Q14: James de la Cruz | R14: Enviado 31/12/2025, 1:05:52 p. m. | T14: No | V14: Cuentas Por Cobrar | W14: FLORES SURTIDAS
A15: 90784 | B15: Carlos Moreno | C15: 57308162659 | D15: ? | E15: 1× Flora mini box orquidea | F15: Riomar | G15: Estefanía Pérez | H15: Cra 51 # 84-149 - Conjunto Edificio yuma - apto 303 | I15: 3208162659 | J15: 46022 | K15: 0.58333333 | M15: 90000 | N15: 46022.531 | O15: 12:57 | P15: TERMINADO | Q15: Elibeth Salgado | R15: Enviado 31/12/2025, 12:58:15 p. m. | T15: No | U15: Zona 3 | V15: Transferencia 5431
A16: 90783 | B16: claudia Castro | C16: 573106442346 | D16: 95 | E16: 1× Arreglo Personalizado | G16: claudia castro | H16: cra 58#79-121 apto 902B - Casa | I16: 3106442346 | J16: 46022 | K16: 0.54166667 | M16: 363000 | N16: 46022.446 | O16: 12:43 | P16: TERMINADO | Q16: James de la Cruz | R16: Enviado 31/12/2025, 12:44:10 p. m. | T16: No | V16: Transferencia 5431 | W16: FLORES SURTIDAS
A17: 90782 | B17: Pablo Vargas | C17: 573507547854 | D17: 51 | E17: 1× Bouquet 24 Rosas Rojas | F17: La Floresta | G17: Diana Rodriguez | H17: carrera 35 #63b-31 - Casa | I17: 3014699503 | J17: 46022 | K17: 0.58333333 | M17: 191000 | N17: 46022 | O17: 12:26 | P17: TERMINADO | Q17: James de la Cruz | R17: Enviado 31/12/2025, 12:27:06 p. m. | T17: No | U17: Zona 3 | V17: Transferencia 5431
A18: 90781 | B18: Magdolia Sánchez | C18: 573002068419 | D18: 32 | E18: 1× Mini Box Surtida | F18: Altos del Prado | G18: Magdolia Sánchez | H18: Carrera 59B#84-48 edificio vivace apto 1704 T1 - Edificio | I18: 3005903655 | J18: 46022 | K18: 0.029166667 | M18: 78000 | N18: 46022.502 | O18: 12:04 | P18: TERMINADO | Q18: Elibeth Salgado | R18: Enviado 31/12/2025, 12:05:06 p. m. | T18: No | U18: Zona 2 | V18: Transferencia 5431
A19: 90780 | B19: Mauricio Cuesta | C19: 573206349902 | D19: 95 | E19: 1× Arreglo Personalizado | F19: San Felipe | G19: Daniela Guette | H19: Calle 68 No 22c-16 - Casa | J19: 46022 | K19: 0.52847222 | M19: 135000 | N19: 46022.487 | O19: 11:47 | P19: TERMINADO | Q19: Cristina Arrieta | R19: Enviado 31/12/2025, 11:48:07 a. m. | T19: No | U19: Zona 2 | V19: Transferencia 5431 | W19: bouquet de 12 rosas lilas como el de la foto
A20: 90779 | B20: Nicolas Geraldino Aaron | C20: 573219173591 | D20: 45 | E20: 1× Bouquet Gerbera | F20: Entrega En Tienda | G20: Novia | H20: Entrega En Tienda - Entrega En Tienda | I20: 3219173591 | J20: 46022 | K20: 0 | M20: 150000 | N20: 46022.463 | O20: 11:09 | P20: TERMINADO | Q20: Elibeth Salgado | R20: Enviado 31/12/2025, 11:09:38 a. m. | T20: Sí | U20: Entrega En Tienda | V20: Efectivo
A21: 90778 | B21: Jacobo Jaramillo | C21: 573012089960 | D21: 5 | E21: 1× Flora Box Romantic Flores 24 Rosas | F21: Buenavista | G21: Jacobo Jaramillo | H21: Calle 99 C # 64 A - 45. Edif. Vallarta, apto 815 T4 - Edificio | I21: 3012089960 | J21: 46022 | K21: 0.0034722222 | M21: 230000 | N21: 46022.442 | O21: 11:00 | P21: TERMINADO | Q21: Cristina Arrieta | R21: Enviado 31/12/2025, 11:01:00 a. m. | T21: No | U21: Zona 3 | V21: Link Bold
A22: 90777 | B22: David Bohorquez rodelo | C22: 573059227701 | D22: 52 | E22: 1× Bouquet 12 Rosas Rojas | F22: Granadillo | G22: Camila gonzales | H22: Cra 45 #84-29 edificio Hispania real apart 11 - Casa | J22: 46022 | K22: 0 | M22: 109000 | N22: 46022.441 | O22: 10:57 | P22: TERMINADO | Q22: Elibeth Salgado | R22: Enviado 31/12/2025, 10:57:25 a. m. | T22: No | U22: Zona 4 | V22: Transferencia 5431
A23: 90776 | B23: Simon Hakim | C23: 573107175874 | D23: 51 | E23: 1× Bouquet 24 Rosas Rojas | F23: El Golf | G23: Salwa Chahin | H23: cra 59 # 81-149 piso 4 edificio Lenox - Edificio - Edificio | I23: 3182618317 | J23: 46022 | K23: 0.45833333 | M23: 188000 | N23: 46022.433 | O23: 10:48 | P23: TERMINADO | Q23: Elibeth Salgado | R23: Enviado 31/12/2025, 10:49:03 a. m. | T23: No | U23: Zona 3 | V23: Transferencia 5431
A24: 90775 | B24: mary nuñez | C24: 573156151131 | D24: 95 | E24: 1× Arreglo Personalizado | G24: mary nuñez | H24: Cra75a #88-71 conjunto puerto alegre apt 501G - Casa | I24: 315 6151131 | J24: 46022 | K24: 0 | M24: 40000 | N24: 46022.44 | O24: 10:35 | P24: TERMINADO | Q24: Cristina Arrieta | R24: Enviado 31/12/2025, 10:36:00 a. m. | T24: No | V24: Obsequio | W24: rosas blancas una docena CANJE
A25: 90774 | B25: Silvia Quintero | C25: 573135739800 | D25: 31 | E25: 1× Mini Box Hortensias y Mini Rosa | F25: Altos de Riomar | G25: Magdolia Sánchez | H25: Cra 59b 84 48 apto 1704 torre 1 edificio Vivace - Edificio | I25: 3005903655 | J25: 46022 | K25: 0.45833333 | M25: 78000 | N25: 46022.403 | O25: 10:18 | P25: TERMINADO | Q25: Cristina Arrieta | R25: Enviado 31/12/2025, 10:19:07 a. m. | T25: No | U25: Zona 3 | V25: Transferencia 4038
A26: 90773 | B26: Andres Mejia | C26: 573125118337 | D26: 24 | E26: 1× Flora Box Mediana Sembrado | F26: Miramar | G26: Fabiola Menco | H26: Transversal 43 No. 100-50 Edificio Napoli Torre 5 Apto 519 - Conjunto | I26: 3226529301 | J26: 46022 | K26: 0 | M26: 182000 | N26: 46022.419 | O26: 10:17 | P26: TERMINADO | Q26: Elibeth Salgado | R26: Enviado 31/12/2025, 10:17:15 a. m. | T26: No | U26: Zona 4 | V26: Transferencia 5431
A27: 90772 | B27: Laura Coronell Higgins | C27: 573113889439 | D27: ? | E27: 1× Flora Mini Plus Box cuadrada surtida pastel y topper hbd | F27: La Campiña | G27: Karilin Arteta | H27: Carrera 44 número 84 - 126 edificio Verona apto 802 - Edificio | I27: 3113432540 | J27: 46022 | K27: 0.45833333 | M27: 159000 | N27: 46022.395 | O27: 09:41 | P27: TERMINADO | Q27: Cristina Arrieta | R27: Enviado 31/12/2025, 9:41:41 a. m. | T27: No | U27: Zona 4 | V27: Transferencia 5431
A28: 90771 | B28: Sausan Osman | C28: 573186598255 | D28: 35 | E28: 1× Canasto Surtido Morado | F28: Altos de Riomar | G28: Widad Osman | H28: Cra 59 # 96-153 apto 304 - Casa | I28: 313709-2142 | J28: 46022 | K28: 0.91666667 | M28: 308000 | N28: 46022.371 | O28: 09:17 | P28: TERMINADO | Q28: James de la Cruz | R28: Enviado 31/12/2025, 9:17:54 a. m. | T28: No | U28: Zona 3 | V28: Transferencia 5431 | W28: Feliz cumpleaños a la mejor mamá, hija, hermana, cuñada y tía del mundo. Te queremos mucho. Que Dios conceda cada uno de tus deseos y te llene de bendiciones siempre.
A29: 90770 | B29: Antwan Rojas | C29: 573238135245 | D29: 52 | E29: 1× Bouquet 12 Rosas Rojas | F29: Villa Campestre | G29: Sara Catalina Rodríguez Osorio-casa 5 | H29: Transversal 3b n23-200 - Conjunto balcones de villacampestre casa 5 | I29: 3238135245 | J29: 46022 | K29: 0.45833333 | M29: 115000 | N29: 46022.373 | O29: 09:06 | P29: TERMINADO | Q29: Cristina Arrieta | R29: Enviado 31/12/2025, 9:06:28 a. m. | T29: No | U29: Zona 5 | V29: Transferencia 5431
A30: 90769 | B30: eder arrieta | C30: 573005631561 | D30: 95 | E30: 1× Arreglo Personalizado | F30: Entrega En Tienda | G30: eder arrieta | H30: Entrega En Tienda - Entrega En Tienda | I30: 300 5631561 | J30: 46022 | K30: 0.41666667 | M30: 140000 | N30: 46022.37 | O30: 08:59 | P30: TERMINADO | Q30: Elibeth Salgado | R30: Enviado 31/12/2025, 9:00:04 a. m. | T30: Sí | U30: Entrega En Tienda | V30: Transferencia 5431 | W30: un bouquet de 4 girasoles y margaritas y dos ramitos de una rosa con otra florecitas
A31: 90768 | B31: Jamid Orozco | C31: 573052891232 | D31: 41 | E31: 1× Canasto Mediano Sweet | F31: Entrega En Tienda | G31: Jamid Orozco | H31: Entrega En Tienda - Entrega En Tienda | I31: 3052891232 | J31: 46022 | K31: 0.39652778 | M31: 150000 | N31: 46022.319 | O31: 08:09 | P31: TERMINADO | Q31: Cristina Arrieta | R31: Enviado 31/12/2025, 8:10:17 a. m. | T31: Sí | U31: Entrega En Tienda | V31: Transferencia 5431
A32: 90767 | B32: Sebastian Martinez | C32: 573165316328 | D32: 3 | E32: 1× Flora Box Redonda Orquídea | F32: Ciudad Jardín Modelo | G32: Tita | H32: Cra 38d #76-60 - Casa | J32: 46022 | K32: 0.375 | M32: 361000 | N32: 46021.769 | O32: 18:58 | P32: TERMINADO | Q32: Elibeth Salgado | R32: Enviado 30/12/2025, 6:58:41 p. m. | T32: No | V32: Transferencia 5431
A33: 90766 | B33: Wilfran Hernández Gómez | C33: 573044284127 | D33: 31 | E33: 1× Mini Box Hortensias y Mini Rosa | F33: Caribe Verde | G33: LUISA FERNANDA ZAPATA | H33: Cra9g#122-94 Caribe plaza 1 torre 1 apto 702 - Casa | I33: 3044284127 | J33: 46022 | K33: 0 | M33: 95000 | N33: 46021 | O33: 18:38 | P33: TERMINADO | Q33: Cristina Arrieta | R33: Enviado 30/12/2025, 6:38:40 p. m. | T33: No | U33: Zona 6 | V33: Transferencia 5431 | W33: Quisiera que fuera envuelta en un papel elegante
A34: 90765 | B34: eli franco | C34: 573013903481 | D34: 95 | E34: 1× Arreglo Personalizado | F34: Entrega En Tienda | G34: eli franco | H34: Entrega En Tienda - Entrega En Tienda | I34: 3013903481 | J34: 46021 | K34: 0 | M34: 39000 | N34: 46021 | O34: 18:35 | P34: TERMINADO | Q34: Elibeth Salgado | R34: Enviado 30/12/2025, 6:35:53 p. m. | T34: Sí | U34: Entrega En Tienda | V34: Datafono Credibanco | W34: flores surtidas
A35: 90764 | B35: lourdes atique | C35: 573205420119 | D35: 95 | E35: 1× Arreglo Personalizado | F35: Altos de Riomar | G35: stephanie saieh | H35: Cra 58 no 90-88 Casa - Casa | I35: 3205420119 | J35: 46022 | K35: 0.41666667 | M35: 238000 | N35: 46021 | O35: 17:29 | P35: TERMINADO | Q35: Adriana Suarez | R35: Enviado 30/12/2025, 5:30:13 p. m. | T35: No | U35: Zona 3 | V35: Cuentas Por Cobrar | W35: 5 paq.de soliaster,3 paqu. de eucalipto,2 paqu.de fuyi,1 paq.de pinopio amarillo,5 rosas,2 paq.de boca de dragon blanca,2 paq.de ruscus,1 paq,de aster,12 piñas.
A36: 90763 | B36: laura paternostro | C36: 573183607759 | D36: 95 | E36: 1× Arreglo Personalizado | F36: Entrega En Tienda | G36: laura paternostro | H36: Entrega En Tienda - Entrega En Tienda | J36: 46021 | K36: 0 | M36: 15000 | N36: 46021 | O36: 17:01 | P36: TERMINADO | Q36: Elibeth Salgado | R36: Enviado 30/12/2025, 5:01:42 p. m. | T36: Sí | U36: Entrega En Tienda | V36: Datafono Credibanco | W36: medio paquete de pino
A37: 90762 | B37: david rodas | C37: 575667005 | D37: 52 | E37: 1× Bouquet 12 Rosas Rojas | F37: Bostón | G37: david rodas | H37: Entrega En Tienda - Entrega En Tienda | I37: 5667005 | J37: 46021 | K37: 0 | M37: 100000 | N37: 46021.707 | O37: 17:00 | P37: TERMINADO | Q37: Elibeth Salgado | R37: Enviado 30/12/2025, 5:00:54 p. m. | T37: No | U37: Zona 2 | V37: Datafono Credibanco
A38: 90761 | B38: indira cañas | C38: 573106242990 | D38: 95 | E38: 1× Arreglo Personalizado | F38: Miramar | G38: indira cañas | H38: tv 57#99-180 apto 703 select | I38: 3106242990 | J38: 46022 | K38: 0.41666667 | M38: 162000 | N38: 46021.687 | O38: 16:38 | P38: TERMINADO | Q38: Adriana Suarez | R38: Enviado 30/12/2025, 4:39:06 p. m. | T38: No | U38: Zona 4 | V38: Transferencia 4038 | W38: 5 hortencias,1 paq. de pino,1 de eucalipto,1 de astromelia,2 de hipérico,18 rosas rojas.
A39: 90760 | B39: Jesus Camaño | C39: 573046167890 | D39: 31 | ? | E39: 1× Mini Box Hortensias y Mini Rosa | 1× Marquito Girasol | F39: Paraíso | G39: Jesús Camaño | H39: Carrera 63 #77C-177 - Casa | I39: 3046167890 | J39: 46021 | K39: 0.70833333 | M39: 200000 | N39: 46021.669 | O39: 16:27 | P39: TERMINADO | Q39: Elibeth Salgado | R39: Enviado 30/12/2025, 4:27:49 p. m. | T39: No | U39: Zona 3 | V39: Transferencia 4966 | W39: Feliz cumpleaños mi princesa hermosa. Te amo
A40: 90759 | B40: yanelis alvarez | C40: 573008907262 | D40: 31 | E40: 1× Mini Box Hortensias y Mini Rosa | F40: Paraíso | G40: Camila | H40: Cr 71 80- 25 paraíso - Casa | I40: 3013021116 | J40: 46021 | K40: 0.64722222 | M40: 80000 | N40: 46021.611 | O40: 14:54 | P40: TERMINADO | Q40: Cristina Arrieta | R40: Enviado 30/12/2025, 2:54:30 p. m. | T40: No | U40: Zona 3 | V40: Transferencia 5431
A41: 90758 | B41: Jhojan Rojas | C41: 573105999160 | D41: 18 | E41: 1× Flora Gift Box JP | F41: Simón Bolívar | G41: Anelays mendoza | H41: Carrera 5b #23-68 - Casa | I41: 3163568025 | J41: 46022 | K41: 0.34027778 | M41: 285000 | N41: 46021 | O41: 14:41 | P41: TERMINADO | Q41: Elibeth Salgado | R41: Enviado 30/12/2025, 2:41:17 p. m. | T41: No | U41: Zona 2 | V41: Transferencia 5431 | W41: Que quede divino, es para la mujer de mis sueños. Entregar temprano.
A42: 90757 | B42: Ada Ruiz | C42: 573185159146 | D42: ? | E42: 1× Flora Mini Plus Box Redonda surtida ponerle 3 mini girasoles y ponerle virgen pequeña milagrosa. | F42: El Golf | G42: Ada Ruiz | H42: Cra 59 # 81-229 Apto 602 Edificio Venice - Edificio | I42: 3185159146 | J42: 46021 | K42: 0.66666667 | M42: 188000 | N42: 46021.584 | O42: 14:14 | P42: TERMINADO | Q42: Elibeth Salgado | R42: Enviado 30/12/2025, 2:14:44 p. m. | T42: No | U42: Zona 3 | V42: Transferencia 5431 | W42: Feliz Año y Próspero 2026 Fila Abdala Ruiz
A43: 90756 | B43: Lorena Vasquez | C43: 573023275940 | D43: 63 | E43: 1× Guacal Surtido Lirio | F43: Ciudad Jardín Modelo | G43: Lorena Vasquez | H43: Calle 83 41 E 44 - Casa | I43: 3023273940 | J43: 46022 | K43: 0.625 | M43: 171000 | N43: 46021.552 | O43: 13:38 | P43: TERMINADO | Q43: Cristina Arrieta | R43: Enviado 30/12/2025, 1:38:48 p. m. | T43: No | V43: Transferencia 5431
A44: 90755 | B44: Generans Andrés Anaya | C44: 573106321533 | D44: 12 | E44: 1× Flora Box Surtida Rosas y Orquídeas | G44: Sofy | H44: Cra 57 # 81 - 77 Edificio villa aleida 801 - Edificio | I44: 3106321533 | J44: 46021 | K44: 0.58333333 | M44: 452200 | N44: 46021.542 | O44: 13:01 | P44: TERMINADO | Q44: Elibeth Salgado | R44: Enviado 30/12/2025, 1:01:29 p. m. | T44: No | V44: Transferencia 4966
A45: 90754 | B45: Jesus Valles | C45: 573222218451 | D45: 32 | ? | E45: 1× Mini Box Surtida | 1× Mini Box Hortensias y Mini Rosa | F45: soledad | G45: Sra Olga y tiffany | H45: Calle 80 #22-04 - Casa Robles Por la olímpica derecho | I45: 3222218451 | J45: 46021 | K45: 0.58333333 | M45: 170000 | N45: 46021.489 | O45: 12:39 | P45: TERMINADO | Q45: Elibeth Salgado | R45: Enviado 30/12/2025, 12:39:54 p. m. | T45: No | V45: Link Bold | W45: La nota solo sería en uno
A46: 90753 | B46: Angel Ibarra | C46: 573017925741 | D46: 23 | E46: 1× Flora Box Mediana 24 Rosas | F46: miramar | G46: Valentina gomez perez | H46: Cra 43 #98-86 Torre 2 apto 306 balcones de miramar 2 - Edificio | I46: 3042555299 | J46: 46021 | K46: 0 | M46: 212000 | N46: 46021.507 | O46: 12:30 | P46: TERMINADO | Q46: Elibeth Salgado | R46: Enviado 30/12/2025, 12:30:11 p. m. | T46: No | V46: Transferencia 5431
A47: 90752 | B47: Pedro Osorio | C47: 573013575380 | D47: 21 | E47: 1× Flora Box Mediana Pastel | F47: Entrega En Tienda | G47: Pedro Osorio | H47: Entrega En Tienda - Entrega En Tienda | I47: 3013575380 | J47: 46021 | K47: 0.55694444 | M47: 180000 | N47: 46021.512 | O47: 12:18 | P47: TERMINADO | Q47: Elibeth Salgado | R47: Enviado 30/12/2025, 12:18:57 p. m. | T47: Sí | U47: Entrega En Tienda | V47: Datafono Credibanco
A48: 90751 | B48: Juan Sebastian Daza | C48: 573026090941 | D48: 21 | E48: 1× Flora Box Mediana Pastel | F48: Entrega En Tienda | G48: Juan Sebastian Daza | H48: Entrega En Tienda - Entrega En Tienda | I48: 3026090941 | J48: 46021 | K48: 0.013888889 | M48: 180000 | N48: 46021 | O48: 12:14 | P48: TERMINADO | Q48: Elibeth Salgado | R48: Enviado 30/12/2025, 12:14:26 p. m. | T48: Sí | U48: Entrega En Tienda | V48: Datafono Credibanco | W48: Bienvenida amor
A49: 90750 | B49: Jhonny Lidueña | C49: 573042985233 | D49: 45 | E49: 1× Bouquet Gerbera | F49: los robles | G49: Daniela González | H49: Calle 48a 16 sur 19 - Casa | I49: 3023584769 | J49: 46021 | K49: 0.625 | M49: 180000 | N49: 46021 | O49: 11:52 | P49: TERMINADO | Q49: Elibeth Salgado | R49: Enviado 30/12/2025, 11:52:32 a. m. | T49: No | V49: Transferencia 5431
A50: 90749 | B50: Jaime Fernandez | C50: 573004917332 | D50: 68 | E50: 1× Virgen Guadalupe o Milagrosa Grande | F50: Entrega En Tienda | G50: Jaime Fernandez | H50: Entrega En Tienda - Entrega En Tienda | I50: 3004917332 | J50: 46021 | K50: 0 | M50: 200000 | N50: 46021 | O50: 11:51 | P50: TERMINADO | Q50: Cristina Arrieta | R50: Enviado 30/12/2025, 11:51:40 a. m. | T50: Sí | U50: Entrega En Tienda | V50: Datafono Credibanco
A51: 90748 | B51: Daniela Bojanini | C51: 4.40045e+15 | D51: 95 | E51: 1× Arreglo Personalizado | F51: san vicente | G51: Jackie Bojanini | H51: cra. 53 # 82-93 edificio Danielle apto 6 - Edificio | I51: 3205389039 | J51: 46021 | K51: 0.58333333 | M51: 6000 | N51: 46021.486 | O51: 11:39 | P51: TERMINADO | Q51: Elibeth Salgado | R51: Enviado 30/12/2025, 11:40:24 a. m. | T51: No | U51: Zona 3 | V51: Datafono Credibanco | W51: canasto surtido
A52: 90747 | B52: Thalia Zambrano | C52: 573008060488 | D52: 7 | E52: 1× Flora Box Mediana Aire | F52: caujaral | G52: Kate Gómez | H52: Calle 8#10-132 torre 7 apto 101 - Casa | I52: 3008060488 | J52: 46021 | K52: 0.01875 | M52: 285000 | N52: 46021.448 | O52: 10:59 | P52: TERMINADO | Q52: Elibeth Salgado | R52: Enviado 30/12/2025, 10:59:33 a. m. | T52: No | V52: Transferencia 4038
A53: 90746 | B53: María José Ospina Burgos | C53: 57313 7545246 | D53: 31 | E53: 1× Mini Box Hortensias y Mini Rosa | F53: Villa Carolina | G53: Isabella morón | H53: Cra 72#88-61 torre 6 apto 501 Edificio balcones de Andalucía 1 Villa Carolina - Edificio | I53: 3137545246 | J53: 46021 | K53: 0.48263889 | M53: 80000 | N53: 46021.434 | O53: 10:29 | P53: TERMINADO | Q53: Cristina Arrieta | R53: Enviado 30/12/2025, 10:30:35 a. m. | T53: No | U53: Zona 3 | V53: Transferencia 5431
A54: 90745 | B54: Leo Ariza Vásquez | C54: 573226471069 | D54: 95 | E54: 1× Arreglo Personalizado | F54: Ciudad Jardín Modelo | G54: Mairym | H54: Cra 41 f #83-18 - Casa | I54: 3022453560 | J54: 46021 | K54: 0.95833333 | M54: 81000 | N54: 46021 | O54: 10:21 | P54: TERMINADO | Q54: Elibeth Salgado | R54: Enviado 30/12/2025, 10:22:02 a. m. | T54: No | V54: Transferencia 5431 | W54: Quiero que el arreglo sea un bouquets, surtido entre hortensias, orquídeas, claveles y rosas, en lo posible colores pasteles, suaves. Un bouquets de los que valen 70.000
A55: 90744 | B55: Juan David Orozco | C55: 573218440050 | D55: 52 | E55: 1× Bouquet 12 Rosas Rojas | F55: Ciudad Jardín Modelo | G55: Andreina Arango | H55: Cra 42 no 80b-92 - Casa | I55: 3108763691 | J55: 46022 | K55: 0.375 | M55: 111000 | N55: 46021.423 | O55: 10:20 | P55: TERMINADO | Q55: Elibeth Salgado | R55: Enviado 30/12/2025, 10:20:54 a. m. | T55: No | V55: Transferencia 5431
A56: 90743 | B56: Carolina Guzman | C56: 573013215661 | D56: ? | E56: Bouquet de novia en cartuchos,gypso,lepidium y 3 rosas blancas y un botonier como foto | F56: La Concepción | G56: Carolina Guzman | H56: Entrega En Tienda - Entrega En Tienda | I56: 3013215661 | J56: 46021 | K56: 0.45833333 | M56: 100000 | N56: 46021.411 | O56: 09:58 | P56: TERMINADO | Q56: Cristina Arrieta | R56: Enviado 30/12/2025, 9:59:07 a. m. | T56: No | U56: Zona 1 | V56: Transferencia 6913 | W56: bouquet de novia y botinier como el de la foto en wpp
A57: 90742 | B57: Sebastian Rodriguez leon | C57: 573116729321 | D57: 20 | E57: 1× Flora Box Mediana Topiario | F57: Villa Santos | G57: Isabella arteta | H57: Carrera 50#107-110 - Conjunto villas de santoral Casa 27 | I57: 3116729321 | J57: 46021 | K57: 0.41666667 | M57: 210000 | N57: 46021.369 | O57: 09:06 | P57: TERMINADO | Q57: Cristina Arrieta | R57: Enviado 30/12/2025, 9:06:46 a. m. | T57: No | U57: Zona 4 | V57: Transferencia 5431
A58: 90741 | B58: Daniel José Durán Quiroz | C58: 573018702355 | D58: 51 | E58: 1× Bouquet 24 Rosas Rojas | F58: Altos del Prado | G58: Carolina de la hoz | H58: Cra. 51 #82-26 - Oficina contactamos | J58: 46021 | K58: 0 | M58: 188000 | N58: 46021 | O58: 08:47 | P58: TERMINADO | Q58: Elibeth Salgado | R58: Enviado 30/12/2025, 8:48:25 a. m. | T58: No | U58: Zona 2 | V58: Transferencia 4038 | W58: Ninguna solo la nota que pase
A59: 90740 | B59: Zulay Navarro | C59: 573011486903 | D59: 32 | E59: 1× Mini Box Surtida | F59: El Recreo | G59: Kelly Contreras | H59: Carrera 41 # 65b-17 TQM - Edificio | I59: 314 3438769 | J59: 46021 | K59: 0.41666667 | M59: 84000 | N59: 46020.465 | O59: 07:39 | P59: TERMINADO | Q59: James de la Cruz | R59: Enviado 30/12/2025, 7:40:01 a. m. | T59: No | U59: Zona 2 | V59: Transferencia 5431
A60: 90739 | B60: monica manga | C60: 573014591116 | D60: ? | E60: CANASTO GRANDE X 50 ROSAS ROJAS SIN EUCALIPTO | F60: Villa Campestre | G60: nidia martinez | H60: Calle 3 No 51B - 137 Corales 1 Casa 33 - Casa | J60: 46021 | K60: 0.39583333 | M60: 375000 | N60: 46021 | O60: 07:32 | P60: TERMINADO | Q60: James de la Cruz | R60: Enviado 30/12/2025, 7:33:03 a. m. | T60: No | U60: Zona 5 | V60: Cuentas Por Cobrar | W60: NO EUCALIPTO OJO ,EL ARREGLO ESE PERO EN CANASTO OJOOOOOOO
A61: 90738 | B61: JENNIFER TORRES | C61: 573183740725 | D61: 29 | E61: 1× Mini Box Orquidea | F61: Ciudad Jardín Modelo | G61: JENNIFER TORRES | H61: CLL 79B 42E - 323 APT 201 EDIFICIO HANABERT - Casa | I61: 318 3740725 | J61: 46021 | K61: 0 | M61: 91000 | N61: 46020.753 | O61: 18:30 | P61: TERMINADO | Q61: Elibeth Salgado | R61: Enviado 29/12/2025, 6:31:07 p. m. | T61: No | V61: Transferencia 5431
A62: 90737 | B62: ANUAR MEOLA | C62: 57195739533 | D62: 45 | ? | E62: 1× Bouquet Gerbera | 1× Bouquet Flora Antique | F62: Entrega En Tienda | G62: ANUAR MEOLA | H62: Entrega En Tienda - Entrega En Tienda | I62: 195739533 | J62: 46020 | K62: 0 | M62: 330000 | N62: 46020.75 | O62: 18:28 | P62: TERMINADO | Q62: Elibeth Salgado | R62: Enviado 29/12/2025, 6:29:01 p. m. | T62: Sí | U62: Entrega En Tienda | V62: Datafono Credibanco
A63: 90736 | B63: gabriela castro | C63: 570000 | D63: 46 | E63: bouquet surtido | F63: Entrega En Tienda | G63: gabriela castro | H63: Entrega En Tienda - Entrega En Tienda | I63: 0 | J63: 46020 | K63: 0 | M63: 70000 | N63: 46020 | O63: 18:23 | P63: TERMINADO | Q63: James de la Cruz | R63: Enviado 29/12/2025, 6:23:54 p. m. | T63: Sí | U63: Entrega En Tienda | V63: Efectivo
A64: 90735 | B64: Grace Forero | C64: 573205468224 | D64: 1 | E64: 1× Flora Box Redonda 24 Rosas de Jardín | F64: Miramar | G64: Patricia goenaga | H64: TV 44 #100-82 depto 732 Torre 8 conjunto tozcana - Edificio | I64: 3045387746 | J64: 46021 | K64: 0.33333333 | M64: 312000 | N64: 46020.664 | O64: 16:56 | P64: TERMINADO | Q64: Cristina Arrieta | R64: Enviado 29/12/2025, 4:56:53 p. m. | T64: No | U64: Zona 4 | V64: Transferencia 5431
A65: 90733 | B65: Andrea Gutierrez | C65: 573018964911 | D65: 68 | E65: 1× Virgen Guadalupe o Milagrosa Grande | F65: La Campiña | G65: Nicolle Del Valle | H65: Cra 43b #90-138 - Casa | J65: 46020 | K65: 0.70833333 | M65: 209000 | N65: 46020.687 | O65: 16:39 | P65: TERMINADO | Q65: James de la Cruz | R65: Enviado 29/12/2025, 4:39:36 p. m. | T65: No | U65: Zona 4 | V65: Transferencia Jaque | W65: Dentro de lo posible, flores moradas, rosadas
A66: 90732 | B66: GABRIEL BARBOSA | C66: 573158664163 | D66: ? | E66: 1× Bouquet 12 Rosas Rosadas | F66: Entrega En Tienda | G66: GABRIEL BARBOSA | H66: Entrega En Tienda - Entrega En Tienda | J66: 46020 | K66: 0.70833333 | M66: 100000 | N66: 46020.692 | O66: 16:36 | P66: TERMINADO | Q66: Elibeth Salgado | R66: Enviado 29/12/2025, 4:37:22 p. m. | T66: Sí | U66: Entrega En Tienda | V66: Transferencia 5431
A67: 90731 | B67: Stefee Agudelo | C67: 17863700214 | D67: 5 | E67: 1× Flora Box Romantic Flores 24 Rosas | F67: la victoria | G67: Neyra Sánchez | H67: Calle 45 No. 10E 107 - Casa | I67: 300 7595042 | J67: 46020 | K67: 0 | M67: 238000 | N67: 46020.625 | O67: 15:56 | P67: TERMINADO | Q67: Cristina Arrieta | R67: Enviado 29/12/2025, 3:56:40 p. m. | T67: No | V67: Transferencia 4038
A68: 90730 | B68: Laura Bent Borrero | C68: 573108042766 | D68: ? | E68: 1× Mini Box Hortensias y Mini Rosa OJO HORTENCIA AZUL Y MINI ROSAS BLANCAS | F68: Campo Alegre | G68: María Alejandra Doria | H68: Carrera 41C #84-107 detrás del conjunto atardeceres, esquina, campo alegre - Conjunto | I68: 3015182932 | J68: 46020 | K68: 0.70833333 | M68: 86000 | N68: 46020 | O68: 15:55 | P68: TERMINADO | Q68: Adriana Suarez | R68: Enviado 29/12/2025, 3:55:13 p. m. | T68: No | U68: Zona 4 | V68: Transferencia 5431
A69: 90729 | B69: santigo londoño | C69: 573165317948 | D69: 52 | E69: 1× Bouquet 12 Rosas Rojas | F69: Entrega En Tienda | G69: santigo londoño | H69: Entrega En Tienda - Entrega En Tienda | I69: 3165317948 | J69: 46020 | K69: 0.70833333 | M69: 100000 | N69: 46020 | O69: 15:44 | P69: TERMINADO | Q69: Elibeth Salgado | R69: Enviado 29/12/2025, 3:45:15 p. m. | T69: Sí | U69: Entrega En Tienda | V69: Datafono Credibanco
A70: 90728 | B70: Yuranys Vieira Oviedo | C70: 573017970570 | D70: 30 | E70: 1× Mini Box Claveles | F70: Altos de Riomar | G70: Annie | H70: Centro Comercial Plaza del Parque - Centro Comercial | J70: 46021 | K70: 0.375 | M70: 78000 | N70: 46020 | O70: 15:32 | P70: TERMINADO | Q70: Elibeth Salgado | R70: Enviado 29/12/2025, 3:32:26 p. m. | T70: No | U70: Zona 3 | V70: Transferencia 4038
A71: 90727 | B71: miller daniel montealegre trujillo | C71: 573019796476 | D71: 52 | E71: 2× Bouquet 12 Rosas Rojas | F71: Entrega En Tienda | G71: miller daniel montealegre trujillo | H71: Entrega En Tienda - Entrega En Tienda | I71: 3019796476 | J71: 46020 | K71: 0 | M71: 200000 | N71: 46020.645 | O71: 15:29 | P71: TERMINADO | Q71: Cristina Arrieta | R71: Enviado 29/12/2025, 3:29:42 p. m. | T71: Sí | U71: Entrega En Tienda | V71: Datafono Credibanco
A72: 90726 | B72: Melany Andrea Acosta Padilla | C72: 573146649148 | D72: 29 | E72: 1× Mini Box Orquidea | F72: San Salvador | G72: Melany Acosta | H72: Calle 85 #78D-26 edificio puerto real APT 708 - Edificio | I72: 3146649148 | J72: 46022 | K72: 0.375 | M72: 92000 | N72: 46020 | O72: 15:16 | P72: TERMINADO | Q72: Elibeth Salgado | R72: Enviado 29/12/2025, 3:16:49 p. m. | T72: No | U72: Zona 3 | V72: Transferencia 5431
A73: 90725 | B73: stefani echeverri | C73: 57000 | D73: 95 | E73: 1× Arreglo Personalizado | F73: Entrega En Tienda | G73: stefani echeverri | H73: Entrega En Tienda - Entrega En Tienda | J73: 46020 | K73: 0 | M73: 34000 | N73: 46020.608 | O73: 14:36 | P73: TERMINADO | Q73: Cristina Arrieta | R73: Enviado 29/12/2025, 2:37:17 p. m. | T73: Sí | U73: Entrega En Tienda | V73: Datafono Credibanco | W73: flores surtidas
A74: 90724 | B74: Nicolas Rodríguez | C74: 573142881716 | D74: 21 | E74: 1× Flora Box Mediana Pastel | F74: El Golf | G74: Nicolás | H74: calle 81#64-29. edf Rosa del parque, apto 4D - Edificio | I74: 3142881716 | J74: 46020 | K74: 0 | M74: 188000 | N74: 46020.585 | O74: 14:19 | P74: TERMINADO | Q74: James de la Cruz | R74: Enviado 29/12/2025, 2:19:11 p. m. | T74: No | U74: Zona 3 | V74: Link Bold | W74: Que la tarjeta diga: bienvenida a casa. Te amamos mucho!!
A75: 90723 | B75: Rita Rangel | C75: 573022601836 | D75: ? | E75: 1× Canasto Lavanda pero en tonos amarillos,no rosas | F75: La Unión | G75: Kra 8 # 30_ 158 torre de las palmas | H75: Kra 8 # 30_158 - Conjunto | I75: 3022601836 | J75: 46021 | K75: 0.33333333 | M75: 240000 | N75: 46020.581 | O75: 14:13 | P75: TERMINADO | Q75: Elibeth Salgado | R75: Enviado 29/12/2025, 2:13:47 p. m. | T75: No | U75: Zona 2 | V75: Transferencia 5431 | W75: ojo tonos amarillos
A76: 90722 | B76: claudia pacheco roca | C76: 573213335580 | D76: 53 | ? | ? | E76: 1× Bouquet 6 Rosas Rojas | 1× Ferrero Rocher 8 und | 1× Vino Espumoso JP. Chenet 175 ml | F76: Caribe Verde | G76: maría rodríguez | H76: Crr 8k N: 128/25 casa 100 ciudad caribe, Manzana 19 - Casa | I76: 3005468586 | J76: 46021 | K76: 0.41666667 | M76: 170000 | N76: 46020.578 | O76: 13:58 | P76: TERMINADO | Q76: Elibeth Salgado | R76: Enviado 29/12/2025, 1:59:02 p. m. | T76: No | U76: Zona 6 | V76: Transferencia 5431 | W76: ROSAS AMARILLAS
A77: 90721 | B77: ludwing landazabal | C77: 573182803558 | D77: 46 | E77: BOUQUET SURTIDO | F77: Altos del Prado | G77: maría angélica garcía | H77: cra 52B #94-226 apto 501 - Casa | I77: 3014145861 | J77: 46020 | K77: 0.625 | M77: 88000 | N77: 46020.567 | O77: 13:38 | P77: TERMINADO | Q77: Elibeth Salgado | R77: Enviado 29/12/2025, 1:38:55 p. m. | T77: No | U77: Zona 2 | V77: Datafono Credibanco
A78: 90720 | B78: Bleidys Barrios | C78: 573006836554 | D78: 62 | E78: 1× Guacal Hortensias | F78: La Victoria | G78: Para el amor de mi vida; Mi Mami | H78: Carrera 9E # 45B- 128 - Casa | I78: 3006836554 | J78: 46022 | K78: 0.625 | M78: 198000 | N78: 46020.48 | O78: 13:03 | P78: TERMINADO | Q78: Adriana Suarez | R78: Enviado 29/12/2025, 1:04:14 p. m. | T78: No | V78: Transferencia 4038
A79: 90719 | B79: Juan Carlos Márquez | C79: 573107272834 | D79: 29 | E79: 1× Mini Box Orquidea | F79: Villa Carolina | G79: Luz María | H79: Cra70 # 91-35 apartamento 103. Torre 1 parques del tivoli - Conjunto | I79: 3107272835 | J79: 46020 | K79: 0.625 | M79: 90000 | N79: 46020.528 | O79: 12:57 | P79: TERMINADO | Q79: Cristina Arrieta | R79: Enviado 29/12/2025, 12:57:39 p. m. | T79: No | U79: Zona 3 | V79: Transferencia 5431
A80: 90718 | B80: Juan Carlos Márquez | C80: 573107272834 | D80: 52 | E80: 1× Bouquet 12 Rosas Rojas | F80: El Golf | G80: Gladys pulgar | H80: Cra57#79-319 - Edificio | I80: 3107272835 | J80: 46020 | K80: 0.625 | M80: 108000 | N80: 46020 | O80: 12:56 | P80: TERMINADO | Q80: Elibeth Salgado | R80: Enviado 29/12/2025, 12:56:43 p. m. | T80: No | U80: Zona 3 | V80: Transferencia 5431
A81: 90717 | B81: ana karina lopez | C81: 573045710986 | D81: 95 | E81: 1× Arreglo Personalizado | F81: Riomar | G81: ana karina | H81: cra 53 # 64-226 - Casa | I81: 304 5710986 | J81: 46020 | K81: 0 | M81: 30000 | N81: 46020.518 | O81: 12:28 | P81: TERMINADO | Q81: Elibeth Salgado | R81: Enviado 29/12/2025, 12:29:20 p. m. | T81: No | U81: Zona 3 | V81: Transferencia 4038 | W81: 4 rosas blancas 4000 de gypso
A82: 90716 | B82: RICARDO RUMIE | C82: 57000 | D82: 95 | E82: 1× Arreglo Personalizado | F82: Entrega En Tienda | G82: RICARDO RUMIE | H82: Entrega En Tienda - Entrega En Tienda | I82: 0 | J82: 46020 | K82: 0 | M82: 77000 | N82: 46020.501 | O82: 12:02 | P82: TERMINADO | Q82: Cristina Arrieta | R82: Enviado 29/12/2025, 12:03:30 p. m. | T82: Sí | U82: Entrega En Tienda | V82: Datafono Credibanco | W82: FLORES SURTIDAS
A83: 90715 | B83: Darly Rincón | C83: 573208162910 | D83: 39 | E83: 1× Canasto Lavanda | F83: Lucero | G83: Jackeline | H83: Calle 53d #31-73 - Casa | J83: 46020 | K83: 0.58333333 | M83: 237000 | N83: 46020.372 | O83: 11:51 | P83: TERMINADO | Q83: Elibeth Salgado | R83: Enviado 29/12/2025, 11:51:24 a. m. | T83: No | U83: Zona 2 | V83: Transferencia 4966 | W83: Nuestra mamá acaba de llegar a casa después de un fuerte accidente, por favor llenen el ramo de amor y gratitud.
A84: 90714 | B84: FUNDACION CON AMOR SOCIAL , | C84: 573002627762 | D84: 95 | E84: 1× Arreglo Personalizado | F84: Entrega En Tienda | G84: FUNDACION CON AMOR SOCIAL | H84: Entrega En Tienda - Entrega En Tienda | J84: 46020 | K84: 0 | M84: 10000 | N84: 46020.489 | O84: 11:46 | P84: TERMINADO | Q84: Cristina Arrieta | R84: Enviado 29/12/2025, 11:46:38 a. m. | T84: Sí | U84: Entrega En Tienda | V84: Cuentas Por Cobrar | W84: rosas rojas,pino,hipérico rojo
A85: 90713 | B85: Mauricio Vergara Danies | C85: 573188833795 | D85: 5 | E85: 1× Flora Box Romantic Flores 12 Rosas | F85: Villa Country | G85: Viviana | H85: Cra 51 No 79 85 Aopt 904 - Edificio | J85: 46020 | K85: 0.58333333 | M85: 198000 | N85: 46020.476 | O85: 11:36 | P85: TERMINADO | Q85: Elibeth Salgado | R85: Enviado 29/12/2025, 11:36:46 a. m. | T85: No | U85: Zona 3 | V85: Transferencia 6913
A86: 90712 | B86: Kaira De la hoz | C86: 573022820261 | D86: 32 | E86: 1× Mini Box Surtida | F86: El Prado | G86: Kaira | H86: Cra 53 #72-169 oficina bancoomeva - Oficina | I86: 3022820261 | J86: 46020 | K86: 0.58333333 | M86: 82000 | N86: 46020 | O86: 11:31 | P86: TERMINADO | Q86: Cristina Arrieta | R86: Enviado 29/12/2025, 11:31:15 a. m. | T86: No | U86: Zona 1 | V86: Transferencia 5431
A87: 90711 | B87: Dilan Bolaño | C87: 573186670707 | D87: 66 | E87: 1× Marquito Girasol | F87: Villa Country | G87: Kendry Fernandez | H87: Cl. 77b #59b-27, Nte. Centro Historico, Barranquilla, Atlántico - Oficina | I87: 3147156623 | J87: 46020 | K87: 0.58333333 | M87: 128000 | N87: 46020.457 | O87: 11:20 | P87: TERMINADO | Q87: Cristina Arrieta | R87: Enviado 29/12/2025, 11:20:48 a. m. | T87: No | U87: Zona 3 | V87: Transferencia 5431
A88: 90710 | B88: Rocío Chapman | C88: 13053384931 | D88: ? | E88: Cnasta de frutas con girasoles,no tantas flores | F88: Altos del Prado | G88: enrique chapman | H88: Carrera. 55 # 82158 - Casa | J88: 46020 | K88: 0.58333333 | M88: 228000 | N88: 46020 | O88: 11:07 | P88: TERMINADO | Q88: Elibeth Salgado | R88: Enviado 29/12/2025, 11:08:08 a. m. | T88: No | U88: Zona 2 | V88: Link Bold | W88: ponerle girasoles no tantas flores
A89: 90709 | B89: Mauricio Ortiz | C89: 573003182878 | D89: ? | E89: 2 centros de mesa en base de madera alargado como foto uno en blanco y otro con rojo | G89: Mauricio Ortiz | H89: 000 - Casa | I89: 3003182878 | J89: 46021 | K89: 0.41666667 | M89: 0 | N89: 46020.431 | O89: 10:22 | P89: TERMINADO | Q89: Elibeth Salgado | R89: Enviado 29/12/2025, 10:22:42 a. m. | T89: No | V89: Obsequio | W89: centros de mesa como foto uno en blanco y otro con rojo
A90: 90708 | B90: Carla Grosso | C90: 573173694439 | D90: 62 | E90: 1× Guacal Hortensias | F90: Altos del Prado | G90: David y Carla | H90: Cra 52 n 82-161 ed asturia ap 7 - Edificio | I90: 3215017309 | J90: 46020 | K90: 0.4375 | M90: 188000 | N90: 46020.399 | O90: 09:40 | P90: TERMINADO | Q90: Elibeth Salgado | R90: Enviado 29/12/2025, 9:41:25 a. m. | T90: No | U90: Zona 2 | V90: Transferencia 5431
A91: 90707 | B91: Zilary Gamarra | C91: 573013645460 | D91: 70 | E91: 1× Cerámica Sweet Pea | F91: Las Delicias | G91: Iveth Mejía | H91: Calle 69C #39-73 apto 3B - Edificio | J91: 46020 | K91: 0.45833333 | M91: 103000 | N91: 46020.396 | O91: 09:34 | P91: TERMINADO | Q91: Cristina Arrieta | R91: Enviado 29/12/2025, 9:35:00 a. m. | T91: No | U91: Zona 2 | V91: Transferencia 4038 | W91: Es un regalo de cumpleaños que ojalá llegue en la mañana de hoy
A92: 90706 | B92: Natalia Gutiérrez | C92: 573215408807 | D92: 3 | E92: 1× Flora Box Redonda Orquídea | F92: Altos de Riomar | G92: Sofía Pérez Gutiérrez | H92: Cra 59 # 96-153 Apto 1103 Edificio Bruxxel - Edificio | I92: 3215408807 | J92: 46020 | K92: 0.45833333 | M92: 358000 | N92: 46020.361 | O92: 08:50 | P92: TERMINADO | Q92: Elibeth Salgado | R92: Enviado 29/12/2025, 8:50:59 a. m. | T92: No | U92: Zona 3 | V92: Transferencia 4966
A93: 90705 | B93: Juan Oñate | C93: 573013708185 | D93: 32 | E93: 1× Mini Box Surtida | F93: La Victoria | G93: Ruby Milena Ariza | H93: ⁠Carrera 10B #45c2-117 - Casa | J93: 46020 | K93: 0.41666667 | M93: 88000 | N93: 46020 | O93: 08:23 | P93: TERMINADO | Q93: Elibeth Salgado | R93: Enviado 29/12/2025, 8:24:03 a. m. | T93: No | V93: Transferencia 4966
A94: 90704 | B94: Balerina Herrera | C94: 573107131591 | D94: 46 | E94: 1× Bouquet Surtido | F94: Entrega En Tienda | G94: Balerina Herrera | H94: k | I94: 3107131591 | J94: 46020 | K94: 0.41666667 | M94: 300000 | N94: 46018.816 | O94: 07:56 | P94: TERMINADO | Q94: James de la Cruz | R94: Enviado 29/12/2025, 7:56:40 a. m. | T94: Sí | U94: Entrega En Tienda | V94: Transferencia 4966
A95: 90703 | B95: MARIA CLAUDIA 0 | C95: 570000 | D95: 95 | E95: 1× Arreglo Personalizado | F95: Entrega En Tienda | G95: 0 | H95: Entrega En Tienda - Entrega En Tienda | J95: 46018 | K95: 0 | M95: 30000 | N95: 46018.701 | O95: 16:50 | P95: TERMINADO | Q95: Elibeth Salgado | R95: Enviado 27/12/2025, 4:50:29 p. m. | T95: Sí | U95: Entrega En Tienda | V95: Efectivo | W95: FLORES SURTIDAS
A96: 90702 | B96: movich , | C96: 573007682024 | D96: 95 | E96: 1× Arreglo Personalizado | F96: Entrega En Tienda | G96: movich | H96: Entrega En Tienda - Entrega En Tienda | I96: 3007682024 | J96: 46018 | K96: 0 | M96: 0 | N96: 46018 | O96: 16:37 | P96: TERMINADO | Q96: Cristina Arrieta | R96: Enviado 27/12/2025, 4:38:06 p. m. | T96: Sí | U96: Entrega En Tienda | V96: Cuentas Por Cobrar | W96: PLAN BÁSICO 9 ROSAS ROSADAS (X2)
A97: 90701 | B97: maría isaza | C97: 570000 | D97: 95 | E97: 1× Arreglo Personalizado | F97: Entrega En Tienda | G97: maría isaza | H97: Entrega En Tienda - Entrega En Tienda | I97: 0 | J97: 46018 | K97: 0 | M97: 10000 | N97: 46018 | O97: 16:33 | P97: TERMINADO | Q97: Elibeth Salgado | R97: Enviado 27/12/2025, 4:33:24 p. m. | T97: Sí | U97: Entrega En Tienda | V97: Efectivo | W97: flores surtidas
A98: 90700 | B98: luis fernando guzman | C98: 574636715 | D98: 95 | E98: 1× Arreglo Personalizado | F98: Entrega En Tienda | G98: luis fernando guzman | H98: Entrega En Tienda - Entrega En Tienda | I98: 4636715 | J98: 46018 | K98: 0 | M98: 35000 | N98: 46018 | O98: 16:32 | P98: TERMINADO | Q98: Cristina Arrieta | R98: Enviado 27/12/2025, 4:32:55 p. m. | T98: Sí | U98: Entrega En Tienda | V98: Transferencia 6913 | W98: bouquet surtido
A99: 90699 | B99: Elkin salcedo | C99: 573155252368 | D99: 17 | E99: 1× Flora Gift Box Rosa Roja JP | F99: Bostón | G99: yenis baloco | H99: calle 65 47 45 edificio realix primer piso - Casa | I99: 3155252368 | J99: 46018 | K99: 0 | M99: 275000 | N99: 46018.679 | O99: 16:18 | P99: TERMINADO | Q99: Elibeth Salgado | R99: Enviado 27/12/2025, 4:19:19 p. m. | T99: No | U99: Zona 2 | V99: Transferencia 5431
A100: 90698 | B100: cielo rodríguez | C100: 573016260061 | D100: 41 | E100: 1× Canasto Mediano Sweet | F100: Entrega En Tienda | G100: cielo rodríguez | H100: Entrega En Tienda - Entrega En Tienda | I100: 3016260061 | J100: 46018 | K100: 0 | M100: 150000 | N100: 46018 | O100: 15:57 | P100: TERMINADO | Q100: Cristina Arrieta | R100: Enviado 27/12/2025, 3:58:16 p. m. | T100: Sí | U100: Entrega En Tienda | V100: Transferencia 6913
...

Sheet Domicilios
A1: N°Pedido | B1: Cliente | C1: Telefono | D1: Producto | E1: Dirección de Entrega | F1: Barrio | G1: Destinatario | H1: TelefonoDestino | I1: Domiciliario | J1: TelefonoDomiciliario | K1: Externo | L1: Estado Domicilio | M1: FechaAsignación | N1: FechaEntrega | O1: Observaciones | P1: Zona | Q1: Foto | R1: Hora_Salida | S1: Hora_Entrega
A2: 92993 | B2: Danna sanjuanelo | C2: 573003346799 | D2: 1× Corazón Mini Surtido M/12 | E2: Recoger en Tienda | F2: Recoger en Tienda | G2: Danna sanjuanelo | H2: 573003346799 | K2: 46089.687 | L2: Pendiente | M2: 03/08/2026 16:29:47 | N2: 03/08/2026 - 17:00:00 | R2: 46076.613 | S2: 46076.645
A3: 92987 | B3: alex avilez | C3: 573205423436 | D3: 1 BOUQUET X 12 ROSAS ROSADAS Y BLANCAS | E3: Calle 110 No 49e-86 condominio isabella - APTO: 301 TORRE: 1 | F3: Villa Santos | G3: DANIELA JARABA | H3: 573008834542 | I3: EXT - Juan David | K3: 46089.669 | L3: En Ruta | M3: 03/08/2026 16:03:52 | N3: 03/08/2026 - 16:30:00 | P3: Zona 4 | R3: 46076.613 | S3: 46076.627
A4: 92986 | B4: María andrea Rodríguez | C4: 573006498138 | D4: 1× Mini Box Orquidea M/22 | E4: Cra 59b #91-74 - edificio Trivento apto 1201 | F4: Altos de Riomar | G4: Isabella | H4: 573157496731 | I4: EXT - Moni | K4: 46089.7 | L4: Entregado | M4: 03/08/2026 16:47:54 | N4: 03/08/2026 - 04:00:00 | P4: Zona 3 | R4: 46074.449 | S4: 46074.45
A5: 92983 | B5: Mauricio Andrés Figueroa Ricardo | C5: 573148167126 | D5: 1× Bouquet Aire M/7 | E5: Calle 70B#41-87 - Clínica Santa ana | F5: Delicias | G5: Mauricio Figueroa | H5: 573148167126 | K5: 46089.673 | L5: Pendiente | M5: 03/08/2026 16:08:32 | N5: 03/08/2026 - 16:00:00 | R5: 46074.46 | S5: 46076.456
A6: 92980 | B6: Danna sanjuanelo | C6: 573003346799 | D6: 1× Flora Mini Plus Box Redonda M/28 | E6: Cra 50#61-172 | F6: El Prado | G6: Mileidy segura | H6: 573114100464 | I6: EXT - William Osorio | K6: 46089.672 | L6: Entregado | M6: 03/08/2026 16:07:24 | N6: 03/08/2026 - 17:00:00 | P6: Zona 1 | R6: 46076.613 | S6: 46076.623
A7: 92979 | B7: Joiker Alejandro | C7: 573126314688 | D7: 1× Mini Box Orquidea M/22 | 1× Ferrero Rocher 8 und | E7: Recoger en Tienda | F7: Recoger en Tienda | G7: Joiker Alejandro | H7: 573126314688 | K7: 46089.678 | L7: Pendiente | M7: 03/08/2026 16:16:50 | N7: 03/08/2026 - 17:00:00 | R7: 46076.528 | S7: 46076.583
A8: 92978 | B8: Javier Chacon | C8: 573117169931 | D8: 1× Corazón Mini Surtido M/12 | 1× Oso de Peluche | E8: Carrera 52 #106-140 - Casa 94 | F8: Riomar | G8: Madeleine Vecino | H8: 573004400740 | K8: 46089.651 | L8: En Ruta | M8: 03/08/2026 15:37:11 | N8: 03/08/2026 - 04:00:00 | P8: Zona 3
A9: 92977 | B9: David Gomez | C9: 573044408100 | D9: 1× Mini Box Orquidea M/22 | E9: Calle 99 #56-48 edificio Santillana - Torre 2 apto 1606 | F9: Altos de Riomar | G9: Santillana | H9: 573044408100 | I9: EXT - Moni | K9: 46089.683 | L9: Entregado | M9: 03/08/2026 16:23:45 | N9: 03/08/2026 - 04:00:00 | P9: Zona 3 | R9: 46089.717 | S9: 46089.718
A10: 92975 | B10: Andrés Serret | C10: 573015889880 | D10: 1× Mini Box Clavel Fucsia M/20 | E10: Recoger en Tienda | F10: Recoger en Tienda | G10: Andrés Serret | H10: 573015889880 | K10: 46089.616 | L10: Pendiente | M10: 03/08/2026 14:47:21 | N10: 03/08/2026 - 00:00:00
A11: 92974 | B11: Nicolás Fuentes | C11: 573155928344 | D11: 1× Mini Box Orquidea M/22 | E11: Cra. 58 #98-71 | F11: Riomar | G11: Raquel Padilla Quintana | I11: EXT - Moni | K11: 46089.679 | L11: Entregado | M11: 03/08/2026 16:17:11 | N11: 03/08/2026 - 00:00:00 | P11: Zona 3 | R11: 46089.716 | S11: 46076.526
A12: 92973 | B12: Nico Sanchez | C12: 3004612667 | D12: 1× Corazón Mini Surtido M/12 | E12: Calle 1A #30-61 - Apto 511 torre 2 | F12: Riomar | G12: Sofía vueltas | H12: 573044233449 | I12: Elvis | K12: 46089.65 | L12: En Ruta | M12: 03/08/2026 15:36:16 | N12: 03/08/2026 - 16:00:00 | P12: Zona 3
A13: 92971 | B13: Adrián Raya Carmona | C13: 34644380068 | D13: 1× Guacal Hortensias M/13 | 1× Mini Box Orquidea M/22 | E13: Calle 68 # 32 - 56 - Apto 2 | F13: Olaya | G13: Anna Stand | H13: 573508401213 | I13: Oscar | K13: 46089.673 | L13: Entregado | M13: 03/08/2026 16:09:14 | N13: 03/08/2026 - 04:30:00 | P13: Zona 2
A14: 92969 | B14: Samia Maloof | C14: 573007524271 | D14: 1× Mini Box Orquidea M/22 | 1× Bouquet 6 Rosas Rojas M/10 | E14: Cra 57 # 81 100 - Casa | F14: El Golf | G14: Samia | H14: 573007524271 | I14: EXT - William Osorio | K14: 46089.66 | L14: Entregado | M14: 03/08/2026 15:50:08 | N14: 03/08/2026 - 15:00:00 | P14: Zona 3 | R14: 46076.574 | S14: 46076.574
A15: 92968 | B15: Nico Sanchez | C15: 30043004612667 | D15: 1× Corazón Mini Surtido M/12 | E15: Cra 52#106-140 - Castellana real | F15: Riomar | G15: Emna Sánchez | H15: 573004612667 | I15: Elvis | K15: 46089.618 | L15: En Ruta | M15: 03/08/2026 14:50:29 | N15: 03/08/2026 - 16:00:00 | P15: Zona 3 | R15: 46076.575 | S15: 46076.575
A16: 92967 | B16: Juan pablo Muñoz gomez | C16: 573013894849 | D16: 1× Flora Box Romantic Flores 12 Rosas M/18 | E16: Carrera52#132-87 - Casa 28 | F16: Villa Campestre | G16: Marasha elite | H16: 573013894849 | I16: Elvis | K16: 46089.654 | L16: En Ruta | M16: 03/08/2026 15:41:10 | N16: 03/08/2026 - 04:00:00 | P16: Zona 5 | R16: 46078.382 | S16: 46078.382
A17: 92966 | B17: Yamal Saghair | C17: 573008446022 | D17: 1× Mini Box Orquidea M/22 | E17: Calle 97 #42f-43 Mirador del mar 2 - Torre 1 apto 204 | F17: Miramar | G17: Keyla | H17: 573012615857 | K17: 46089.63 | L17: Pendiente | M17: 03/08/2026 15:07:53 | N17: 03/08/2026 - 16:00:00 | P17: Zona 4 | R17: 46076.607 | S17: 46076.607
A18: 92965 | B18: Gerardo Ortega | C18: 573208395916 | D18: 1× Bouquet 24 Rosas Rojas M/8 | E18: Cra58#96-158 - Apto 1201 | F18: Altos de Riomar | G18: Micaela Adelaida | H18: 573004056966 | I18: EXT - Moni | K18: 46089.615 | L18: Entregado | M18: 03/08/2026 14:45:12 | N18: 03/08/2026 - 15:00:00 | P18: Zona 3 | R18: 46076.64 | S18: 46076.64
A19: 92964 | B19: Gustavo Cantero | C19: 573009477121 | D19: 1× Bouquet 12 Rosas Rojas M/9 | E19: calle 77 #57-85 - villa fontana , casa 13 | F19: Villa Country | G19: Angie Rincon | H19: 573053042125 | I19: Oscar | K19: 46089.586 | L19: Entregado | M19: 03/08/2026 14:04:09 | N19: 03/08/2026 - 04:00:00 | P19: Zona 3 | R19: 46076.654 | S19: 46076.654
A20: 92963 | B20: Daniel Maestre | C20: 573188709938 | D20: 1× Bouquet 24 Rosas Rojas M/8 | E20: Calle 104 #49e-70 - Casa 1 | F20: Villa Santos | G20: Ana serrano | H20: 573215461190 | I20: EXT - Moni | K20: 46089.607 | L20: Entregado | M20: 03/08/2026 14:33:47 | N20: 03/08/2026 - 16:00:00 | P20: Zona 4 | R20: 46076.686 | S20: 46076.686
A21: 92962 | B21: Jose Llanos | C21: 573052325427 | D21: 1× Mini Box Orquidea M/22 | 1× Mini Box Clavel Fucsia M/20 | E21: Recoger en Tienda | F21: Recoger en Tienda | G21: Jose Llanos | H21: 573052325427 | K21: 46089.586 | L21: Pendiente | M21: 03/08/2026 14:03:50 | N21: 03/08/2026 - 02:00:00 | R21: 46076.759 | S21: 46076.759
A22: 92961 | B22: Ana María Martínez | C22: 573152727192 | D22: 1× Mini Box Orquidea M/22 | E22: Cra 64d #85-179 - Edificio macarol apto 501 | F22: Altos de Riomar | G22: Ana Marcela Martinez | H22: 573156165550 | I22: EXT - Moni | K22: 46089.663 | L22: Entregado | M22: 03/08/2026 15:54:27 | N22: 03/08/2026 - 15:00:00 | P22: Zona 3 | R22: 46077.359 | S22: 46077.359
A23: 92960 | B23: Carlos Bayuelo | C23: 310 6376698 | D23: 1× Mini Box Orquidea M/22 | 1× Flora Mini Plus Box Redonda M/28 | 1× Corazón Mini Surtido M/12 | E23: Recoger en Tienda | F23: Recoger en Tienda | G23: Carlos Bayuelo | H23: 573106376698 | K23: 46089.673 | L23: Pendiente | M23: 03/08/2026 16:08:44 | N23: 03/08/2026 - 03:00:00 | R23: 46077.48 | S23: 46077.48
A24: 92959 | B24: Pedro Marquez | C24: 573105585460 | D24: 1× Encanto lila M/15 | E24: Cr 48 no 100-78 - Edifio Lanzerotti Apto 201 | F24: Villa Santos | G24: Daniela Orozco | H24: 573105585460 | I24: Elvis | K24: 46089.625 | L24: En Ruta | M24: 03/08/2026 14:59:54 | N24: 03/08/2026 - 04:00:00 | P24: Zona 4 | R24: 46077.386 | S24: 46077.386
A25: 92958 | B25: Juan Esteban Camacho Reyes | C25: 573005273265 | D25: 1× Corazón Mini Surtido M/12 | 1× Ferrero Rocher 8 und | E25: Calle 88#42e43 - Casa 2 pisos | F25: Los Nogales | G25: Marcela Ariza | H25: 573012112234 | I25: EXT - Moni | K25: 46089.595 | L25: Entregado | M25: 03/08/2026 14:17:17 | N25: 03/08/2026 - 15:00:00 | P25: Zona 4 | R25: 46077.405 | S25: 46077.405
A26: 92957 | B26: Madeleine Vecino | C26: 573004400740 | D26: 1× Mini Box Orquidea M/22 | E26: Carrera 52 # 106-140 - Casa 94 Conjunto castellana real | F26: Villa Santos | G26: Madelein Chacón | H26: 573004400740 | I26: Elvis | K26: 46089.617 | L26: En Ruta | M26: 03/08/2026 14:48:32 | N26: 03/08/2026 - 15:00:00 | P26: Zona 4 | R26: 46077.439 | S26: 46077.439
A27: 92956 | B27: Ronald Bayena | C27: 573154447302 | D27: 1× Bouquet 12 Rosas Rojas M/9 | 1× Vino Blanco Terra Vega | E27: Calle 82a#42-09 | F27: Los Nogales | G27: Sophia Ludovica | H27: 573045724174 | I27: EXT - Moni | K27: 46089.623 | L27: Entregado | M27: 03/08/2026 14:57:49 | N27: 03/08/2026 - 03:00:00 | P27: Zona 4 | R27: 46077.483 | S27: 46077.483
A28: 92955 | B28: Leonardo Daniel Meza Cantillo | C28: 3107063615 | D28: 1× Corazón Mini Surtido M/12 | E28: Cra 50 #74-126 - Edificio gaviotas | F28: Villa Country | G28: Shaila Arrieta | H28: 573005435875 | I28: EXT - William Osorio | K28: 46089.704 | L28: Entregado | M28: Sun Mar 08 2026 16:56:31 GMT-0500 (hora estándar de Colombia) | N28: 03/08/2026 - 15:00:00 | P28: Zona 3 | R28: 46077.517 | S28: 46077.517
A29: 92954 | B29: Franklin Pineres | C29: 573116629388 | D29: 1× Flora Box Sembrado 9 Rosas M/20 | E29: Cr 26c7 # 75b - 50 - Casa blanca 1er Piso | F29: El Silencio | G29: Emily Acuña | H29: 573163764650 | I29: Oscar | K29: 46089.63 | L29: Entregado | M29: 03/08/2026 15:07:28 | N29: 03/08/2026 - 03:00:00 | P29: Zona 2 | R29: 46077.617 | S29: 46077.617
A30: 92953 | B30: Emelis Orozco | C30: 573052429073 | D30: 1× Bouquet 12 Rosas Rojas M/9 | E30: Cra. 59b # 58 - 57 - Casa | F30: El Prado | G30: Isabel Cristina | H30: 573002866923 | I30: EXT - Javier | K30: 46089.641 | L30: Entregado | M30: 03/08/2026 15:22:36 | N30: 03/08/2026 - 16:00:00 | P30: Zona 1 | R30: 46077.621 | S30: 46077.621
A31: 92951 | B31: Juan Diego Molina Peñate | C31: 573043117743 | D31: 1× Cerámica Sweet Pea M/16 | E31: Cra. 30 #2C - 196 Edif River Place Torre 1 APTO 304 | F31: Villa Campestre | G31: Juan Diego Molina Peñate | H31: 573043117743 | I31: Elvis | K31: 46089.616 | L31: En Ruta | M31: 03/08/2026 14:46:34 | N31: 03/08/2026 - 15:00:00 | P31: Zona 5 | R31: 46077.621 | S31: 46077.621
A32: 92950 | B32: Geraldine Herrera | C32: 573150491518 | D32: 1× Mini Box Orquidea M/22 | E32: Recoger en Tienda | F32: Recoger en Tienda | G32: ISABEL PEÑA PUCHE | H32: 573150491518 | K32: 46089.575 | L32: Pendiente | M32: 03/08/2026 13:47:34 | N32: 03/08/2026 - 13:00:00 | R32: 46077.643 | S32: 46077.643
A33: 92949 | B33: Esteban Correa | C33: 573015245531 | D33: Cerámica Sweet Pea M/16 | E33: Carrera 59#96-78 - Edif ferrara apto10A | F33: Altos de Riomar | G33: Liliana Payares | H33: 573184187111 | I33: Elvis | K33: 46089.661 | L33: En Ruta | M33: 03/08/2026 15:51:12 | N33: 03/08/2026 - 14:00:00 | P33: Zona 3 | R33: 46077.656 | S33: 46077.656
A34: 92948 | B34: sebastian escalante | C34: 573244514045 | D34: 1× Bouquet 6 Rosas Rojas M/10 | E34: Carrera 18 #51-23 Casa | F34: San José | G34: Diana | I34: EXT - Javier | K34: 46089.619 | L34: En Ruta | M34: 03/08/2026 14:51:45 | N34: 03/08/2026 - 14:00:00 | P34: Zona 2 | R34: 46077.671 | S34: 46077.671
A35: 92947 | B35: 3246899919 | C35: 573246899919 | D35: 1× Mini Box Orquidea M/22 | E35: Carrera 47 #102-170 - Apto 201 - torre 2 | F35: Villa Santos | G35: Ble | H35: 573246899919 | I35: Oscar | K35: 46089.603 | L35: Entregado | M35: 03/08/2026 14:27:39 | N35: 03/08/2026 - 02:00:00 | P35: Zona 4 | R35: 46077.682 | S35: 46077.682
A36: 92946 | B36: Santiago Ramón Blanco Estrada | C36: 573028023810 | D36: 1× Corazón Mini Surtido M/12 | E36: Cra7A#45D-54 - Casa | F36: Buenos Aires | G36: Marcela Pérez | H36: 573028023810 | I36: EXT - Javier | K36: 46089.569 | L36: Entregado | M36: 03/08/2026 13:39:50 | N36: 03/08/2026 - 03:00:00 | P36: Zona 2 | R36: 46077.731 | S36: 46077.731
A37: 92943 | B37: Jonathan orozco valencia | C37: 573013506011 | D37: 1× Canasto Mediano Sweet M/4 | E37: Cra 75#78-54 - Torre 7 apto 101 | F37: Paraíso | G37: Alix Gómez | H37: 573013506011 | I37: Elvis | K37: 46089.598 | L37: Entregado | M37: 03/08/2026 14:21:20 | N37: 03/08/2026 - 14:00:00 | P37: Zona 3 | R37: 46077.731 | S37: 46077.731
A38: 92942 | B38: Jonathan orozco valencia | C38: 573013506011 | D38: 1× Guacal Hortensias M/13 | E38: Cra 75#78-54 - Torre 7 apto 101 | F38: Paraíso | G38: Diana valencia | H38: 573013506011 | I38: Elvis | K38: 46089.599 | L38: Entregado | M38: 03/08/2026 14:22:18 | N38: 03/08/2026 - 14:00:00 | P38: Zona 3 | R38: 46077.734 | S38: 46077.734
A39: 92941 | B39: Elizabeth Martinez de Iguaran | C39: 573114239021 | D39: 1× Bouquet 6 Rosas Rojas M/10 | 1× Ferrero Rocher 8 und | E39: Centro comercial Viva, restaurante Olivia - Centro comercial Viva, restaurante Olivia | F39: Centro | G39: Elizabeth Martinez de Iguaran | H39: 573114239021 | K39: 46089.535 | L39: Pendiente | M39: 03/08/2026 12:50:52 | N39: 03/08/2026 - 03:00:00 | P39: Zona 2 | R39: 46077.735 | S39: 46077.735
A40: 92940 | B40: Edgardo Ramírez | C40: 573243585945 | D40: 1× Guacal Hortensias M/13 | E40: Carrera 35 # 56-27 | F40: El Recreo | G40: Yulianis | H40: 573045961095 | I40: Oscar | K40: 46089.591 | L40: Entregado | M40: 03/08/2026 14:10:29 | N40: 03/08/2026 - 14:00:00 | P40: Zona 2 | R40: 46077.735 | S40: 46077.735
A41: 92939 | B41: Andrés López | C41: 573128297775 | D41: 1× Bouquet 24 Rosas Rojas M/8 | E41: Calle 53d #19-30 - Casa | F41: El Carmén | G41: Camila Benítez | H41: 573105923689 | I41: EXT - William Osorio | K41: 46089.628 | L41: Entregado | M41: 03/08/2026 15:04:41 | N41: 03/08/2026 - 14:00:00 | P41: Zona 2 | R41: 46077.754 | S41: 46077.754
A42: 92935 | B42: Juan dario valencia Benavides | C42: 573204208147 | D42: 1× Bouquet 6 Rosas Rojas M/10 | E42: Calle 93 #49c-42 - Calle 93 #49c-42- Ballena Azul Gourment | F42: El Poblado | G42: Maria José cervantes Molinares | H42: 573147387811 | I42: Oscar | K42: 46089.604 | L42: Entregado | M42: 03/08/2026 14:29:36 | N42: 03/08/2026 - 14:00:00 | P42: Zona 3 | R42: 46078.398 | S42: 46078.398
A43: 92934 | B43: Leiner salas | C43: 573016147069 | D43: 1× Cerámica Sweet Pea M/16 | E43: Carrera 51B # 86-48 - Recepción clínica de fractura | F43: Riomar | G43: María Angelica | H43: 573209588809 | I43: EXT - William Osorio | K43: 46089.619 | L43: Entregado | M43: 03/08/2026 14:51:32 | N43: 03/08/2026 - 14:00:00 | P43: Zona 3 | R43: 46078.404 | S43: 46078.404
A44: 92933 | B44: Andres De la Hoz Hoz | C44: 84383137308438 | D44: 2× Mini Box Orquidea M/22 | E44: Calle 72 # 24 C - 16 - Casa 1, Conjunto Aryliz tocar timbre | F44: San Felipe | G44: Isabelita y Pao | H44: 573166256584 | I44: EXT - William Osorio | K44: 46089.532 | L44: Entregado | M44: 03/08/2026 12:46:29 | N44: 03/08/2026 - 14:00:00 | P44: Zona 2 | R44: 46078.404 | S44: 46078.404
A45: 92932 | B45: José Segebre | C45: 57321524086969 | D45: 1× Corazón Mini Surtido M/12 | E45: Recoger en Tienda | F45: Recoger en Tienda | G45: José Segebre | H45: 573215240869 | K45: 46089.569 | L45: Pendiente | M45: 03/08/2026 13:39:16 | N45: 03/08/2026 - 13:00:00 | R45: 46078.432 | S45: 46078.432
A46: 92931 | B46: Alisson prentt viloria | C46: 34620769481 | D46: 1× Bouquet Aire M/7 | 1× Ferrero Rocher 8 und | E46: Cl 69E#41-98 - Torre 2 apto 504 | F46: Las Delicias | G46: Liliana Viloria | H46: 573004073607 | I46: EXT - William Osorio | K46: 46089.571 | L46: Entregado | M46: 03/08/2026 13:41:46 | N46: 03/08/2026 - 14:00:00 | P46: Zona 2 | R46: 46078.435 | S46: 46078.435
A47: 92929 | B47: Jaiver fonseca | C47: 573017997710 | D47: 1× Mini Box Clavel Fucsia M/20 | E47: Calle 96 no 71-37 - Torre 6 apto 203 | F47: Altos de Riomar | G47: Jaiver Fonseca | H47: 573017997710 | I47: Elvis | K47: 46089.636 | L47: En Ruta | M47: 03/08/2026 15:15:41 | N47: 03/08/2026 - 02:00:00 | P47: Zona 3 | R47: 46078.464 | S47: 46078.464
A48: 92928 | B48: Jesus Alberto Cardoso | C48: 573186228967 | D48: box mini plus surtido- con 5 rosas | E48: Recoger en Tienda | F48: Recoger en Tienda | G48: Jesus Alberto Cardoso | H48: 573186228967 | K48: 46089.633 | L48: Pendiente | M48: 03/08/2026 15:11:56 | N48: 03/08/2026 - 12:30:00 | R48: 46078.464 | S48: 46078.464
A49: 92926 | B49: Giovanni Villarreal | C49: 573006489514 | D49: 1× Mini Box Orquidea M/22 | E49: Carrera 25 # 1A - 124 - Mint apartamentos, 1911 torre 3 | F49: Portal de Genoves | G49: Jennifer Guzman | H49: 573006489514 | I49: Oscar | K49: 46089.574 | L49: Entregado | M49: 03/08/2026 13:47:10 | N49: 03/08/2026 - 13:00:00 | P49: zona 5 | R49: 46078.494 | S49: 46078.494
A50: 92922 | B50: Hernando Carrazco | C50: 573173579313 | D50: 1× Bouquet 6 Rosas Rojas M/10 | E50: Calle 117 # 42 -189 conjunto canario - Torre 24 apto 201 | F50: Alameda del Río | G50: Daisy Quevedo | H50: 573173666064 | I50: EXT - Javier | K50: 46089.563 | L50: Entregado | M50: Sun Mar 08 2026 13:31:29 GMT-0500 (hora estándar de Colombia) | N50: 03/08/2026 - 00:00:00 | P50: Zona 6 | R50: 46078.496 | S50: 46078.496
A51: 92921 | B51: Fabián Padilla | C51: 573022812819 | D51: 1× Bouquet 6 Rosas Rojas M/10 | E51: Calle 91#70-64 - Casa dos pisos (2) rejas negras | F51: Villa Carolina | G51: Isabella Huertas | H51: 573113106759 | I51: Elvis | K51: 46089.595 | L51: Entregado | M51: 03/08/2026 14:17:21 | N51: 03/08/2026 - 14:30:00 | P51: Zona 3 | R51: 46078.5 | S51: 46078.5
A52: 92920 | B52: Eduardo Pachano | C52: 573004214517 | D52: 1× Flora Box Redonda 24 Rosas de Jardin M/17 | E52: Calle 96 #71-165 - Torre 3A 1004 | F52: Riomar | G52: EduardoPachano | H52: 573004214517 | I52: Elvis | K52: 46089.501 | L52: Entregado | M52: 03/08/2026 12:00:58 | N52: 03/08/2026 - 02:00:00 | P52: Zona 3 | R52: 46078.583 | S52: 46078.583
A53: 92919 | B53: Mauricio Sandoval | C53: 57320940951551 | D53: 1× Encanto lila M/15 | E53: Recoger en Tienda | F53: Recoger en Tienda | G53: Mauricio Sandoval | H53: 573209409515 | K53: 46089.568 | L53: Pendiente | M53: 03/08/2026 13:38:31 | N53: 03/08/2026 - 12:00:00 | R53: 46078.583 | S53: 46078.583
A54: 92916 | B54: Jesús Martínez | C54: 573003322666 | D54: 2× Mini Box Clavel Fucsia M/20 | E54: Recoger en Tienda | F54: Recoger en Tienda | G54: Jesús Martínez | H54: 573003322666 | K54: 46089.448 | L54: Pendiente | M54: 03/08/2026 10:45:49 | N54: 03/08/2026 - 00:00:00 | R54: 46078.583 | S54: 46078.583
A55: 92915 | B55: Gabriel Dykhoff serrano | C55: 573127035334 | D55: 1× Bouquet 24 Rosas Rojas M/8 | E55: Calle 69E#32-125 - Apto 1 | F55: Olaya | G55: Gabriel Dykhoff | H55: 573127035334 | I55: EXT - Javier | K55: 46089.526 | L55: Entregado | M55: 03/08/2026 12:37:24 | N55: 03/08/2026 - 03:00:00 | P55: Zona 2 | R55: 46078.601 | S55: 46078.601
A56: 92914 | B56: David Ricardo | C56: 573502817351 | D56: 1× Guacal Hortensias M/13 | E56: Recoger en Tienda | F56: Recoger en Tienda | G56: David Ricardo | H56: 573502817351 | K56: 46089.449 | L56: Pendiente | M56: 03/08/2026 10:46:38 | N56: 03/08/2026 - 00:00:00 | R56: 46078.621 | S56: 46078.621
A57: 92913 | B57: Carlos Paternina | C57: 573005873865 | D57: 1× Mini Box Orquidea M/22 | E57: Calle35 b # 20-51 - Apto 4 primer piso | F57: San José | G57: Katty y Valery Sofia | H57: 573015202077 | I57: EXT - William Osorio | K57: 46089.517 | L57: Entregado | M57: 03/08/2026 12:24:35 | N57: 03/08/2026 - 02:00:00 | P57: Zona 2 | R57: 46078.648 | S57: 46078.648
A58: 92912 | B58: Jesus Camaño | C58: 573046167890 | D58: 1× Encanto lila M/15 | 1× Cerámica Sweet Pea M/16 | E58: Carrera 74 #79-119 | F58: Paraíso | G58: Maria Gomez | H58: 573207472778 | I58: Elvis | K58: 46089.6 | L58: Entregado | M58: 03/08/2026 14:24:12 | N58: 03/08/2026 - 14:00:00 | P58: Zona 3 | R58: 46078.657 | S58: 46078.657
A59: 92908 | B59: Sofía Hoyos | C59: 573014139346 | D59: 1× Flora Box Romantic Flores 12 Rosas M/18 | 1× Oso de Peluche | E59: Cra 41D #74-95 - Conjunto Residencial Oporto. Torre 2. Apto 413 | F59: Las Delicias | G59: Mariangel | H59: 573226242456 | I59: Elvis | K59: 46089.674 | L59: Entregado | M59: 03/08/2026 16:11:04 | N59: 03/08/2026 - 02:00:00 | P59: Zona 2 | R59: 46078.657 | S59: 46078.657
A60: 92907 | B60: Salin Rizcala | C60: 573015934541 | D60: 1× Bouquet 6 Rosas Rojas M/10 | E60: cr 79 # 83-38 - apt 202 casa | F60: San Salvador | G60: Ana Condia | H60: 573007592052 | I60: Elvis | K60: 46089.597 | L60: Entregado | M60: 03/08/2026 14:19:26 | N60: 03/08/2026 - 13:00:00 | P60: Zona 3 | R60: 46078.673 | S60: 46078.673
A61: 92906 | B61: Jimi Caleth Povea Navarro | C61: 573004826083 | D61: 1× Bouquet 6 Rosas Rojas M/10 | 1× Ferrero Rocher 8 und | E61: Calle 75B #41-87 - Torre 1 Apto 1201 edificio "Las torres de San Juan" cerca al centro comercial Único. barrio betania | F61: Bethania | G61: Sheily Riaño Guerra | H61: 573022009383 | I61: EXT - Javier | K61: 46089.618 | L61: En Ruta | M61: 03/08/2026 14:49:53 | N61: 03/08/2026 - 02:00:00 | P61: Zona 2 | R61: 46078.726 | S61: 46078.726
A62: 92904 | B62: Alberto Villarreal Bernal | C62: 573045849541 | D62: 1× Mini Box Orquidea M/22 | E62: Carrera 54 #55-127 - Edificio 11 de noviembre apto706 | F62: El Prado | G62: Luisa Fernanda Mejía | H62: 573242526558 | I62: EXT - William Osorio | K62: 46089.583 | L62: Entregado | M62: 03/08/2026 14:00:05 | N62: 03/08/2026 - 00:00:00 | P62: Zona 1 | R62: 46078.873 | S62: 46078.873
A63: 92903 | B63: William Moreno calderon | C63: 573003591462 | D63: 1× Bouquet 6 Rosas Rojas M/10 | E63: Cr 78#78-78 - Torre A - 409 conjunto brisas del parque | F63: Paraíso | G63: Rosa María Umaña | H63: 573107283794 | I63: Elvis | K63: 46089.597 | L63: Entregado | M63: 03/08/2026 14:20:02 | N63: 03/08/2026 - 00:00:00 | P63: Zona 3 | R63: 46078.874 | S63: 46078.874
A64: 92900 | B64: María arteta | C64: 573006358140 | D64: 1× Bouquet 12 Rosas Rojas M/9 | E64: Carrera 33#103-45 - Conjunto villa de las colinas | F64: Las Estrellas | G64: Maria arteta | H64: 573222595986 | I64: EXT - William Osorio | K64: 46089.643 | L64: Entregado | M64: 03/08/2026 15:26:03 | N64: 03/08/2026 - 14:00:00 | P64: Zona 4 | R64: 46079.359 | S64: 46079.359
A65: 92899 | B65: JUAN DAVID ABISAMBRA | C65: 57003176637 | D65: CAJA MEDIANA CUADRADA CON ARREGLO DE LA MINIBOX ORQUIDEA | E65: Cra 56 #79 -342. Edificio San Angelo. Apto 1601 | F65: san vicente | G65: Paulina | I65: Elvis | K65: 46089.591 | L65: Entregado | M65: 03/08/2026 14:11:34 | N65: 03/08/2026 - 14:00:00 | P65: Zona 3 | R65: 46079.362 | S65: 46079.362
A66: 92896 | B66: Mateo Cantillo | C66: 573057683063 | D66: 1× Bouquet 12 Rosas Rojas M/9 | E66: Cra 70#86-76 - Casa Oriana | F66: El Limoncito | G66: Oriana Cabrales | H66: 573225721015 | K66: 46089.544 | L66: Pendiente | M66: 03/08/2026 13:03:54 | N66: 03/08/2026 - 14:00:00 | P66: Zona 3 | R66: 46079.391 | S66: 46079.391
A67: 92895 | B67: Fredy Lugo | C67: 573106894979 | D67: 1× Mini Box Orquidea M/22 | E67: Calle84-42b-45 - Casa blanca con rejas blancas | F67: Los Nogales | G67: Lila perez | H67: 573057860370 | I67: EXT - William Osorio | K67: 46089.539 | L67: Entregado | M67: 03/08/2026 12:56:07 | N67: 03/08/2026 - 02:00:00 | P67: Zona 4 | R67: 46079.391 | S67: 46079.391
A68: 92894 | B68: Omar Daniel Sánchez Quintero | C68: 573023902381 | D68: 1× Corazón Mini Surtido M/12 | E68: Recoger en Tienda | F68: Recoger en Tienda | G68: Omar Daniel Sánchez Quintero | H68: 573023902381 | K68: 46089.466 | L68: Pendiente | M68: 03/08/2026 11:11:41 | N68: 03/08/2026 - 02:00:00 | R68: 46079.408 | S68: 46079.408
A69: 92893 | B69: Wilson leon | C69: 573234632212 | D69: 1× Canasto Aire M/1- mini box claveles fucsia | E69: Hotel radisson - Calle 84 # 51-28, | F69: san vicente | G69: Orismay | H69: 573234632212 | K69: 46089.504 | L69: Pendiente | M69: 03/08/2026 12:06:24 | N69: 03/08/2026 - 11:00:00 | P69: Zona 3 | R69: 46079.41 | S69: 46079.41
A70: 92892 | B70: Santiago coronado Martínez | C70: 573122768847 | D70: 1× Mini Box Clavel Fucsia M/20 | E70: Calle 78 # 42-111 - Apto 503 edificio britany | F70: Ciudad Jardin | G70: Andrea Espitia | H70: 573046549343 | K70: 46089.487 | L70: Pendiente | M70: 03/08/2026 11:41:13 | N70: 03/08/2026 - 14:00:00 | P70: Zona 4 | R70: 46079.423 | S70: 46079.423
A71: 92888 | B71: Giovanni Mastroianni | C71: 573114301416 | D71: 1× Mini Box Orquidea M/22 | E71: Cra 55 80 131 - Casa de rejas negras | F71: Altos del Prado | G71: Melissa Medina | I71: Elvis | K71: 46089.533 | L71: Entregado | M71: 03/08/2026 12:47:15 | N71: 03/08/2026 - 13:00:00 | P71: Zona 2 | R71: 46079.424 | S71: 46079.424
A72: 92887 | B72: Samuel Pombo | C72: 573112118759 | D72: 1× Mini Box Orquidea M/22 | E72: Calle 99 # 58 - 99 - Edificio Portobello Torre 3 apto 1402 | F72: Riomar | G72: Lucia Cortes | I72: EXT - Javier | K72: 46089.533 | L72: Entregado | M72: 03/08/2026 12:47:40 | N72: 03/08/2026 - 13:00:00 | P72: Zona 3 | R72: 46079.425 | S72: 46079.425
A73: 92886 | B73: NATALY RUDAS | C73: 573116677797 | D73: 1× Encanto lila M/15 | E73: CRA 53 #90B-42 TORRE 5 AP 401 - CONJ EL ENCANTO | F73: Altos de Riomar | G73: ESTEISY RUDAS | H73: 573116677797 | I73: Elvis | K73: 46089.519 | L73: Entregado | M73: 03/08/2026 12:27:31 | N73: 03/08/2026 - 02:00:00 | P73: Zona 3 | R73: 46079.486 | S73: 46079.486
A74: 92885 | B74: Javier Eduardo Sanchez Cantillo | C74: 573052578032 | D74: 1 x Mini Corazon Rosas Rojas | E74: Calle79b#42-322 - apto 101 | F74: Ciudad Jardin | G74: Gabriela Plata | H74: 573052578032 | K74: 46089.442 | L74: Pendiente | M74: 03/08/2026 10:36:58 | N74: 03/08/2026 - 23:00:00 | P74: Zona 4 | R74: 46079.491 | S74: 46079.491
A75: 92884 | B75: Angelica Quintero Mojica | C75: 573112024333 | D75: 1× Flora Box Mediana Pastel M/19 | E75: Calle 1c # 20–79 mm 10-1 Conj Mallorca torre 1 apto 504 | F75: Ciudad de Mallorquin | G75: Daril Amaya | H75: 573045291724 | I75: Elvis | K75: 46089.595 | L75: Entregado | M75: Sun Mar 08 2026 14:16:12 GMT-0500 (hora estándar de Colombia) | N75: 03/08/2026 - 13:00:00 | P75: zona 5 | R75: 46079.493 | S75: 46079.493
A76: 92882 | B76: María Tapia | C76: 573042441999 | D76: 1× Bouquet 6 Rosas Rojas M/10 | E76: Calle 99 # 58 - 99 - Edificio Portobelo Torre 3 Apto 903 | F76: Riomar | G76: Viviana Mora | H76: 573042441999 | I76: Elvis | K76: 46089.516 | L76: Entregado | M76: 03/08/2026 12:23:23 | N76: 03/08/2026 - 01:00:00 | P76: Zona 3 | R76: 46079.493 | S76: 46079.493
A77: 92879 | B77: Isabella Villadiego | C77: 573206470322 | D77: 1× Mini Box Orquidea M/22 | E77: Carrera 22 #127-00 - Conjunto manglar torre 4 apto 708 | F77: Ciudad de Mallorquin | G77: Ana Cecilia | H77: 573234741832 | I77: Elvis | K77: 46089.447 | L77: Entregado | M77: 03/08/2026 10:44:16 | N77: 03/08/2026 - 01:00:00 | P77: zona 5 | R77: 46079.503 | S77: 46079.503
A78: 92878 | B78: Maximiliam Garcia Camacho | C78: 573017717218 | D78: 1× Mini Box Orquidea M/22 | E78: Calle 1a # 30 - 61 - Edificio sunset boulevard apto 408 | F78: Portal de Genoves | G78: Isabela Cotes | H78: 573017717218 | I78: Elvis | K78: 46089.447 | L78: Entregado | M78: 03/08/2026 10:43:42 | N78: 03/08/2026 - 01:00:00 | P78: zona 5 | R78: 46079.519 | S78: 46079.519
A79: 92877 | B79: Jaime Martínez | C79: 573013882003 | D79: 1× Canasto Lavanda M/3 | E79: Calle 38 #23-84 - Casa esquinera de dos pisos, entrada sobre la 38 | F79: Montes | G79: Carmen Sánchez | H79: 573016476237 | K79: 46089.633 | L79: Pendiente | M79: 03/08/2026 15:11:27 | N79: 03/08/2026 - 01:00:00 | P79: Zona 2 | R79: 46079.521 | S79: 46079.521
A80: 92874 | B80: Valentina quiñones | C80: 573187321627 | D80: 1× Mini Box Orquidea M/22 | E80: Cra43b#90-152 - Edifico Balconi90 apto 302 | F80: El Tabor | G80: Vanesa escudero | H80: 573012120265 | K80: 46089.447 | L80: Pendiente | M80: 03/08/2026 10:43:01 | N80: 03/08/2026 - 01:00:00 | P80: Zona 4 | R80: 46079.521 | S80: 46079.521
A81: 92872 | B81: Nicolas orozco | C81: 573217755180 | D81: 1× Bouquet 24 Rosas Rojas M/8 | 1× Bouquet 12 Rosas Rojas M/9 | E81: CARRERA 52 No 82 203, EDIFICIO LUCCA 52 - Apto 2002 | F81: Altos del Prado | G81: Linda Fontakvo | H81: 573160560530 | K81: 46089.633 | L81: Pendiente | M81: 03/08/2026 15:10:57 | N81: 03/07/2026 - 01:00:00 | P81: Zona 2 | R81: 46079.535 | S81: 46079.535
A82: 92871 | B82: Alberto Urueta | C82: 573164708911 | D82: 3× Mini Box Clavel Fucsia M/20 | E82: Cra 57 # 84-155 Edi. Odessa Apto 8B | F82: san vicente | G82: Alberto Urueta | H82: 573164708911 | K82: 46088.873 | L82: Pendiente | M82: 03/07/2026 20:57:29 | N82: 03/08/2026 - 00:00:00 | P82: Zona 3 | R82: 46079.558 | S82: 46079.558
A83: 92870 | B83: Michael Hainsfurth | C83: 13059988217 | D83: 1× Guacal Hortensias M/13 | E83: Cra 52 # 106 - 213 - Oceana 52 Apto 1105 Torre 2 | F83: Villa Santos | G83: Jenifer Rios | H83: 573045365575 | I83: Elvis | K83: 46089.589 | L83: Entregado | M83: 03/08/2026 14:07:56 | N83: 03/08/2026 - 01:00:00 | P83: Zona 4 | R83: 46079.59 | S83: 46079.59
A84: 92869 | B84: Carlos Rueda | C84: 573004304422 | D84: Corazon mediano rosas rojas | E84: Cra 53 # 132 - 15 Conjunto Tenerife - Casa 5 | F84: Villa Campestre | G84: Veraine Vera | I84: Elvis | K84: 46089.596 | L84: Entregado | M84: 03/08/2026 14:18:36 | N84: 03/08/2026 - 10:00:00 | P84: Zona 5 | R84: 46079.598 | S84: 46079.598
A85: 92868 | B85: Hans wehdeking | C85: 573114121833 | D85: 1× Flora Box Redonda 24 Rosas de Jardin M/17 | E85: Crav58 # 96-106 - Apro 5 B eduf artefacto | F85: Altos del Limón | G85: Liliana y daniella | H85: 573114121833 | I85: Elvis | K85: 46089.484 | L85: Entregado | M85: 03/08/2026 11:37:23 | N85: 03/08/2026 - 13:00:00 | P85: Zona 3 | R85: 46079.611 | S85: 46079.611
A86: 92867 | B86: Lauren Ramírez | C86: 573243585945 | D86: 1× Canasto Mediano Sweet M/4 | 1× Marquito Surtido M/14 | E86: Calle 79 #42f -93 - Apto 406 | F86: Ciudad Jardin | G86: Gixela Díaz | H86: 573243585945 | K86: 46089.496 | L86: En Ruta | M86: 03/08/2026 11:54:36 | N86: 03/08/2026 - 12:00:00 | P86: Zona 4 | R86: 46079.631 | S86: 46079.631
A87: 92866 | B87: María Alejandra Cotes | C87: 573138831564 | D87: 1× Bouquet Aire M/7 | E87: Cr 59 no 74 – 72 Edificio Prado Colonial Apto 2C - Apto 2C | F87: El Prado | G87: Emily y Jaime | H87: 573007389560 | K87: 46089.57 | L87: Pendiente | M87: 03/08/2026 13:40:45 | N87: 03/08/2026 - 01:00:00 | P87: Zona 1 | R87: 46079.655 | S87: 46079.655
A88: 92865 | B88: Lucas Avila Manotas | C88: 573008366418 | D88: 1× Bouquet 12 Rosas Rojas M/9 | 2× Bouquet 6 Rosas Rojas M/10 | E88: Cra. 55#80-56 - 6 | F88: Riomar | G88: Ramón Avila | H88: 573008366418 | I88: Elvis | K88: 46089.59 | L88: Entregado | M88: 03/08/2026 14:09:17 | N88: 03/08/2026 - 01:00:00 | P88: Zona 3 | R88: 46079.668 | S88: 46079.668
A89: 92864 | B89: Mireya Velez | C89: 573106364062 | D89: 1× Mini Box Orquidea M/22 | E89: Cra 52 # 99a - 168 - Casa 27 Reservas de San Bernardo | F89: Riomar | G89: Claudia Chacón | H89: 573205116170 | I89: Elvis | K89: 46089.448 | L89: Entregado | M89: 03/08/2026 10:44:50 | N89: 03/08/2026 - 12:00:00 | P89: Zona 3 | R89: 46079.668 | S89: 46079.668
A90: 92862 | B90: Manuel Macías Ríos | C90: 573052988140 | D90: 1× Mini Box Claveles M/23 CLAVEL FUSCIA | E90: Calle 104 transversal 43a-37 - Dimaro Apartamentos Torre 1 apto 803 en Miramar | F90: Miramar | G90: Yajaira Ríos López | H90: 573052988140 | K90: 46088.794 | L90: Pendiente | M90: 03/07/2026 19:03:11 | N90: 03/08/2026 - 12:00:00 | P90: Zona 4 | R90: 46079.668 | S90: 46079.668
A91: 92861 | B91: ALVARO VILLAREAL | C91: 5719543974714 | D91: 1× Bouquet 12 Rosas Rojas M/9 | E91: CRA 64#98-90 apto 709 Alameda campestre - APTO 709 | F91: Riomar | G91: ALVARO VILLAREAL | I91: Oscar | K91: 46088.798 | L91: Entregado | M91: 03/07/2026 19:09:24 | N91: 03/08/2026 - 08:00:00 | P91: Zona 3 | R91: 46079.678 | S91: 46079.678
A92: 92857 | B92: Andriu Romero | C92: 573014686030 | D92: 1× Mini Box Orquidea M/22 | E92: Recoger en Tienda | F92: Recoger en Tienda | G92: Andriu Romero | H92: 573014686030 | K92: 46088.783 | L92: Pendiente | M92: 03/07/2026 18:47:11 | N92: 03/08/2026 - 08:00:00 | R92: 46079.678 | S92: 46079.678
A93: 92856 | B93: Santiago Sanchez | C93: 573156670982 | D93: 1× Flora Box Redonda 24 Rosas de Jardin M/17 | E93: Cra 54 #132-249 - Conjunto ocho ríos casa 7 | F93: Villa Campestre | G93: Paola Amorocho | H93: 573185779237 | I93: EXT - Juan David | K93: 46089.71 | L93: Pendiente | M93: 03/08/2026 17:02:22 | N93: 03/08/2026 - 12:00:00 | P93: Zona 5 | R93: 46079.687 | S93: 46079.687
A94: 92855 | B94: juancarlos hernandez | C94: 573005293740 | D94: 1× Mini Box Claveles M/23 | E94: Cra 58 #94-40 apto 601 - edificio elite 58 - edificio elite 58 | F94: Altos de Riomar | G94: olga suarez | H94: 573005293740 | K94: 46088.789 | L94: Pendiente | M94: 03/07/2026 18:56:20 | N94: 03/08/2026 - 08:00:00 | P94: Zona 3 | R94: 46079.716 | S94: 46079.716
A95: 92853 | B95: Camilo Franco | C95: 573008588209 | D95: 1× Bouquet 12 Rosas Rojas M/9 | E95: Calle 69b 33-43 - Casa segundo piso | F95: Olaya | G95: Katherin Mejia | H95: 573207258284 | I95: EXT - William Osorio | K95: 46089.587 | L95: Entregado | M95: 03/08/2026 14:04:57 | N95: 03/08/2026 - 10:00:00 | P95: Zona 2 | R95: 46079.716 | S95: 46079.716
A96: 92852 | B96: HRD INVERSIONES | C96: 573003858601 | D96: 2× Bouquet 12 Rosas Rojas M/9 | E96: CRA 25 # 1A- 124 EDIF MINT - APTO 307 TORRE 2 | G96: JULY DIAZ, AHIJADA SARA, ZORY GALLON | K96: 46088.916 | L96: Pendiente | M96: 03/07/2026 21:59:40 | N96: 03/08/2026 - 08:00:00 | R96: 46079.759 | S96: 46079.759
A97: 92851 | B97: Emir Andres Calaveras Quevedo | C97: 573233315915 | D97: 1× Bouquet 12 Rosas Rojas M/9 | 1× Ferrero Rocher 8 und | E97: Calle 36 #13_40 bonanza soledad | F97: Soledad | G97: Brillith Obregón | H97: 573147853196 | K97: 46089.37 | L97: Pendiente | M97: 03/08/2026 08:52:31 | N97: 03/08/2026 - 08:00:00 | P97: Zona 6 | R97: 46080.327 | S97: 46080.327
A98: 92844 | B98: HRD INVERSIONES | C98: 573003858601 | D98: 1× Bouquet 24 Rosas Rojas M/8 / 2 ENCANTO FLORA BLACO CON ROSADO | E98: CALLE 99# 58-99 PORTPOBELLO APTO 1204 - APTO 1204 | G98: MARGARITA ARRIETA | K98: 46088.885 | L98: Pendiente | M98: 03/07/2026 21:14:07 | N98: 03/08/2026 - 08:00:00 | R98: 46080.439 | S98: 46080.439
A99: 92843 | B99: juan david hernandez | C99: 573183309978 | D99: 1× Bouquet 6 Rosas Rojas M/10 | E99: cr 30A # 1b- 245 edificio paradise living apt 1104 torre A - al lado clinica porto azul | F99: Portal de Genoves | G99: silvia rueda | H99: 573157335190 | K99: 46089.343 | L99: Pendiente | M99: 03/08/2026 08:13:14 | N99: 03/08/2026 - 09:06:00 | P99: zona 5 | R99: 46080.408 | S99: 46080.408
A100: 92842 | B100: Manuel Alejandro Jiménez Mercado | C100: 573186000036 | D100: 1× Flora Mini Plus Box Redonda M/21 | E100: Cra 55 # 91 101 | F100: Altos de Riomar | G100: Judith Mercado | H100: 573156706066 | K100: 46089.403 | L100: Pendiente | M100: 03/08/2026 09:40:44 | N100: 03/08/2026 - 11:00:00 | P100: Zona 3 | R100: 46080.408 | S100: 46080.408
...

Sheet Pagos
A1: IDPago | B1: PedidoID | C1: MetodoPago | D1: Valor | E1: FechaPago | H1: TOTAL | I1: MET_PAGO_1 | J1: MET_PAGO_2
A2: 1 | B2: 90000 | C2: EFECTIVO | D2: 100000 | H2: 300000 | I2: 100000 | J2: 200000
A3: 2 | B3: 90000 | C3: TARJETA | D3: 200000

Sheet Caja
A1: Fecha | B1: Base | C1: Efectivo | D1: Gasto | E1: Total_Efectivo | F1: Nueva_Base | G1: Guardado
A2: 46017 | B2: 76000 | C2: 305000 | D2: 148500 | E2: 232500 | F2: 39000
A3: 46018 | B3: 39000 | C3: 890000 | E3: 929000
A4: 46021 | B4: 50600 | D4: 27000 | E4: 23600 | F4: 23600
A5: 46027 | B5: 126600 | C5: 470000 | D5: 201200 | E5: 395400 | F5: 95400
A6: 46028 | B6: 95400 | C6: 111000 | D6: 44500 | E6: 161900 | F6: 70200
A7: 46029 | B7: 70200 | C7: 190000 | D7: 42000 | E7: 218200 | F7: 69200
A8: 46030 | B8: 69200 | C8: 296000 | D8: 24000 | E8: 341200 | F8: 41200
A9: 46031 | B9: 41200 | C9: 18000 | D9: 20000 | E9: 39200 | F9: 39200
A10: 46037 | B10: 104100 | C10: 277000 | D10: 206800 | E10: 174300 | F10: 75000 | G10: 100000
A11: 46038 | B11: 75000 | C11: 0 | E11: 75000 | G11: 0
A12: 46039 | B12: 100000 | C12: 34000 | D12: 65000 | E12: 69000 | F12: 69000 | G12: 0
A13: 46041 | B13: 69000 | C13: 598000 | D13: 220800 | E13: 446200 | F13: 102300 | G13: 400000
A14: 46042 | B14: 102300 | C14: 627000 | D14: 60600 | E14: 668700 | F14: 101700 | G14: 550000
A15: 46043 | B15: 101700 | C15: 38000 | D15: 45000 | E15: 94700 | F15: 92700 | G15: 0
A16: 46044 | B16: 92700 | C16: 150000 | D16: 37000 | E16: 205700 | F16: 56200 | G16: 150000
A17: 46045 | B17: 56200 | D17: 41900 | E17: 14300 | F17: 14300 | G17: 0
A18: 46046 | B18: 0 | C18: 0 | D18: 0 | E18: 0 | F18: 156300 | G18: 0
A19: 46048 | B19: 156300 | C19: 474000 | D19: 64000 | E19: 566300 | F19: 76300 | G19: 490000
A20: 46049 | B20: 76300 | C20: 30000 | D20: 71500 | E20: 34800 | F20: 37800 | G20: 0
A21: 46050 | B21: 37800 | C21: 640000 | D21: 213000 | E21: 464800 | F21: 64800 | G21: 400000
A22: 46051 | B22: 64800 | C22: 518000 | D22: 68000 | E22: 514800 | F22: 74800 | G22: 440000
A23: 46052 | B23: 90800 | C23: 0 | D23: 63000 | E23: 27800 | F23: 29800 | G23: 0
A24: 46056 | B24: 10800 | C24: 115000 | D24: 6000 | E24: 119800 | F24: 120000 | G24: 0
A25: 46057 | B25: 120000 | C25: 270000 | D25: 220000 | E25: 170000 | F25: 124000 | G25: 160000
A26: 46058 | B26: 124000 | C26: 400000 | D26: 118000 | E26: 406000 | F26: 56000 | G26: 350000
A27: 46059 | B27: 56000 | C27: 125000 | D27: 17000 | E27: 164000 | F27: 161300 | G27: 0
A28: 46060 | B28: 161300 | C28: 292000 | D28: 105000 | E28: 348300 | F28: 68300 | G28: 280000
A29: 46062 | B29: 68300 | C29: 0 | D29: 56000 | E29: 12300 | F29: 12300 | G29: 0
... A45: 46090 | B45: 63600 | C45: 27000 | D45: 90000 | E45: 600 | F45: 3600 | G45: 3600

Sheet Domiciliarios
A1: ID Domiciliario | B1: Nombre | C1: Disponibilidad | D1: Telefono | E1: Externo
A2: DOM001 | B2: Elvis | C2: Sí | D2: 3110925692 | E2: NO
A3: DOM002 | B3: Oscar | C3: Sí | D3: 3183858712 | E3: NO
A4: DOM003 | B4: Javier | C4: Sí | D4: 3505830273 | E4: NO
A5: DOM004 | B5: EXT - William Osorio | C5: Sí | D5: 3006666911 | E5: SI
A6: DOM005 | B6: EXT - Antonio Orozco | C6: Sí | D6: 3045805246 | E6: SI
A7: DOM006 | B7: EXT - Omar Hernandez | C7: Sí | D7: 3013970888 | E7: SI
A8: DOM007 | B8: EXT - Mandados | C8: Sí | D8: 3117317875 | E8: SI
A9: DOM008 | B9: EXT - fausto | C9: Sí | D9: 3505830273 | E9: SI
A10: DOM009 | B10: EXT - Juan D | C10: SI | D10: 3166180703 | E10: SI

Sheet Catalogo
A1: id | B1: name | C1: price | D1: img | E1: categoria | F1: activo
A3: 95 | B3: Arreglo Personalizado | C3: 0 | D3: https://floraapp.s3.us-east-1.amazonaws.com/personalizado_andrea.jpg | E3: Personalizado | F3: TRUE
A4: 1 | B4: Flora Box Redonda 24 Rosas de Jardin | C4: 350000 | D4: https://floraapp.s3.us-east-1.amazonaws.com/Imagen1.jpg | E4: Flora Box | F4: TRUE
A5: 2 | B5: Flora Box Redonda 70 Rosas | C5: 580000 | D5: https://floraapp.s3.us-east-1.amazonaws.com/Imagen2.jpg | E5: Flora Box | F5: TRUE
A6: 3 | B6: Flora Box Redonda Orquídea | C6: 410000 | D6: https://floraapp.s3.us-east-1.amazonaws.com/Imagen3.jpg | E6: Flora Box | F6: TRUE
A7: 4 | B7: Flora Box Redonda Lirio | C7: 410000 | D7: https://floraapp.s3.us-east-1.amazonaws.com/Imagen4.jpg | E7: Flora Box | F7: TRUE
A8: 5 | B8: Flora Box Romantic Flores 12 Rosas | C8: 220000 | D8: https://floraapp.s3.us-east-1.amazonaws.com/Imagen5.jpg | E8: Flora Box | F8: TRUE
A9: 104 | B9: Flora Box Romantic Flores 12 Rosas | C9: 220000 | D9: https://flora-s3-bucket.s3.us-east-1.amazonaws.com/Flora+Box+Romantic+12+Rosas+v2.png | E9: Flora Box | F9: FALSE
A10: 103 | B10: Flora Box Romantic Flores 24 Rosas | C10: 150000 | D10: https://floraapp.s3.us-east-1.amazonaws.com/Imagen5.jpg | E10: Flora Box | F10: FALSE
A11: 6 | B11: Flora Box Mediana Tierra | C11: 300000 | D11: https://floraapp.s3.us-east-1.amazonaws.com/Imagen6.png | E11: Flora Box | F11: TRUE
A12: 7 | B12: Flora Box Mediana Aire | C12: 300000 | D12: https://floraapp.s3.us-east-1.amazonaws.com/Imagen7.jpg | E12: Flora Box | F12: TRUE
A13: 8 | B13: Flora Box Mediana Tulipanes | C13: 350000 | D13: https://floraapp.s3.us-east-1.amazonaws.com/Imagen8.jpg | E13: Flora Box | F13: TRUE
A14: 9 | B14: Flora Box Grande Orquídea | C14: 310000 | D14: https://floraapp.s3.us-east-1.amazonaws.com/Imagen9.jpg | E14: Flora Box | F14: TRUE
... A109: 94 | B109: Ambientador 120 ml | C109: 40000 | D109: https://floraapp.s3.us-east-1.amazonaws.com/Imagen93.jpg | E109: Adicionales | F109: TRUE

Sheet San_Valentin
A1: id | B1: name | C1: price | D1: img | E1: Estado_Receta | F1: Insumos_Faltantes | G1: Nota | H1: cantidad
A2: 54 | B2: Flora Heart Extragrande | C2: 750000 | D2: https://floraapp.s3.us-east-1.amazonaws.com/san_valentin/imagen_1.jpeg | G2: 54 | H2: {=IFERROR(_xludf.XLOOKUP(G2, CATALOGO_ARREGLOS!A:A, CATALOGO_ARREGLOS!F:F), 0)} -> 0
A3: 55 | B3: Flora Heart Grande | C3: 300000 | D3: https://floraapp.s3.us-east-1.amazonaws.com/san_valentin/imagen_2.jpeg | G3: 55 | H3: {=IFERROR(_xludf.XLOOKUP(G3, CATALOGO_ARREGLOS!A:A, CATALOGO_ARREGLOS!F:F), 0)} -> 0
A4: 56 | B4: Flora Heart Mediano | C4: 220000 | D4: https://floraapp.s3.us-east-1.amazonaws.com/san_valentin/imagen_3.jpeg | G4: 56 | H4: {=IFERROR(_xludf.XLOOKUP(G4, CATALOGO_ARREGLOS!A:A, CATALOGO_ARREGLOS!F:F), 0)} -> 0
A5: 57 | B5: Mini Heart Rosas | C5: 130000 | D5: https://floraapp.s3.us-east-1.amazonaws.com/san_valentin/imagen_4.jpeg | G5: 57 | H5: {=IFERROR(_xludf.XLOOKUP(G5, CATALOGO_ARREGLOS!A:A, CATALOGO_ARREGLOS!F:F), 0)} -> 0
A6: 58 | B6: Mini Heart Surtido | C6: 120000 | D6: https://floraapp.s3.us-east-1.amazonaws.com/san_valentin/imagen_5.jpeg | G6: 58 | H6: {=IFERROR(_xludf.XLOOKUP(G6, CATALOGO_ARREGLOS!A:A, CATALOGO_ARREGLOS!F:F), 0)} -> 0
A7: 48 | B7: Bouquet 100 Rosas | C7: 600000 | D7: https://floraapp.s3.us-east-1.amazonaws.com/san_valentin/imagen_6.jpeg | G7: 48 | H7: {=IFERROR(_xludf.XLOOKUP(G7, CATALOGO_ARREGLOS!A:A, CATALOGO_ARREGLOS!F:F), 0)} -> 0
A8: 49 | B8: Bouquet 50 Rosas | C8: 320000 | D8: https://floraapp.s3.us-east-1.amazonaws.com/san_valentin/imagen_7.jpeg | G8: 49 | H8: {=IFERROR(_xludf.XLOOKUP(G8, CATALOGO_ARREGLOS!A:A, CATALOGO_ARREGLOS!F:F), 0)} -> 0
A9: 50 | B9: Bouquet 36 Rosas | C9: 250000 | D9: https://floraapp.s3.us-east-1.amazonaws.com/Imagen50.jpg | G9: 50 | H9: {=IFERROR(_xludf.XLOOKUP(G9, CATALOGO_ARREGLOS!A:A, CATALOGO_ARREGLOS!F:F), 0)} -> 0
A10: 51 | B10: Bouquet 24 Rosas | C10: 200000 | D10: https://floraapp.s3.us-east-1.amazonaws.com/san_valentin/imagen_9.jpeg | G10: 51 | H10: {=IFERROR(_xludf.XLOOKUP(G10, CATALOGO_ARREGLOS!A:A, CATALOGO_ARREGLOS!F:F), 0)} -> 0
A11: 52 | B11: Bouquet 12 Rosas | C11: 120000 | D11: https://floraapp.s3.us-east-1.amazonaws.com/san_valentin/imagen_10.jpeg | G11: 52 | H11: {=IFERROR(_xludf.XLOOKUP(G11, CATALOGO_ARREGLOS!A:A, CATALOGO_ARREGLOS!F:F), 0)} -> 0
A12: 53 | B12: Bouquet 6 Rosas | C12: 90000 | D12: https://floraapp.s3.us-east-1.amazonaws.com/san_valentin/imagen_11.jpeg | G12: 53 | H12: {=IFERROR(_xludf.XLOOKUP(G12, CATALOGO_ARREGLOS!A:A, CATALOGO_ARREGLOS!F:F), 0)} -> 0
A13: 37 | B13: Canasto 100 Rosas Rojas | C13: 800000 | D13: https://floraapp.s3.us-east-1.amazonaws.com/san_valentin/imagen_12.jpeg | G13: 37 | H13: {=IFERROR(_xludf.XLOOKUP(G13, CATALOGO_ARREGLOS!A:A, CATALOGO_ARREGLOS!F:F), 0)} -> 0
... A34: 94 | B34: Ambientador 120 ml | C34: 40000 | D34: https://floraapp.s3.us-east-1.amazonaws.com/san_valentin/Ambientador+120+ml.jpeg | G34: 94 | H34: {=IFERROR(_xludf.XLOOKUP(G34, CATALOGO_ARREGLOS!A:A, CATALOGO_ARREGLOS!F:F), 0)} -> 0

Sheet Copia de Inventario
A1: Id | B1: Codigo | C1: Nombre de Producto | D1: Categoria | E1: Stock_Mínimo | F1: Stock_Actual | G1: Fecha_Caducidad | H1: Estado | I1: Und Medida | J1: Provedor | K1: Color
A2: 1 | B2: 7702728230129 | C2: Rosas | D2: Flor | E2: 10 | F2: 82 | G2: 45981 | H2: Disponible | I2: Paquete
A3: 2 | B3: 7702728230130 | C3: orquideas | D3: Follaje | E3: 10 | F3: 240 | G3: 45981 | H3: Casi Agotado
A4: 3 | B4: 7702728230132 | C4: girasol | D4: Flor | F4: 5 | G4: 45938 | H4: Agotado
A5: 4 | B5: 7702728230133 | C5: girasol | D5: Flor | F5: 20 | G5: 45938 | H5: Disponible
A6: 5 | B6: 7702728230135 | C6: tulipan | D6: Flor | F6: 1 | G6: 45938 | H6: Agotado
A7: 6 | B7: 7702728230137 | C7: Caja 5x5 | D7: Caja
A8: 7 | B8: 60 | C8: caja | D8: caja | E8: 20 | F8: 340
A9: 8 | B9: 7707188188263 | C9: clavellina | D9: flor | E9: 1 | F9: 22 | G9: 45968 | H9: Disponible

Sheet Inventario
A1: CODIGO | B1: NOMBRE | C1: CATEGORIA | D1: SUBCATEGORIA | E1: COLOR | F1: DESCRIPCION | G1: PROVEDOR | H1: STOCK_ACTUAL | I1: ESTADO | J1: VALOR | K1: CODIGOPROVEDOR
A2: FL00106300 | B2: ALHELI BLANCO | C2: FLORES | E2: BLANCO | F2: =IFERROR(__xludf.DUMMYFUNCTION("IFERROR( TEXTJOIN("" | "", TRUE, UNIQUE( FILTER( Movimientos_Inventario!G:G, TRIM(CLEAN(Movimientos_Inventario!C:C)) = TRIM(CLEAN(A2)), Movimientos_Inventario!G:G <> """" ) ) ), """")"),"") | G2: JUAN DAVID (AURA) BOGOTA | H2: 0 | I2: =IF(H2=0,"AGOTADO",IF(H2<=10,"CASI AGOTADO","DISPONIBLE")) -> AGOTADO
A3: FL00110300 | B3: ALHELI LILA | C3: FLORES | E3: LILA | F3: =IFERROR(__xludf.DUMMYFUNCTION("IFERROR( TEXTJOIN("" | "", TRUE, UNIQUE( FILTER( Movimientos_Inventario!G:G, TRIM(CLEAN(Movimientos_Inventario!C:C)) = TRIM(CLEAN(A3)), Movimientos_Inventario!G:G <> """" ) ) ), """")"),"CATALAGO MUJER") -> CATALAGO MUJER | G3: JUAN DAVID (AURA) BOGOTA | H3: 12 | I3: =IF(H3=0,"AGOTADO",IF(H3<=10,"CASI AGOTADO","DISPONIBLE")) -> DISPONIBLE
A4: FL00115300 | B4: ALHELI ROSADA | C4: FLORES | E4: ROSADA | F4: =IFERROR(__xludf.DUMMYFUNCTION("IFERROR( TEXTJOIN("" | "", TRUE, UNIQUE( FILTER( Movimientos_Inventario!G:G, TRIM(CLEAN(Movimientos_Inventario!C:C)) = TRIM(CLEAN(A4)), Movimientos_Inventario!G:G <> """" ) ) ), """")"),"") | G4: JUAN DAVID (AURA) BOGOTA | I4: =IF(H4=0,"AGOTADO",IF(H4<=10,"CASI AGOTADO","DISPONIBLE")) -> AGOTADO
A5: FL00206300 | B5: ASTROMELIA BLANCA | C5: FLORES | E5: BLANCA | F5: =IFERROR(__xludf.DUMMYFUNCTION("IFERROR( TEXTJOIN("" | "", TRUE, UNIQUE( FILTER( Movimientos_Inventario!G:G, TRIM(CLEAN(Movimientos_Inventario!C:C)) = TRIM(CLEAN(A5)), Movimientos_Inventario!G:G <> """" ) ) ), """")"),"CATALOGO MUJER") -> CATALOGO MUJER | G5: JUAN DAVID (AURA) BOGOTA | H5: 5 | I5: =IF(H5=0,"AGOTADO",IF(H5<=10,"CASI AGOTADO","DISPONIBLE")) -> CASI AGOTADO
A6: FL00209300 | B6: ASTROMELIA FUCSIA | C6: FLORES | E6: FUCSIA | F6: CATALOGO MUJER | G6: JUAN DAVID (AURA) BOGOTA | H6: 10 | I6: =IF(H6=0,"AGOTADO",IF(H6<=10,"CASI AGOTADO","DISPONIBLE")) -> CASI AGOTADO
A7: FL00210300 | B7: ASTROMELIA LILA | C7: FLORES | E7: LILA | F7: =IFERROR(__xludf.DUMMYFUNCTION("IFERROR( TEXTJOIN("" | "", TRUE, UNIQUE( FILTER( Movimientos_Inventario!G:G, TRIM(CLEAN(Movimientos_Inventario!C:C)) = TRIM(CLEAN(A7)), Movimientos_Inventario!G:G <> """" ) ) ), """")"),"") | G7: JUAN DAVID (AURA) BOGOTA | I7: =IF(H7=0,"AGOTADO",IF(H7<=10,"CASI AGOTADO","DISPONIBLE")) -> AGOTADO
A8: FL00212300 | B8: ASTROMELIA NARANJA | C8: FLORES | E8: NARANJA | F8: =IFERROR(__xludf.DUMMYFUNCTION("IFERROR( TEXTJOIN("" | "", TRUE, UNIQUE( FILTER( Movimientos_Inventario!G:G, TRIM(CLEAN(Movimientos_Inventario!C:C)) = TRIM(CLEAN(A8)), Movimientos_Inventario!G:G <> """" ) ) ), """")"),"") | G8: JUAN DAVID (AURA) BOGOTA | I8: =IF(H8=0,"AGOTADO",IF(H8<=10,"CASI AGOTADO","DISPONIBLE")) -> AGOTADO
A9: FL00214300 | B9: ASTROMELIA ROJA | C9: FLORES | E9: ROJA | F9: =IFERROR(__xludf.DUMMYFUNCTION("IFERROR( TEXTJOIN("" | "", TRUE, UNIQUE( FILTER( Movimientos_Inventario!G:G, TRIM(CLEAN(Movimientos_Inventario!C:C)) = TRIM(CLEAN(A9)), Movimientos_Inventario!G:G <> """" ) ) ), """")"),"") | G9: JUAN DAVID (AURA) BOGOTA | I9: =IF(H9=0,"AGOTADO",IF(H9<=10,"CASI AGOTADO","DISPONIBLE")) -> AGOTADO
A10: FL00215300 | B10: ASTROMELIA ROSADA | C10: FLORES | E10: ROSADA | F10: =IFERROR(__xludf.DUMMYFUNCTION("IFERROR( TEXTJOIN("" | "", TRUE, UNIQUE( FILTER( Movimientos_Inventario!G:G, TRIM(CLEAN(Movimientos_Inventario!C:C)) = TRIM(CLEAN(A10)), Movimientos_Inventario!G:G <> """" ) ) ), """")"),"CATALOGO MUJER") -> CATALOGO MUJER | G10: JUAN DAVID (AURA) BOGOTA | H10: 20 | I10: =IF(H10=0,"AGOTADO",IF(H10<=10,"CASI AGOTADO","DISPONIBLE")) -> DISPONIBLE
A11: FL00312400 | B11: AVES DEL PARAISO | C11: FLORES | E11: DEL PARAISO | F11: =IFERROR(__xludf.DUMMYFUNCTION("IFERROR( TEXTJOIN("" | "", TRUE, UNIQUE( FILTER( Movimientos_Inventario!G:G, TRIM(CLEAN(Movimientos_Inventario!C:C)) = TRIM(CLEAN(A11)), Movimientos_Inventario!G:G <> """" ) ) ), """")"),"") | G11: CARLOS SANCHEZ MEDELLIN | I11: =IF(H11=0,"AGOTADO",IF(H11<=10,"CASI AGOTADO","DISPONIBLE")) -> AGOTADO
A12: FL00417300 | B12: BALL GREEN | C12: FLORES | E12: GREEN | F12: =IFERROR(__xludf.DUMMYFUNCTION("IFERROR( TEXTJOIN("" | "", TRUE, UNIQUE( FILTER( Movimientos_Inventario!G:G, TRIM(CLEAN(Movimientos_Inventario!C:C)) = TRIM(CLEAN(A12)), Movimientos_Inventario!G:G <> """" ) ) ), """")"),"") | G12: JUAN DAVID (AURA) BOGOTA | I12: =IF(H12=0,"AGOTADO",IF(H12<=10,"CASI AGOTADO","DISPONIBLE")) -> AGOTADO
A13: FL00510300 | B13: BELLADONA | C13: FLORES | F13: =IFERROR(__xludf.DUMMYFUNCTION("IFERROR( TEXTJOIN("" | "", TRUE, UNIQUE( FILTER( Movimientos_Inventario!G:G, TRIM(CLEAN(Movimientos_Inventario!C:C)) = TRIM(CLEAN(A13)), Movimientos_Inventario!G:G <> """" ) ) ), """")"),"") | G13: JUAN DAVID (AURA) BOGOTA | I13: =IF(H13=0,"AGOTADO",IF(H13<=10,"CASI AGOTADO","DISPONIBLE")) -> AGOTADO
A14: FL00606300 | B14: BOCA DE DRAGON BLANCO | C14: FLORES | E14: DE DRAGON BLANCO | F14: =IFERROR(__xludf.DUMMYFUNCTION("IFERROR( TEXTJOIN("" | "", TRUE, UNIQUE( FILTER( Movimientos_Inventario!G:G, TRIM(CLEAN(Movimientos_Inventario!C:C)) = TRIM(CLEAN(A14)), Movimientos_Inventario!G:G <> """" ) ) ), """")"),"") | G14: JUAN DAVID (AURA) BOGOTA | I14: =IF(H14=0,"AGOTADO",IF(H14<=10,"CASI AGOTADO","DISPONIBLE")) -> AGOTADO
A15: FL00615300 | B15: BOCA DE DRAGON ROSADO | C15: FLORES | E15: DE DRAGON ROSADO | F15: CATALOGO MUJER | G15: JUAN DAVID (AURA) BOGOTA | H15: 30 | I15: =IF(H15=0,"AGOTADO",IF(H15<=10,"CASI AGOTADO","DISPONIBLE")) -> DISPONIBLE
A16: FL00705300 | B16: BOTON DE ORO | C16: FLORES | E16: DE ORO | F16: =IFERROR(__xludf.DUMMYFUNCTION("IFERROR( TEXTJOIN("" | "", TRUE, UNIQUE( FILTER( Movimientos_Inventario!G:G, TRIM(CLEAN(Movimientos_Inventario!C:C)) = TRIM(CLEAN(A16)), Movimientos_Inventario!G:G <> """" ) ) ), """")"),"") | G16: JUAN DAVID (AURA) BOGOTA | I16: =IF(H16=0,"AGOTADO",IF(H16<=10,"CASI AGOTADO","DISPONIBLE")) -> AGOTADO
A17: FL00809300 | B17: CALACHOES FUCSIAS | C17: FLORES | E17: FUCSIAS | F17: =IFERROR(__xludf.DUMMYFUNCTION("IFERROR( TEXTJOIN("" | "", TRUE, UNIQUE( FILTER( Movimientos_Inventario!G:G, TRIM(CLEAN(Movimientos_Inventario!C:C)) = TRIM(CLEAN(A17)), Movimientos_Inventario!G:G <> """" ) ) ), """")"),"") | G17: JUAN DAVID (AURA) BOGOTA | I17: =IF(H17=0,"AGOTADO",IF(H17<=10,"CASI AGOTADO","DISPONIBLE")) -> AGOTADO
A18: FL00815300 | B18: CALACHOES ROSADOS | C18: FLORES | E18: ROSADOS | F18: =IFERROR(__xludf.DUMMYFUNCTION("IFERROR( TEXTJOIN("" | "", TRUE, UNIQUE( FILTER( Movimientos_Inventario!G:G, TRIM(CLEAN(Movimientos_Inventario!C:C)) = TRIM(CLEAN(A18)), Movimientos_Inventario!G:G <> """" ) ) ), """")"),"") | G18: JUAN DAVID (AURA) BOGOTA | I18: =IF(H18=0,"AGOTADO",IF(H18<=10,"CASI AGOTADO","DISPONIBLE")) -> AGOTADO
A19: FL00917300 | B19: CAMPANA DE IRLANDA | C19: FLORES | E19: DE IRLANDA | F19: =IFERROR(__xludf.DUMMYFUNCTION("IFERROR( TEXTJOIN("" | "", TRUE, UNIQUE( FILTER( Movimientos_Inventario!G:G, TRIM(CLEAN(Movimientos_Inventario!C:C)) = TRIM(CLEAN(A19)), Movimientos_Inventario!G:G <> """" ) ) ), """")"),"CATALOGO MUJER") -> CATALOGO MUJER | G19: JUAN DAVID (AURA) BOGOTA | H19: 2 | I19: =IF(H19=0,"AGOTADO",IF(H19<=10,"CASI AGOTADO","DISPONIBLE")) -> CASI AGOTADO
A20: FL01006300 | B20: CAMPANOLAS BLANCAS | C20: FLORES | E20: BLANCAS | F20: =IFERROR(__xludf.DUMMYFUNCTION("IFERROR( TEXTJOIN("" | "", TRUE, UNIQUE( FILTER( Movimientos_Inventario!G:G, TRIM(CLEAN(Movimientos_Inventario!C:C)) = TRIM(CLEAN(A20)), Movimientos_Inventario!G:G <> """" ) ) ), """")"),"") | G20: JUAN DAVID (AURA) BOGOTA | I20: =IF(H20=0,"AGOTADO",IF(H20<=10,"CASI AGOTADO","DISPONIBLE")) -> AGOTADO
A21: FL01011300 | B21: CAMPANOLAS MORADA | C21: FLORES | E21: MORADA | F21: =IFERROR(__xludf.DUMMYFUNCTION("IFERROR( TEXTJOIN("" | "", TRUE, UNIQUE( FILTER( Movimientos_Inventario!G:G, TRIM(CLEAN(Movimientos_Inventario!C:C)) = TRIM(CLEAN(A21)), Movimientos_Inventario!G:G <> """" ) ) ), """")"),"") | G21: JUAN DAVID (AURA) BOGOTA | I21: =IF(H21=0,"AGOTADO",IF(H21<=10,"CASI AGOTADO","DISPONIBLE")) -> AGOTADO
A22: FL01015300 | B22: CAMPANOLAS ROSADA | C22: FLORES | E22: ROSADA | F22: =IFERROR(__xludf.DUMMYFUNCTION("IFERROR( TEXTJOIN("" | "", TRUE, UNIQUE( FILTER( Movimientos_Inventario!G:G, TRIM(CLEAN(Movimientos_Inventario!C:C)) = TRIM(CLEAN(A22)), Movimientos_Inventario!G:G <> """" ) ) ), """")"),"CATALOGO MUJER") -> CATALOGO MUJER | G22: JUAN DAVID (AURA) BOGOTA | H22: 0 | I22: =IF(H22=0,"AGOTADO",IF(H22<=10,"CASI AGOTADO","DISPONIBLE")) -> AGOTADO
A23: FL01117000 | B23: CANCION DE LA INDIA | C23: FLORES | E23: DE LA INDIA | F23: =IFERROR(__xludf.DUMMYFUNCTION("IFERROR( TEXTJOIN("" | "", TRUE, UNIQUE( FILTER( Movimientos_Inventario!G:G, TRIM(CLEAN(Movimientos_Inventario!C:C)) = TRIM(CLEAN(A23)), Movimientos_Inventario!G:G <> """" ) ) ), """")"),"") | G23: JUAN DAVID AURA / CARLOS SANCHEZ | I23: =IF(H23=0,"AGOTADO",IF(H23<=10,"CASI AGOTADO","DISPONIBLE")) -> AGOTADO
A24: FL01206300 | B24: CARTUCHO | C24: FLORES | F24: =IFERROR(__xludf.DUMMYFUNCTION("IFERROR( TEXTJOIN("" | "", TRUE, UNIQUE( FILTER( Movimientos_Inventario!G:G, TRIM(CLEAN(Movimientos_Inventario!C:C)) = TRIM(CLEAN(A24)), Movimientos_Inventario!G:G <> """" ) ) ), """")"),"") | G24: JUAN DAVID (AURA) BOGOTA | I24: =IF(H24=0,"AGOTADO",IF(H24<=10,"CASI AGOTADO","DISPONIBLE")) -> AGOTADO
A25: FL01309300 | B25: CHAMELIA FUSCIA | C25: FLORES | E25: FUSCIA | F25: =IFERROR(__xludf.DUMMYFUNCTION("IFERROR( TEXTJOIN("" | "", TRUE, UNIQUE( FILTER( Movimientos_Inventario!G:G, TRIM(CLEAN(Movimientos_Inventario!C:C)) = TRIM(CLEAN(A25)), Movimientos_Inventario!G:G <> """" ) ) ), """")"),"") | G25: JUAN DAVID (AURA) BOGOTA | I25: =IF(H25=0,"AGOTADO",IF(H25<=10,"CASI AGOTADO","DISPONIBLE")) -> AGOTADO
A26: FL01315300 | B26: CHAMELIA ROSADA | C26: FLORES | E26: ROSADA | F26: =IFERROR(__xludf.DUMMYFUNCTION("IFERROR( TEXTJOIN("" | "", TRUE, UNIQUE( FILTER( Movimientos_Inventario!G:G, TRIM(CLEAN(Movimientos_Inventario!C:C)) = TRIM(CLEAN(A26)), Movimientos_Inventario!G:G <> """" ) ) ), """")"),"") | G26: JUAN DAVID (AURA) BOGOTA | I26: =IF(H26=0,"AGOTADO",IF(H26<=10,"CASI AGOTADO","DISPONIBLE")) -> AGOTADO
A27: FL01412300 | B27: CHISPITAS | C27: FLORES | F27: =IFERROR(__xludf.DUMMYFUNCTION("IFERROR( TEXTJOIN("" | "", TRUE, UNIQUE( FILTER( Movimientos_Inventario!G:G, TRIM(CLEAN(Movimientos_Inventario!C:C)) = TRIM(CLEAN(A27)), Movimientos_Inventario!G:G <> """" ) ) ), """")"),"") | G27: JUAN DAVID (AURA) BOGOTA | I27: =IF(H27=0,"AGOTADO",IF(H27<=10,"CASI AGOTADO","DISPONIBLE")) -> AGOTADO
A28: FL01501300 | B28: CLAVEL AMARILLO | C28: FLORES | E28: AMARILLO | F28: =IFERROR(__xludf.DUMMYFUNCTION("IFERROR( TEXTJOIN("" | "", TRUE, UNIQUE( FILTER( Movimientos_Inventario!G:G, TRIM(CLEAN(Movimientos_Inventario!C:C)) = TRIM(CLEAN(A28)), Movimientos_Inventario!G:G <> """" ) ) ), """")"),"") | G28: JUAN DAVID (AURA) BOGOTA | I28: =IF(H28=0,"AGOTADO",IF(H28<=10,"CASI AGOTADO","DISPONIBLE")) -> AGOTADO
A29: FL01505300 | B29: CLAVEL BICOLOR | C29: FLORES | E29: BICOLOR | F29: =IFERROR(__xludf.DUMMYFUNCTION("IFERROR( TEXTJOIN("" | "", TRUE, UNIQUE( FILTER( Movimientos_Inventario!G:G, TRIM(CLEAN(Movimientos_Inventario!C:C)) = TRIM(CLEAN(A29)), Movimientos_Inventario!G:G <> """" ) ) ), """")"),"") | G29: JUAN DAVID (AURA) BOGOTA | I29: =IF(H29=0,"AGOTADO",IF(H29<=10,"CASI AGOTADO","DISPONIBLE")) -> AGOTADO
A30: FL01506300 | B30: CLAVEL BLANCO | C30: FLORES | E30: BLANCO | F30: =IFERROR(__xludf.DUMMYFUNCTION("IFERROR( TEXTJOIN("" | "", TRUE, UNIQUE( FILTER( Movimientos_Inventario!G:G, TRIM(CLEAN(Movimientos_Inventario!C:C)) = TRIM(CLEAN(A30)), Movimientos_Inventario!G:G <> """" ) ) ), """")"),"") | G30: JUAN DAVID (AURA) BOGOTA | I30: =IF(H30=0,"AGOTADO",IF(H30<=10,"CASI AGOTADO","DISPONIBLE")) -> AGOTADO
A31: FL01509300 | B31: CLAVEL FUCSIA | C31: FLORES | E31: FUCSIA | F31: =IFERROR(__xludf.DUMMYFUNCTION("IFERROR( TEXTJOIN("" | "", TRUE, UNIQUE( FILTER( Movimientos_Inventario!G:G, TRIM(CLEAN(Movimientos_Inventario!C:C)) = TRIM(CLEAN(A31)), Movimientos_Inventario!G:G <> """" ) ) ), """")"),"CATALOGO MUJER") -> CATALOGO MUJER | G31: JUAN DAVID (AURA) BOGOTA | H31: 15 | I31: =IF(H31=0,"AGOTADO",IF(H31<=10,"CASI AGOTADO","DISPONIBLE")) -> DISPONIBLE
A32: FL01519300 | B32: CLAVEL MAMON | C32: FLORES | E32: MAMON | F32: =IFERROR(__xludf.DUMMYFUNCTION("IFERROR( TEXTJOIN("" | "", TRUE, UNIQUE( FILTER( Movimientos_Inventario!G:G, TRIM(CLEAN(Movimientos_Inventario!C:C)) = TRIM(CLEAN(A32)), Movimientos_Inventario!G:G <> """" ) ) ), """")"),"CATALOGO MUJER") -> CATALOGO MUJER | G32: JUAN DAVID (AURA) BOGOTA | H32: 8 | I32: =IF(H32=0,"AGOTADO",IF(H32<=10,"CASI AGOTADO","DISPONIBLE")) -> CASI AGOTADO
A33: FL01512300 | B33: CLAVEL NARANJA | C33: FLORES | E33: NARANJA | F33: =IFERROR(__xludf.DUMMYFUNCTION("IFERROR( TEXTJOIN("" | "", TRUE, UNIQUE( FILTER( Movimientos_Inventario!G:G, TRIM(CLEAN(Movimientos_Inventario!C:C)) = TRIM(CLEAN(A33)), Movimientos_Inventario!G:G <> """" ) ) ), """")"),"") | G33: JUAN DAVID (AURA) BOGOTA | I33: =IF(H33=0,"AGOTADO",IF(H33<=10,"CASI AGOTADO","DISPONIBLE")) -> AGOTADO
A34: FL01504300 | B34: CLAVEL BEIGE | C34: FLORES | E34: BEIGE | F34: =IFERROR(__xludf.DUMMYFUNCTION("IFERROR( TEXTJOIN("" | "", TRUE, UNIQUE( FILTER( Movimientos_Inventario!G:G, TRIM(CLEAN(Movimientos_Inventario!C:C)) = TRIM(CLEAN(A34)), Movimientos_Inventario!G:G <> """" ) ) ), """")"),"") | G34: JUAN DAVID (AURA) BOGOTA | I34: =IF(H34=0,"AGOTADO",IF(H34<=10,"CASI AGOTADO","DISPONIBLE")) -> AGOTADO
A35: FL01514300 | B35: CLAVEL ROJO | C35: FLORES | E35: ROJO | F35: =IFERROR(__xludf.DUMMYFUNCTION("IFERROR( TEXTJOIN("" | "", TRUE, UNIQUE( FILTER( Movimientos_Inventario!G:G, TRIM(CLEAN(Movimientos_Inventario!C:C)) = TRIM(CLEAN(A35)), Movimientos_Inventario!G:G <> """" ) ) ), """")"),"") | G35: JUAN DAVID (AURA) BOGOTA | I35: =IF(H35=0,"AGOTADO",IF(H35<=10,"CASI AGOTADO","DISPONIBLE")) -> AGOTADO
A36: FL01515300 | B36: CLAVEL ROSADO | C36: FLORES | E36: ROSADO | F36: =IFERROR(__xludf.DUMMYFUNCTION("IFERROR( TEXTJOIN("" | "", TRUE, UNIQUE( FILTER( Movimientos_Inventario!G:G, TRIM(CLEAN(Movimientos_Inventario!C:C)) = TRIM(CLEAN(A36)), Movimientos_Inventario!G:G <> """" ) ) ), """")"),"CATALOGO MUJER") -> CATALOGO MUJER | G36: JUAN DAVID (AURA) BOGOTA | H36: 26 | I36: =IF(H36=0,"AGOTADO",IF(H36<=10,"CASI AGOTADO","DISPONIBLE")) -> DISPONIBLE
A37: FL01606300 | B37: CLAVEL CHINO BLANCO | C37: FLORES | E37: CHINO BLANCO | F37: =IFERROR(__xludf.DUMMYFUNCTION("IFERROR( TEXTJOIN("" | "", TRUE, UNIQUE( FILTER( Movimientos_Inventario!G:G, TRIM(CLEAN(Movimientos_Inventario!C:C)) = TRIM(CLEAN(A37)), Movimientos_Inventario!G:G <> """" ) ) ), """")"),"") | G37: JUAN DAVID (AURA) BOGOTA | I37: =IF(H37=0,"AGOTADO",IF(H37<=10,"CASI AGOTADO","DISPONIBLE")) -> AGOTADO
A38: FL01614300 | B38: CLAVEL CHINO ROJO | C38: FLORES | E38: CHINO ROJO | F38: =IFERROR(__xludf.DUMMYFUNCTION("IFERROR( TEXTJOIN("" | "", TRUE, UNIQUE( FILTER( Movimientos_Inventario!G:G, TRIM(CLEAN(Movimientos_Inventario!C:C)) = TRIM(CLEAN(A38)), Movimientos_Inventario!G:G <> """" ) ) ), """")"),"") | G38: JUAN DAVID (AURA) BOGOTA | I38: =IF(H38=0,"AGOTADO",IF(H38<=10,"CASI AGOTADO","DISPONIBLE")) -> AGOTADO
A39: FL01615300 | B39: CLAVEL CHINO ROSADO | C39: FLORES | E39: CHINO ROSADO | F39: =IFERROR(__xludf.DUMMYFUNCTION("IFERROR( TEXTJOIN("" | "", TRUE, UNIQUE( FILTER( Movimientos_Inventario!G:G, TRIM(CLEAN(Movimientos_Inventario!C:C)) = TRIM(CLEAN(A39)), Movimientos_Inventario!G:G <> """" ) ) ), """")"),"") | G39: JUAN DAVID (AURA) BOGOTA | I39: =IF(H39=0,"AGOTADO",IF(H39<=10,"CASI AGOTADO","DISPONIBLE")) -> AGOTADO
A40: FL01701300 | B40: CLAVELLINA AMARILLA | C40: FLORES | E40: AMARILLA | F40: =IFERROR(__xludf.DUMMYFUNCTION("IFERROR( TEXTJOIN("" | "", TRUE, UNIQUE( FILTER( Movimientos_Inventario!G:G, TRIM(CLEAN(Movimientos_Inventario!C:C)) = TRIM(CLEAN(A40)), Movimientos_Inventario!G:G <> """" ) ) ), """")"),"CATALOGO MUJER") -> CATALOGO MUJER | G40: JUAN DAVID (AURA) BOGOTA | H40: 3 | I40: =IF(H40=0,"AGOTADO",IF(H40<=10,"CASI AGOTADO","DISPONIBLE")) -> CASI AGOTADO
A41: FL01706300 | B41: CLAVELLINA BLANCA | C41: FLORES | E41: BLANCA | F41: =IFERROR(__xludf.DUMMYFUNCTION("IFERROR( TEXTJOIN("" | "", TRUE, UNIQUE( FILTER( Movimientos_Inventario!G:G, TRIM(CLEAN(Movimientos_Inventario!C:C)) = TRIM(CLEAN(A41)), Movimientos_Inventario!G:G <> """" ) ) ), """")"),"") | G41: JUAN DAVID (AURA) BOGOTA | H41: 7 | I41: =IF(H41=0,"AGOTADO",IF(H41<=10,"CASI AGOTADO","DISPONIBLE")) -> CASI AGOTADO
A42: FL01709300 | B42: CLAVELLINA FUCSIA | C42: FLORES | E42: FUCSIA | F42: CATALOGO MUJER | G42: JUAN DAVID (AURA) BOGOTA | H42: 5 | I42: =IF(H42=0,"AGOTADO",IF(H42<=10,"CASI AGOTADO","DISPONIBLE")) -> CASI AGOTADO
A43: FL01711300 | B43: CLAVELLINA MORADA | C43: FLORES | E43: MORADA | F43: =IFERROR(__xludf.DUMMYFUNCTION("IFERROR( TEXTJOIN("" | "", TRUE, UNIQUE( FILTER( Movimientos_Inventario!G:G, TRIM(CLEAN(Movimientos_Inventario!C:C)) = TRIM(CLEAN(A43)), Movimientos_Inventario!G:G <> """" ) ) ), """")"),"") | G43: JUAN DAVID (AURA) BOGOTA | I43: =IF(H43=0,"AGOTADO",IF(H43<=10,"CASI AGOTADO","DISPONIBLE")) -> AGOTADO
A44: FL01712300 | B44: CLAVELLINA NARANJA | C44: FLORES | E44: NARANJA | F44: =IFERROR(__xludf.DUMMYFUNCTION("IFERROR( TEXTJOIN("" | "", TRUE, UNIQUE( FILTER( Movimientos_Inventario!G:G, TRIM(CLEAN(Movimientos_Inventario!C:C)) = TRIM(CLEAN(A44)), Movimientos_Inventario!G:G <> """" ) ) ), """")"),"") | G44: JUAN DAVID (AURA) BOGOTA | I44: =IF(H44=0,"AGOTADO",IF(H44<=10,"CASI AGOTADO","DISPONIBLE")) -> AGOTADO
A45: FL01714300 | B45: CLAVELLINA ROJA | C45: FLORES | E45: ROJA | F45: =IFERROR(__xludf.DUMMYFUNCTION("IFERROR( TEXTJOIN("" | "", TRUE, UNIQUE( FILTER( Movimientos_Inventario!G:G, TRIM(CLEAN(Movimientos_Inventario!C:C)) = TRIM(CLEAN(A45)), Movimientos_Inventario!G:G <> """" ) ) ), """")"),"") | G45: JUAN DAVID (AURA) BOGOTA | I45: =IF(H45=0,"AGOTADO",IF(H45<=10,"CASI AGOTADO","DISPONIBLE")) -> AGOTADO
A46: FL01715300 | B46: CLAVELLINA ROSADA | C46: FLORES | E46: ROSADA | F46: CATALOGO MUJER | G46: JUAN DAVID (AURA) BOGOTA | H46: 34 | I46: =IF(H46=0,"AGOTADO",IF(H46<=10,"CASI AGOTADO","DISPONIBLE")) -> DISPONIBLE
A47: FL01705300 | B47: CLAVELLINA BICOLOR | C47: FLORES | E47: BICOLOR | F47: =IFERROR(__xludf.DUMMYFUNCTION("IFERROR( TEXTJOIN("" | "", TRUE, UNIQUE( FILTER( Movimientos_Inventario!G:G, TRIM(CLEAN(Movimientos_Inventario!C:C)) = TRIM(CLEAN(A47)), Movimientos_Inventario!G:G <> """" ) ) ), """")"),"") | G47: JUAN DAVID (AURA) BOGOTA | I47: =IF(H47=0,"AGOTADO",IF(H47<=10,"CASI AGOTADO","DISPONIBLE")) -> AGOTADO
A48: FL01811400 | B48: COLLES MORADO | C48: FLORES | E48: MORADO | F48: =IFERROR(__xludf.DUMMYFUNCTION("IFERROR( TEXTJOIN("" | "", TRUE, UNIQUE( FILTER( Movimientos_Inventario!G:G, TRIM(CLEAN(Movimientos_Inventario!C:C)) = TRIM(CLEAN(A48)), Movimientos_Inventario!G:G <> """" ) ) ), """")"),"") | G48: CARLOS SANCHEZ MEDELLIN | I48: =IF(H48=0,"AGOTADO",IF(H48<=10,"CASI AGOTADO","DISPONIBLE")) -> AGOTADO
A49: FL01817300 | B49: COLLES VERDE | C49: FLORES | E49: VERDE | F49: =IFERROR(__xludf.DUMMYFUNCTION("IFERROR( TEXTJOIN("" | "", TRUE, UNIQUE( FILTER( Movimientos_Inventario!G:G, TRIM(CLEAN(Movimientos_Inventario!C:C)) = TRIM(CLEAN(A49)), Movimientos_Inventario!G:G <> """" ) ) ), """")"),"") | G49: JUAN DAVID (AURA) BOGOTA | I49: =IF(H49=0,"AGOTADO",IF(H49<=10,"CASI AGOTADO","DISPONIBLE")) -> AGOTADO
A50: FL01901000 | B50: CRASPEDIA | C50: FLORES | F50: =IFERROR(__xludf.DUMMYFUNCTION("IFERROR( TEXTJOIN("" | "", TRUE, UNIQUE( FILTER( Movimientos_Inventario!G:G, TRIM(CLEAN(Movimientos_Inventario!C:C)) = TRIM(CLEAN(A50)), Movimientos_Inventario!G:G <> """" ) ) ), """")"),"") | G50: JUAN DAVID AURA / CARLOS SANCHEZ | I50: =IF(H50=0,"AGOTADO",IF(H50<=10,"CASI AGOTADO","DISPONIBLE")) -> AGOTADO
A51: FL02015000 | B51: CRISANTEMOS ROSADO | C51: FLORES | E51: ROSADO | F51: =IFERROR(__xludf.DUMMYFUNCTION("IFERROR( TEXTJOIN("" | "", TRUE, UNIQUE( FILTER( Movimientos_Inventario!G:G, TRIM(CLEAN(Movimientos_Inventario!C:C)) = TRIM(CLEAN(A51)), Movimientos_Inventario!G:G <> """" ) ) ), """")"),"") | G51: JUAN DAVID AURA / CARLOS SANCHEZ | I51: =IF(H51=0,"AGOTADO",IF(H51<=10,"CASI AGOTADO","DISPONIBLE")) -> AGOTADO
A52: FL02006400 | B52: CRISANTEMOS BLANCO | C52: FLORES | E52: BLANCO | F52: =IFERROR(__xludf.DUMMYFUNCTION("IFERROR( TEXTJOIN("" | "", TRUE, UNIQUE( FILTER( Movimientos_Inventario!G:G, TRIM(CLEAN(Movimientos_Inventario!C:C)) = TRIM(CLEAN(A52)), Movimientos_Inventario!G:G <> """" ) ) ), """")"),"") | G52: CARLOS SANCHEZ MEDELLIN | I52: =IF(H52=0,"AGOTADO",IF(H52<=10,"CASI AGOTADO","DISPONIBLE")) -> AGOTADO
A53: FL02010400 | B53: CRISANTEMOS LILA | C53: FLORES | E53: LILA | F53: =IFERROR(__xludf.DUMMYFUNCTION("IFERROR( TEXTJOIN("" | "", TRUE, UNIQUE( FILTER( Movimientos_Inventario!G:G, TRIM(CLEAN(Movimientos_Inventario!C:C)) = TRIM(CLEAN(A53)), Movimientos_Inventario!G:G <> """" ) ) ), """")"),"") | G53: CARLOS SANCHEZ MEDELLIN | I53: =IF(H53=0,"AGOTADO",IF(H53<=10,"CASI AGOTADO","DISPONIBLE")) -> AGOTADO
A54: FL02111300 | B54: DELFINIOS MORADO | C54: FLORES | E54: MORADO | F54: =IFERROR(__xludf.DUMMYFUNCTION("IFERROR( TEXTJOIN("" | "", TRUE, UNIQUE( FILTER( Movimientos_Inventario!G:G, TRIM(CLEAN(Movimientos_Inventario!C:C)) = TRIM(CLEAN(A54)), Movimientos_Inventario!G:G <> """" ) ) ), """")"),"") | G54: JUAN DAVID (AURA) BOGOTA | I54: =IF(H54=0,"AGOTADO",IF(H54<=10,"CASI AGOTADO","DISPONIBLE")) -> AGOTADO
A55: FL02103300 | B55: DELFINIOS AZUL | C55: FLORES | E55: AZUL | F55: =IFERROR(__xludf.DUMMYFUNCTION("IFERROR( TEXTJOIN("" | "", TRUE, UNIQUE( FILTER( Movimientos_Inventario!G:G, TRIM(CLEAN(Movimientos_Inventario!C:C)) = TRIM(CLEAN(A55)), Movimientos_Inventario!G:G <> """" ) ) ), """")"),"") | G55: JUAN DAVID (AURA) BOGOTA | I55: =IF(H55=0,"AGOTADO",IF(H55<=10,"CASI AGOTADO","DISPONIBLE")) -> AGOTADO
A56: FL02106300 | B56: DELFINIOS BLANCO | C56: FLORES | E56: BLANCO | F56: =IFERROR(__xludf.DUMMYFUNCTION("IFERROR( TEXTJOIN("" | "", TRUE, UNIQUE( FILTER( Movimientos_Inventario!G:G, TRIM(CLEAN(Movimientos_Inventario!C:C)) = TRIM(CLEAN(A56)), Movimientos_Inventario!G:G <> """" ) ) ), """")"),"") | G56: JUAN DAVID (AURA) BOGOTA | I56: =IF(H56=0,"AGOTADO",IF(H56<=10,"CASI AGOTADO","DISPONIBLE")) -> AGOTADO
A57: FL02110300 | B57: DELFINIOS LILA | C57: FLORES | E57: LILA | F57: =IFERROR(__xludf.DUMMYFUNCTION("IFERROR( TEXTJOIN("" | "", TRUE, UNIQUE( FILTER( Movimientos_Inventario!G:G, TRIM(CLEAN(Movimientos_Inventario!C:C)) = TRIM(CLEAN(A57)), Movimientos_Inventario!G:G <> """" ) ) ), """")"),"") | G57: JUAN DAVID (AURA) BOGOTA | I57: =IF(H57=0,"AGOTADO",IF(H57<=10,"CASI AGOTADO","DISPONIBLE")) -> AGOTADO
A58: FL02215300 | B58: ESPIDIA ROSADA | C58: FLORES | E58: ROSADA | F58: =IFERROR(__xludf.DUMMYFUNCTION("IFERROR( TEXTJOIN("" | "", TRUE, UNIQUE( FILTER( Movimientos_Inventario!G:G, TRIM(CLEAN(Movimientos_Inventario!C:C)) = TRIM(CLEAN(A58)), Movimientos_Inventario!G:G <> """" ) ) ), """")"),"CATALOGO MUJER") -> CATALOGO MUJER | G58: JUAN DAVID (AURA) BOGOTA | H58: 2 | I58: =IF(H58=0,"AGOTADO",IF(H58<=10,"CASI AGOTADO","DISPONIBLE")) -> CASI AGOTADO
A59: FL02306300 | B59: ESTRELLA DE BELEN | C59: FLORES | E59: DE BELEN | F59: =IFERROR(__xludf.DUMMYFUNCTION("IFERROR( TEXTJOIN("" | "", TRUE, UNIQUE( FILTER( Movimientos_Inventario!G:G, TRIM(CLEAN(Movimientos_Inventario!C:C)) = TRIM(CLEAN(A59)), Movimientos_Inventario!G:G <> """" ) ) ), """")"),"") | G59: JUAN DAVID (AURA) BOGOTA | I59: =IF(H59=0,"AGOTADO",IF(H59<=10,"CASI AGOTADO","DISPONIBLE")) -> AGOTADO
A60: FL02401300 | B60: FRESIA AMARILLA | C60: FLORES | E60: AMARILLA | F60: =IFERROR(__xludf.DUMMYFUNCTION("IFERROR( TEXTJOIN("" | "", TRUE, UNIQUE( FILTER( Movimientos_Inventario!G:G, TRIM(CLEAN(Movimientos_Inventario!C:C)) = TRIM(CLEAN(A60)), Movimientos_Inventario!G:G <> """" ) ) ), """")"),"") | G60: JUAN DAVID (AURA) BOGOTA | I60: =IF(H60=0,"AGOTADO",IF(H60<=10,"CASI AGOTADO","DISPONIBLE")) -> AGOTADO
A61: FL02411300 | B61: FRESIAS MORADA | C61: FLORES | E61: MORADA | F61: =IFERROR(__xludf.DUMMYFUNCTION("IFERROR( TEXTJOIN("" | "", TRUE, UNIQUE( FILTER( Movimientos_Inventario!G:G, TRIM(CLEAN(Movimientos_Inventario!C:C)) = TRIM(CLEAN(A61)), Movimientos_Inventario!G:G <> """" ) ) ), """")"),"") | G61: JUAN DAVID (AURA) BOGOTA | I61: =IF(H61=0,"AGOTADO",IF(H61<=10,"CASI AGOTADO","DISPONIBLE")) -> AGOTADO
A62: FL02506400 | B62: FULLY BLANCO | C62: FLORES | E62: BLANCO | F62: =IFERROR(__xludf.DUMMYFUNCTION("IFERROR( TEXTJOIN("" | "", TRUE, UNIQUE( FILTER( Movimientos_Inventario!G:G, TRIM(CLEAN(Movimientos_Inventario!C:C)) = TRIM(CLEAN(A62)), Movimientos_Inventario!G:G <> """" ) ) ), """")"),"") | G62: JUAN DAVID (AURA) BOGOTA | I62: =IF(H62=0,"AGOTADO",IF(H62<=10,"CASI AGOTADO","DISPONIBLE")) -> AGOTADO
A63: FL02501400 | B63: FULLY AMARILLO | C63: FLORES | E63: AMARILLO | F63: =IFERROR(__xludf.DUMMYFUNCTION("IFERROR( TEXTJOIN("" | "", TRUE, UNIQUE( FILTER( Movimientos_Inventario!G:G, TRIM(CLEAN(Movimientos_Inventario!C:C)) = TRIM(CLEAN(A63)), Movimientos_Inventario!G:G <> """" ) ) ), """")"),"") | G63: CARLOS SANCHEZ MEDELLIN | I63: =IF(H63=0,"AGOTADO",IF(H63<=10,"CASI AGOTADO","DISPONIBLE")) -> AGOTADO
A64: FL02511400 | B64: FULLY MORADO | C64: FLORES | E64: MORADO | F64: =IFERROR(__xludf.DUMMYFUNCTION("IFERROR( TEXTJOIN("" | "", TRUE, UNIQUE( FILTER( Movimientos_Inventario!G:G, TRIM(CLEAN(Movimientos_Inventario!C:C)) = TRIM(CLEAN(A64)), Movimientos_Inventario!G:G <> """" ) ) ), """")"),"") | G64: CARLOS SANCHEZ MEDELLIN | I64: =IF(H64=0,"AGOTADO",IF(H64<=10,"CASI AGOTADO","DISPONIBLE")) -> AGOTADO
A65: FL02510400 | B65: FULLY LILA | C65: FLORES | E65: LILA | F65: =IFERROR(__xludf.DUMMYFUNCTION("IFERROR( TEXTJOIN("" | "", TRUE, UNIQUE( FILTER( Movimientos_Inventario!G:G, TRIM(CLEAN(Movimientos_Inventario!C:C)) = TRIM(CLEAN(A65)), Movimientos_Inventario!G:G <> """" ) ) ), """")"),"") | G65: CARLOS SANCHEZ MEDELLIN | I65: =IF(H65=0,"AGOTADO",IF(H65<=10,"CASI AGOTADO","DISPONIBLE")) -> AGOTADO
A66: FL02517400 | B66: FULLY VERDE | C66: FLORES | E66: VERDE | F66: =IFERROR(__xludf.DUMMYFUNCTION("IFERROR( TEXTJOIN("" | "", TRUE, UNIQUE( FILTER( Movimientos_Inventario!G:G, TRIM(CLEAN(Movimientos_Inventario!C:C)) = TRIM(CLEAN(A66)), Movimientos_Inventario!G:G <> """" ) ) ), """")"),"") | G66: CARLOS SANCHEZ MEDELLIN | I66: =IF(H66=0,"AGOTADO",IF(H66<=10,"CASI AGOTADO","DISPONIBLE")) -> AGOTADO
A67: FL02601400 | B67: GERBERAS AMARILLA | C67: FLORES | E67: AMARILLA | F67: =IFERROR(__xludf.DUMMYFUNCTION("IFERROR( TEXTJOIN("" | "", TRUE, UNIQUE( FILTER( Movimientos_Inventario!G:G, TRIM(CLEAN(Movimientos_Inventario!C:C)) = TRIM(CLEAN(A67)), Movimientos_Inventario!G:G <> """" ) ) ), """")"),"") | G67: CARLOS SANCHEZ MEDELLIN | I67: =IF(H67=0,"AGOTADO",IF(H67<=10,"CASI AGOTADO","DISPONIBLE")) -> AGOTADO
A68: FL02606400 | B68: GERBERAS BLANCA | C68: FLORES | E68: BLANCA | F68: CATALOGO MUJER | G68: CARLOS SANCHEZ MEDELLIN | H68: 2 | I68: =IF(H68=0,"AGOTADO",IF(H68<=10,"CASI AGOTADO","DISPONIBLE")) -> CASI AGOTADO
A69: FL02609400 | B69: GERBERAS FUCSIA | C69: FLORES | E69: FUCSIA | F69: =IFERROR(__xludf.DUMMYFUNCTION("IFERROR( TEXTJOIN("" | "", TRUE, UNIQUE( FILTER( Movimientos_Inventario!G:G, TRIM(CLEAN(Movimientos_Inventario!C:C)) = TRIM(CLEAN(A69)), Movimientos_Inventario!G:G <> """" ) ) ), """")"),"") | G69: CARLOS SANCHEZ MEDELLIN | I69: =IF(H69=0,"AGOTADO",IF(H69<=10,"CASI AGOTADO","DISPONIBLE")) -> AGOTADO
A70: FL02612400 | B70: GERBERAS NARANJA | C70: FLORES | E70: NARANJA | F70: =IFERROR(__xludf.DUMMYFUNCTION("IFERROR( TEXTJOIN("" | "", TRUE, UNIQUE( FILTER( Movimientos_Inventario!G:G, TRIM(CLEAN(Movimientos_Inventario!C:C)) = TRIM(CLEAN(A70)), Movimientos_Inventario!G:G <> """" ) ) ), """")"),"") | G70: CARLOS SANCHEZ MEDELLIN | I70: =IF(H70=0,"AGOTADO",IF(H70<=10,"CASI AGOTADO","DISPONIBLE")) -> AGOTADO
A71: FL02615400 | B71: GERBERAS ROSADA | C71: FLORES | E71: ROSADA | F71: CATALOGO MUJER | G71: CARLOS SANCHEZ MEDELLIN | H71: 9 | I71: =IF(H71=0,"AGOTADO",IF(H71<=10,"CASI AGOTADO","DISPONIBLE")) -> CASI AGOTADO
A72: FL02614400 | B72: GERBERAS ROJAS | C72: FLORES | E72: ROJAS | F72: =IFERROR(__xludf.DUMMYFUNCTION("IFERROR( TEXTJOIN("" | "", TRUE, UNIQUE( FILTER( Movimientos_Inventario!G:G, TRIM(CLEAN(Movimientos_Inventario!C:C)) = TRIM(CLEAN(A72)), Movimientos_Inventario!G:G <> """" ) ) ), """")"),"") | G72: CARLOS SANCHEZ MEDELLIN | I72: =IF(H72=0,"AGOTADO",IF(H72<=10,"CASI AGOTADO","DISPONIBLE")) -> AGOTADO
A73: FL02701400 | B73: GIRASOL | C73: FLORES | E73: AMARILLO | F73: =IFERROR(__xludf.DUMMYFUNCTION("IFERROR( TEXTJOIN("" | "", TRUE, UNIQUE( FILTER( Movimientos_Inventario!G:G, TRIM(CLEAN(Movimientos_Inventario!C:C)) = TRIM(CLEAN(A73)), Movimientos_Inventario!G:G <> """" ) ) ), """")"),"") | G73: JUAN DAVID (AURA) BOGOTA | I73: =IF(H73=0,"AGOTADO",IF(H73<=10,"CASI AGOTADO","DISPONIBLE")) -> AGOTADO
A74: FL02806300 | B74: GLADIOLO BLANCO | C74: FLORES | E74: BLANCO | G74: JUAN DAVID (AURA) BOGOTA | I74: =IF(H74=0,"AGOTADO",IF(H74<=10,"CASI AGOTADO","DISPONIBLE")) -> AGOTADO
A75: FL02815300 | B75: GLADIOLO ROSADO | C75: FLORES | E75: ROSADO | F75: =IFERROR(__xludf.DUMMYFUNCTION("IFERROR( TEXTJOIN("" | "", TRUE, UNIQUE( FILTER( Movimientos_Inventario!G:G, TRIM(CLEAN(Movimientos_Inventario!C:C)) = TRIM(CLEAN(A75)), Movimientos_Inventario!G:G <> """" ) ) ), """")"),"") | G75: JUAN DAVID (AURA) BOGOTA | H75: 1 | I75: =IF(H75=0,"AGOTADO",IF(H75<=10,"CASI AGOTADO","DISPONIBLE")) -> CASI AGOTADO
A76: FL02814300 | B76: GLADIOLO ROJO | C76: FLORES | E76: ROJO | F76: =IFERROR(__xludf.DUMMYFUNCTION("IFERROR( TEXTJOIN("" | "", TRUE, UNIQUE( FILTER( Movimientos_Inventario!G:G, TRIM(CLEAN(Movimientos_Inventario!C:C)) = TRIM(CLEAN(A76)), Movimientos_Inventario!G:G <> """" ) ) ), """")"),"") | G76: JUAN DAVID (AURA) BOGOTA | I76: =IF(H76=0,"AGOTADO",IF(H76<=10,"CASI AGOTADO","DISPONIBLE")) -> AGOTADO
A77: FL02809300 | B77: GLADIOLO FUSCIA | C77: FLORES | E77: FUSCIA | F77: =IFERROR(__xludf.DUMMYFUNCTION("IFERROR( TEXTJOIN("" | "", TRUE, UNIQUE( FILTER( Movimientos_Inventario!G:G, TRIM(CLEAN(Movimientos_Inventario!C:C)) = TRIM(CLEAN(A77)), Movimientos_Inventario!G:G <> """" ) ) ), """")"),"") | G77: JUAN DAVID (AURA) BOGOTA | I77: =IF(H77=0,"AGOTADO",IF(H77<=10,"CASI AGOTADO","DISPONIBLE")) -> AGOTADO
A78: FL02915300 | B78: GODETIA ROSADA | C78: FLORES | E78: ROSADA | F78: CATALOGO MUJER | G78: JUAN DAVID (AURA) BOGOTA | H78: 2 | I78: =IF(H78=0,"AGOTADO",IF(H78<=10,"CASI AGOTADO","DISPONIBLE")) -> CASI AGOTADO
A79: FL02909300 | B79: GODETIA FUSCIA | C79: FLORES | E79: FUSCIA | F79: =IFERROR(__xludf.DUMMYFUNCTION("IFERROR( TEXTJOIN("" | "", TRUE, UNIQUE( FILTER( Movimientos_Inventario!G:G, TRIM(CLEAN(Movimientos_Inventario!C:C)) = TRIM(CLEAN(A79)), Movimientos_Inventario!G:G <> """" ) ) ), """")"),"") | G79: JUAN DAVID (AURA) BOGOTA | I79: =IF(H79=0,"AGOTADO",IF(H79<=10,"CASI AGOTADO","DISPONIBLE")) -> AGOTADO
A80: FL02906300 | B80: GODETIA BLANCA | C80: FLORES | E80: BLANCA | F80: =IFERROR(__xludf.DUMMYFUNCTION("IFERROR( TEXTJOIN("" | "", TRUE, UNIQUE( FILTER( Movimientos_Inventario!G:G, TRIM(CLEAN(Movimientos_Inventario!C:C)) = TRIM(CLEAN(A80)), Movimientos_Inventario!G:G <> """" ) ) ), """")"),"") | G80: JUAN DAVID (AURA) BOGOTA | I80: =IF(H80=0,"AGOTADO",IF(H80<=10,"CASI AGOTADO","DISPONIBLE")) -> AGOTADO
A81: FL03006000 | B81: GYPSO | C81: FLORES | E81: BLANCO | F81: =IFERROR(__xludf.DUMMYFUNCTION("IFERROR( TEXTJOIN("" | "", TRUE, UNIQUE( FILTER( Movimientos_Inventario!G:G, TRIM(CLEAN(Movimientos_Inventario!C:C)) = TRIM(CLEAN(A81)), Movimientos_Inventario!G:G <> """" ) ) ), """")"),"CATALOGO MUJER") -> CATALOGO MUJER | G81: JUAN DAVID AURA / CARLOS SANCHEZ | H81: 3 | I81: =IF(H81=0,"AGOTADO",IF(H81<=10,"CASI AGOTADO","DISPONIBLE")) -> CASI AGOTADO
A82: FL03102400 | B82: HORTENCIA ANTIQUE | C82: FLORES | E82: ANTIQUE | F82: =IFERROR(__xludf.DUMMYFUNCTION("IFERROR( TEXTJOIN("" | "", TRUE, UNIQUE( FILTER( Movimientos_Inventario!G:G, TRIM(CLEAN(Movimientos_Inventario!C:C)) = TRIM(CLEAN(A82)), Movimientos_Inventario!G:G <> """" ) ) ), """")"),"") | G82: CARLOS SANCHEZ MEDELLIN | I82: =IF(H82=0,"AGOTADO",IF(H82<=10,"CASI AGOTADO","DISPONIBLE")) -> AGOTADO
A83: FL03107400 | B83: HORTENCIA CHOQUI | C83: FLORES | E83: CHOQUI | F83: =IFERROR(__xludf.DUMMYFUNCTION("IFERROR( TEXTJOIN("" | "", TRUE, UNIQUE( FILTER( Movimientos_Inventario!G:G, TRIM(CLEAN(Movimientos_Inventario!C:C)) = TRIM(CLEAN(A83)), Movimientos_Inventario!G:G <> """" ) ) ), """")"),"") | G83: CARLOS SANCHEZ MEDELLIN | I83: =IF(H83=0,"AGOTADO",IF(H83<=10,"CASI AGOTADO","DISPONIBLE")) -> AGOTADO
A84: FL03103400 | B84: HORTENCIA AZUL | C84: FLORES | E84: AZUL | F84: CATALOGO MUJER | G84: CARLOS SANCHEZ MEDELLIN | H84: 20 | I84: =IF(H84=0,"AGOTADO",IF(H84<=10,"CASI AGOTADO","DISPONIBLE")) -> DISPONIBLE
A85: FL03106400 | B85: HORTENCIA BLANCA | C85: FLORES | E85: BLANCA | F85: CATALOGO MUJER | G85: CARLOS SANCHEZ MEDELLIN | H85: 20 | I85: =IF(H85=0,"AGOTADO",IF(H85<=10,"CASI AGOTADO","DISPONIBLE")) -> DISPONIBLE
A86: FL03117400 | B86: HORTENCIA VERDE | C86: FLORES | E86: VERDE | F86: =IFERROR(__xludf.DUMMYFUNCTION("IFERROR( TEXTJOIN("" | "", TRUE, UNIQUE( FILTER( Movimientos_Inventario!G:G, TRIM(CLEAN(Movimientos_Inventario!C:C)) = TRIM(CLEAN(A86)), Movimientos_Inventario!G:G <> """" ) ) ), """")"),"") | G86: CARLOS SANCHEZ MEDELLIN | I86: =IF(H86=0,"AGOTADO",IF(H86<=10,"CASI AGOTADO","DISPONIBLE")) -> AGOTADO
A87: FL03111400 | B87: HORTENCIA MORADA | C87: FLORES | E87: MORADA | F87: =IFERROR(__xludf.DUMMYFUNCTION("IFERROR( TEXTJOIN("" | "", TRUE, UNIQUE( FILTER( Movimientos_Inventario!G:G, TRIM(CLEAN(Movimientos_Inventario!C:C)) = TRIM(CLEAN(A87)), Movimientos_Inventario!G:G <> """" ) ) ), """")"),"") | G87: CARLOS SANCHEZ MEDELLIN | I87: =IF(H87=0,"AGOTADO",IF(H87<=10,"CASI AGOTADO","DISPONIBLE")) -> AGOTADO
A88: FL03118400 | B88: HORTENCIA VERDE CLARA | C88: FLORES | E88: VERDE CLARA | F88: CATALOGO MUJER | G88: CARLOS SANCHEZ MEDELLIN | H88: 10 | I88: =IF(H88=0,"AGOTADO",IF(H88<=10,"CASI AGOTADO","DISPONIBLE")) -> CASI AGOTADO
A89: FL03115400 | B89: HORTENCIA ROSADA | C89: FLORES | E89: ROSADA | F89: =IFERROR(__xludf.DUMMYFUNCTION("IFERROR( TEXTJOIN("" | "", TRUE, UNIQUE( FILTER( Movimientos_Inventario!G:G, TRIM(CLEAN(Movimientos_Inventario!C:C)) = TRIM(CLEAN(A89)), Movimientos_Inventario!G:G <> """" ) ) ), """")"),"") | G89: CARLOS SANCHEZ MEDELLIN | I89: =IF(H89=0,"AGOTADO",IF(H89<=10,"CASI AGOTADO","DISPONIBLE")) -> AGOTADO
A90: FL03116400 | B90: HORTENCIAS ESMERALDA | C90: FLORES | E90: ESMERALDA | F90: =IFERROR(__xludf.DUMMYFUNCTION("IFERROR( TEXTJOIN("" | "", TRUE, UNIQUE( FILTER( Movimientos_Inventario!G:G, TRIM(CLEAN(Movimientos_Inventario!C:C)) = TRIM(CLEAN(A90)), Movimientos_Inventario!G:G <> """" ) ) ), """")"),"") | G90: CARLOS SANCHEZ MEDELLIN | I90: =IF(H90=0,"AGOTADO",IF(H90<=10,"CASI AGOTADO","DISPONIBLE")) -> AGOTADO
A91: FL03211300 | B91: LEATRIS | C91: FLORES | F91: =IFERROR(__xludf.DUMMYFUNCTION("IFERROR( TEXTJOIN("" | "", TRUE, UNIQUE( FILTER( Movimientos_Inventario!G:G, TRIM(CLEAN(Movimientos_Inventario!C:C)) = TRIM(CLEAN(A91)), Movimientos_Inventario!G:G <> """" ) ) ), """")"),"") | G91: JUAN DAVID (AURA) BOGOTA | I91: =IF(H91=0,"AGOTADO",IF(H91<=10,"CASI AGOTADO","DISPONIBLE")) -> AGOTADO
A92: FL03301300 | B92: LIRIOS AMARILLO | C92: FLORES | E92: AMARILLO | F92: =IFERROR(__xludf.DUMMYFUNCTION("IFERROR( TEXTJOIN("" | "", TRUE, UNIQUE( FILTER( Movimientos_Inventario!G:G, TRIM(CLEAN(Movimientos_Inventario!C:C)) = TRIM(CLEAN(A92)), Movimientos_Inventario!G:G <> """" ) ) ), """")"),"") | G92: JUAN DAVID (AURA) BOGOTA | I92: =IF(H92=0,"AGOTADO",IF(H92<=10,"CASI AGOTADO","DISPONIBLE")) -> AGOTADO
A93: FL03306300 | B93: LIRIOS BLANCO | C93: FLORES | E93: BLANCO | F93: =IFERROR(__xludf.DUMMYFUNCTION("IFERROR( TEXTJOIN("" | "", TRUE, UNIQUE( FILTER( Movimientos_Inventario!G:G, TRIM(CLEAN(Movimientos_Inventario!C:C)) = TRIM(CLEAN(A93)), Movimientos_Inventario!G:G <> """" ) ) ), """")"),"") | G93: JUAN DAVID (AURA) BOGOTA | I93: =IF(H93=0,"AGOTADO",IF(H93<=10,"CASI AGOTADO","DISPONIBLE")) -> AGOTADO
A94: FL03309300 | B94: LIRIOS FUCSIA | C94: FLORES | E94: FUCSIA | F94: =IFERROR(__xludf.DUMMYFUNCTION("IFERROR( TEXTJOIN("" | "", TRUE, UNIQUE( FILTER( Movimientos_Inventario!G:G, TRIM(CLEAN(Movimientos_Inventario!C:C)) = TRIM(CLEAN(A94)), Movimientos_Inventario!G:G <> """" ) ) ), """")"),"") | G94: JUAN DAVID (AURA) BOGOTA | I94: =IF(H94=0,"AGOTADO",IF(H94<=10,"CASI AGOTADO","DISPONIBLE")) -> AGOTADO
A95: FL03312300 | B95: LIRIOS NARANJA | C95: FLORES | E95: NARANJA | F95: =IFERROR(__xludf.DUMMYFUNCTION("IFERROR( TEXTJOIN("" | "", TRUE, UNIQUE( FILTER( Movimientos_Inventario!G:G, TRIM(CLEAN(Movimientos_Inventario!C:C)) = TRIM(CLEAN(A95)), Movimientos_Inventario!G:G <> """" ) ) ), """")"),"") | G95: JUAN DAVID (AURA) BOGOTA | I95: =IF(H95=0,"AGOTADO",IF(H95<=10,"CASI AGOTADO","DISPONIBLE")) -> AGOTADO
A96: FL03315300 | B96: LIRIOS ROSADO | C96: FLORES | E96: ROSADO | F96: =IFERROR(__xludf.DUMMYFUNCTION("IFERROR( TEXTJOIN("" | "", TRUE, UNIQUE( FILTER( Movimientos_Inventario!G:G, TRIM(CLEAN(Movimientos_Inventario!C:C)) = TRIM(CLEAN(A96)), Movimientos_Inventario!G:G <> """" ) ) ), """")"),"") | G96: JUAN DAVID (AURA) BOGOTA | I96: =IF(H96=0,"AGOTADO",IF(H96<=10,"CASI AGOTADO","DISPONIBLE")) -> AGOTADO
A97: FL03401400 | B97: MARGARITA AMARILLA | C97: FLORES | E97: AMARILLA | F97: =IFERROR(__xludf.DUMMYFUNCTION("IFERROR( TEXTJOIN("" | "", TRUE, UNIQUE( FILTER( Movimientos_Inventario!G:G, TRIM(CLEAN(Movimientos_Inventario!C:C)) = TRIM(CLEAN(A97)), Movimientos_Inventario!G:G <> """" ) ) ), """")"),"") | G97: CARLOS SANCHEZ MEDELLIN | I97: =IF(H97=0,"AGOTADO",IF(H97<=10,"CASI AGOTADO","DISPONIBLE")) -> AGOTADO
A98: FL03406400 | B98: MARGARITA BLANCA | C98: FLORES | E98: BLANCA | F98: =IFERROR(__xludf.DUMMYFUNCTION("IFERROR( TEXTJOIN("" | "", TRUE, UNIQUE( FILTER( Movimientos_Inventario!G:G, TRIM(CLEAN(Movimientos_Inventario!C:C)) = TRIM(CLEAN(A98)), Movimientos_Inventario!G:G <> """" ) ) ), """")"),"") | G98: CARLOS SANCHEZ MEDELLIN | I98: =IF(H98=0,"AGOTADO",IF(H98<=10,"CASI AGOTADO","DISPONIBLE")) -> AGOTADO
A99: FL03410400 | B99: MARGARITA LILA | C99: FLORES | E99: LILA | F99: CATALOGO MUJER | G99: CARLOS SANCHEZ MEDELLIN | H99: 14 | I99: =IF(H99=0,"AGOTADO",IF(H99<=10,"CASI AGOTADO","DISPONIBLE")) -> DISPONIBLE
A100: FL03409400 | B100: MARGARITA FUCSIA | C100: FLORES | E100: FUCSIA | F100: =IFERROR(__xludf.DUMMYFUNCTION("IFERROR( TEXTJOIN("" | "", TRUE, UNIQUE( FILTER( Movimientos_Inventario!G:G, TRIM(CLEAN(Movimientos_Inventario!C:C)) = TRIM(CLEAN(A100)), Movimientos_Inventario!G:G <> """" ) ) ), """")"),"") | G100: CARLOS SANCHEZ MEDELLIN | I100: =IF(H100=0,"AGOTADO",IF(H100<=10,"CASI AGOTADO","DISPONIBLE")) -> AGOTADO
...

Sheet Movimientos_Inventario
A1: ID_MOVIMIENTO | B1: FECHA | C1: CODIGO | D1: CANTIDAD | E1: TIPO_MOVIMIENTO | F1: USUARIO | G1: OBSERVACION
A2: 1 | B2: 46062.917 | C2: 1 | D2: 2000 | E2: ENTRADA | F2: 34 | G2: #ERROR!
A3: 2 | B3: 46062.917 | C3: 1 | D3: 2000 | E3: SALIDA | F3: 34
A4: 3 | B4: 46062.918 | C4: 1 | D4: 2000 | E4: SALIDA | F4: 34
A5: 4 | B5: 46063.016 | C5: 1 | D5: 20 | E5: ENTRADA | F5: Sistema
A6: 5 | B6: 46063.024 | C6: 1 | D6: 20 | E6: ENTRADA | F6: Sistema
A7: 6 | B7: 46063.025 | C7: 1 | D7: 20 | E7: ENTRADA | F7: Sistema
A8: 7 | B8: 46063.026 | C8: 1 | D8: 20 | E8: ENTRADA | F8: Sistema
A9: 8 | B9: 46063.027 | C9: 1 | D9: 20 | E9: ENTRADA | F9: Sistema
A10: 9 | B10: 46063.033 | C10: 1 | D10: 20 | E10: ENTRADA | F10: Sistema
A11: 10 | B11: 46063.033 | C11: 1 | D11: 20 | E11: SALIDA | F11: Sistema
A12: 11 | B12: 46063.034 | C12: 1 | D12: 20 | E12: SALIDA | F12: Sistema
A13: 12 | B13: 46063.046 | C13: 1 | D13: 20 | E13: SALIDA | F13: Sistema
A14: 13 | B14: 46063.047 | C14: 1 | D14: 20 | E14: ENTRADA | F14: JAMES
A15: 14 | B15: 46063.048 | C15: 1 | D15: 20 | E15: ENTRADA | F15: JAMES
A16: 15 | B16: 46063.048 | C16: 1 | D16: 20 | E16: ENTRADA | F16: JAMES
A17: 16 | B17: 46063.051 | C17: 1 | D17: 20 | E17: ENTRADA | F17: JAMES | G17: no
A18: 17 | B18: 46065.789 | C18: 104514142100 | D18: 50 | E18: ENTRADA | F18: Paquete
A19: 18 | B19: 46066.433 | C19: 104514142200 | D19: 150 | E19: ENTRADA | F19: Paquete
A20: 19 | B20: 46066.433 | C20: 104514142200 | D20: 150 | E20: ENTRADA | F20: Paquete
A21: 20 | B21: 46066.441 | C21: 104514142200 | D21: 150 | E21: SALIDA | F21: Paquete
A22: 21 | B22: 46066.457 | C22: 104514142100 | D22: 3 | E22: SALIDA | F22: Paquete
A23: 22 | B23: 46066.459 | C23: 104514142200 | D23: 35 | E23: SALIDA | F23: Paquete | G23: san valentin
A24: 23 | B24: 46066.459 | C24: 104514142200 | D24: 35 | E24: SALIDA | F24: Paquete | G24: san valentin
A25: 24 | B25: 46066.461 | C25: 104514142200 | D25: 35 | E25: ENTRADA | F25: Paquete
A26: 25 | B26: 46066.462 | C26: 104514142200 | D26: 1 | E26: SALIDA | F26: Paquete
A27: 26 | B27: 46066.462 | C27: 104514142200 | D27: 1 | E27: SALIDA | F27: Paquete
A28: 27 | B28: 46066.462 | C28: 104514142200 | D28: 1 | E28: ENTRADA | F28: Paquete
A29: 28 | B29: 46066.477 | C29: 104514142200 | D29: 7 | E29: SALIDA | F29: Paquete
A30: 29 | B30: 46066.478 | C30: 104514142200 | D30: 6 | E30: SALIDA | F30: Paquete
A31: 30 | B31: 46066.498 | C31: 104514142200 | D31: 2 | E31: SALIDA | F31: Paquete
A32: 31 | B32: 46066.52 | C32: 104514142200 | D32: 6 | E32: SALIDA | F32: Paquete
A33: 32 | B33: 46066.52 | C33: 104514142100 | D33: 1 | E33: SALIDA | F33: Paquete
A34: 33 | B34: 46066.564 | C34: 104514142100 | D34: 8 | E34: SALIDA | F34: Paquete
A35: 34 | B35: 46066.674 | C35: 104514142200 | D35: 3 | E35: SALIDA | F35: Paquete
A36: 35 | B36: 46066.675 | C36: 104514142100 | D36: 7 | E36: SALIDA | F36: Paquete
... A64: 63 | B64: 46067.772 | C64: 104514142200 | D64: 1 | E64: SALIDA | F64: Paquete
A65: 64 | B65: 46087.476 | C65: FL00615300 | D65: 30 | E65: ENTRADA | F65: Paquete | G65: DIA DE LA MUJER | H65: =COUNTIF(Movimientos_Inventario!C:C,A15) -> 0
A66: 65 | B66: 46087.479 | C66: FL01519300 | D66: 8 | E66: ENTRADA | F66: Paquete | G66: CATALOGO MUJER | H66: =COUNTIF(Movimientos_Inventario!C:C,A16) -> 0
A67: 66 | B67: 46087.48 | C67: FL01706300 | D67: 8 | E67: ENTRADA | F67: Paquete | H67: =COUNTIF(Movimientos_Inventario!C:C,A17) -> 0
A68: 67 | B68: 46087.48 | C68: FL01709300 | D68: 5 | E68: ENTRADA | F68: Paquete | G68: CATALOGO DE LA MUJER | H68: =COUNTIF(Movimientos_Inventario!C:C,A18) -> 0
A69: 68 | B69: 46087.482 | C69: FL01715300 | D69: 40 | E69: ENTRADA | F69: Paquete | H69: =COUNTIF(Movimientos_Inventario!C:C,A19) -> 0
A70: 69 | B70: 46087.485 | C70: FL00215300 | D70: 22 | E70: ENTRADA | F70: Paquete | G70: CATALOGO MUJER | H70: =COUNTIF(Movimientos_Inventario!C:C,A20) -> 0
A71: 70 | B71: 46087.485 | C71: FL00110300 | D71: 12 | E71: ENTRADA | F71: Paquete | G71: CATALAGO MUJER | H71: =COUNTIF(Movimientos_Inventario!C:C,A21) -> 0
A72: 71 | B72: 46087.486 | C72: FL00206300 | D72: 5 | E72: ENTRADA | F72: Paquete | G72: CATALOGO MUJER | H72: =COUNTIF(Movimientos_Inventario!C:C,A22) -> 0
A73: 72 | B73: 46087.489 | C73: FL03006000 | D73: 8 | E73: ENTRADA | F73: Paquete | G73: CATALOGO MUJER | H73: =COUNTIF(Movimientos_Inventario!C:C,A23) -> 0
A74: 73 | B74: 46087.49 | C74: FL04006300 | D74: 3 | E74: ENTRADA | F74: Paquete | G74: CATALOGO MUJER
A75: 74 | B75: 46087.491 | C75: FL02215300 | D75: 3 | E75: ENTRADA | F75: Paquete | G75: CATALOGO MUJER
A76: 75 | B76: 46087.491 | C76: FL00917300 | D76: 3 | E76: ENTRADA | F76: Paquete | G76: CATALOGO MUJER
A77: 76 | B77: 46087.493 | C77: FO1705FIL | D77: 30 | E77: ENTRADA | F77: Paquete | G77: CATALOGO MUJER
A78: 77 | B78: 46087.493 | C78: FO2417FOL | D78: 30 | E78: ENTRADA | F78: Paquete | G78: CATALOGO MUJER
A79: 78 | B79: 46087.493 | C79: FO1917FOL | D79: 50 | E79: ENTRADA | F79: Paquete | G79: CATALOGO MUJER
A80: 79 | B80: 46087.494 | C80: FL02915300 | D80: 2 | E80: ENTRADA | F80: Paquete | G80: CATALOGO MUJER
A81: 80 | B81: 46087.495 | C81: FL01515300 | D81: 30 | E81: ENTRADA | F81: Paquete | G81: CATALOGO MUJER
A82: 81 | B82: 46087.496 | C82: FL01509300 | D82: 15 | E82: ENTRADA | F82: Paquete | G82: CATALOGO MUJER
A83: 82 | B83: 46087.496 | C83: FL01701300 | D83: 6 | E83: ENTRADA | F83: Paquete | G83: CATALOGO MUJER
A84: 83 | B84: 46087.499 | C84: FL04514141100 | D84: 25 | E84: ENTRADA | F84: Paquete
A85: 84 | B85: 46087.5 | C85: FL04515151100 | D85: 15 | E85: ENTRADA | F85: Paquete | G85: CATALOGO MUJER
A86: 85 | B86: 46087.501 | C86: FL04509000200 | D86: 13 | E86: ENTRADA | F86: Paquete | G86: CATALOGO MUJER
A87: 86 | B87: 46087.503 | C87: FL04610300 | D87: 4 | E87: ENTRADA | F87: Paquete | G87: CATALOGO MUJER
A88: 87 | B88: 46087.503 | C88: FL04615300 | D88: 5 | E88: ENTRADA | F88: Paquete | G88: CATALOGO MUJER
A89: 88 | B89: 46087.504 | C89: FL04410300 | D89: 8 | E89: ENTRADA | F89: Paquete | G89: CATALOGO MUJER
A90: 89 | B90: 46087.507 | C90: FL04417300 | D90: 3 | E90: ENTRADA | F90: Paquete | G90: CATALOGO MUJER
A91: 90 | B91: 46087.508 | C91: FL01015300 | D91: 2 | E91: ENTRADA | F91: Paquete | G91: CATALOGO MUJER
A92: 91 | B92: 46088.461 | C92: FL01701300 | D92: 1 | E92: SALIDA | F92: Paquete
A93: 92 | B93: 46088.461 | C93: FL03006000 | D93: 1 | E93: SALIDA | F93: Paquete
A94: 93 | B94: 46088.462 | C94: FL01015300 | D94: 1 | E94: SALIDA | F94: Paquete
A95: 94 | B95: 46088.462 | C95: FL00917300 | D95: 1 | E95: SALIDA | F95: Docena
A96: 95 | B96: 46088.473 | C96: FL04006300 | D96: 1 | E96: SALIDA | F96: Paquete
A97: 96 | B97: 46088.474 | C97: FO1917FOL | D97: 1 | E97: SALIDA | F97: Paquete
A98: 97 | B98: 46088.48 | C98: FO2217MON | D98: 1 | E98: SALIDA | F98: Paquete
A99: 98 | B99: 46088.48 | C99: FO1211FIL | D99: 1 | E99: SALIDA | F99: Paquete
A100: 99 | B100: 46088.481 | C100: FL04515151100 | D100: 1 | E100: SALIDA | F100: Paquete
A101: 100 | B101: 46088.513 | C101: FL04510000200 | D101: 1 | E101: SALIDA | F101: Paquete
A102: 101 | B102: 46088.513 | C102: FL04510000200 | D102: 1 | E102: SALIDA | F102: Paquete
A103: 102 | B103: 46088.515 | C103: FL04509000200 | D103: 13 | E103: SALIDA | F103: Paquete
A104: 103 | B104: 46088.515 | C104: FL04509000100 | D104: 12 | E104: ENTRADA | F104: Paquete | G104: CATALOGO MUJER
